Workbook
Name x: #N/A

Sheet Summary
A1: BRDB LAND — FEASIBILITY STUDY SUMMARY | Named Ranges Registry
A2: All values RM | Col D (live values) reads directly via named ranges | Col F = ExcelJS getValue() path for Nuxt dashboard
A3: Feasibility Study | B3: Named Range | C3: Cell Ref | D3: Live Value | E3: Description | F3: Nuxt ExcelJS path
A6: 2 | B6: DevLandArea_Acres | C6: ='Feasibility Study'!#REF! -> #REF! | D6: =DevLandArea_Acres -> #NAME? | E6: Total dev land (acres) | F6: summary.devLandAcres
A7: 3 | B7: TotalPhasesLandArea_Acres | C7: ='Feasibility Study'!AY10 -> 0
A8: 4 | B8: TotalPhasesLandArea_Sqft | C8: ='Feasibility Study'!AY12 -> 0
A9: 5 | B9: TotalUnits_AllPhases | C9: ='Feasibility Study'!AY13 -> 0 | D9: =TotalUnits_AllPhases -> #NAME? | E9: Total units — all phases | F9: summary.totalUnits | AY9: Phase 3a
A10: 6 | B10: TotalNFA_AllPhases_Sqft | C10: ='Feasibility Study'!AY17 -> 0 | D10: =TotalNFA_AllPhases_Sqft -> #NAME? | E10: Total NFA — all phases (sqft) | F10: summary.totalNFASqft
A11: 7 | B11: TotalGFA_ExcludeCP_Sqft | C11: ='Feasibility Study'!AY16 -> 0 | D11: =TotalGFA_ExcludeCP_Sqft -> #NAME? | E11: Total GFA excl carpark (sqft) | F11: summary.totalGFASqft
A12: GDV WATERFALL
A13: 8 | B13: GDV_Total | C13: ='Feasibility Study'!AY69 | D13: =GDV_Total -> #NAME? | E13: Gross Development Value (RM) | F13: gdv.total
A14: 9 | B14: GDV_GrossSellingPSF | C14: ='Feasibility Study'!AY70 | D14: =GDV_GrossSellingPSF -> #NAME? | E14: GDV gross selling price psf (RM) | F14: gdv.grossPSF
A15: 10 | B15: BumiDiscount_Total | C15: ='Feasibility Study'!AY72 -> 0 | D15: =BumiDiscount_Total -> #NAME? | E15: Less: Bumiputera Discount (RM) | F15: gdv.bumiDiscount
A16: 11 | B16: BumiPenalty_Total | C16: ='Feasibility Study'!AY73 -> 0 | D16: =BumiPenalty_Total -> #NAME? | E16: Less: Bumiputera Penalty (RM) | F16: gdv.bumiPenalty
A17: 12 | B17: LegalFeesSelling_Total | C17: ='Feasibility Study'!AY74 -> 0 | D17: =LegalFeesSelling_Total -> #NAME? | E17: Less: Legal fees SPA (RM) | F17: gdv.legalFees
A18: 13 | B18: EarlyBirdDiscount_Total | C18: ='Feasibility Study'!AY75 | D18: =EarlyBirdDiscount_Total -> #NAME? | E18: Less: Early Bird Discount 9% (RM) | F18: gdv.earlyBird
A19: 14 | B19: NDV_Total | C19: ='Feasibility Study'!AY79 | D19: =NDV_Total -> #NAME? | E19: Net Development Value (RM) | F19: ndv.total
A20: 15 | B20: NDV_NetSellingPSF | C20: ='Feasibility Study'!AY83 -> #DIV/0! | D20: =NDV_NetSellingPSF -> #NAME? | E20: NDV net selling price psf (RM) | F20: ndv.netPSF
A21: LAND & RELATED COSTS
A22: 16 | B22: LandRelatedCosts_Total | C22: ='Feasibility Study'!AY87 -> #DIV/0! | D22: =LandRelatedCosts_Total -> #NAME? | E22: Sec 5 — Land & related total (RM) | F22: gdc.land.total
A23: 17 | B23: LandCost_Total | C23: ='Feasibility Study'!AY88 -> 0 | D23: =LandCost_Total -> #NAME? | E23: 5.1 Land cost (RM) | F23: gdc.land.landCost
A24: 18 | B24: LandConversionPremium_Total | C24: ='Feasibility Study'!AY89 -> 0 | D24: =LandConversionPremium_Total -> #NAME? | E24: 5.2 Land conversion premium (RM) | F24: gdc.land.conversionPremium
A25: 19 | B25: QuitRent_Total | C25: ='Feasibility Study'!AY90 -> 0 | D25: =QuitRent_Total -> #NAME? | E25: 5.3 Quit rent (RM) | F25: gdc.land.quitRent
A26: 20 | B26: Assessment_Total | C26: ='Feasibility Study'!AY91 -> 0 | D26: =Assessment_Total -> #NAME? | E26: 5.4 Assessment (RM) | F26: gdc.land.assessment
A27: 21 | B27: StampDuty_Total | C27: ='Feasibility Study'!AY92 -> #DIV/0! | D27: =StampDuty_Total -> #NAME? | E27: 5.5 Stamp duty on land (RM) | F27: gdc.land.stampDuty
A28: 22 | B28: ValuationFee_Total | C28: ='Feasibility Study'!AY94 -> 0 | D28: =ValuationFee_Total -> #NAME? | E28: 5.6 Valuation fee (RM) | F28: gdc.land.valuation
A29: 23 | B29: LandAmalgamation_Total | C29: ='Feasibility Study'!AY95 -> 0 | D29: =LandAmalgamation_Total -> #NAME? | E29: 5.7 Land amalgamation fee (RM) | F29: gdc.land.amalgamation
A30: GROSS CONSTRUCTION COST (GCC)
A31: 24 | B31: GCC_Total | C31: ='Feasibility Study'!AY99 -> #DIV/0! | D31: =GCC_Total -> #NAME? | E31: Sec 6 — GCC total (RM) | F31: gdc.gcc.total
A32: 25 | B32: GCC_PercentOfNDV | C32: ='Feasibility Study'!AY100 -> #DIV/0! | D32: =GCC_PercentOfNDV -> #NAME? | E32: GCC % of NDV | F32: gdc.gcc.pctOfNDV
A33: 26 | B33: GCC_ConstructionCostPSF | C33: ='Feasibility Study'!AY101 -> #DIV/0! | D33: =GCC_ConstructionCostPSF -> #NAME? | E33: GCC construction cost psf (RM) | F33: gdc.gcc.costPSF
A34: 27 | B34: SubstructurePiling_Total | C34: ='Feasibility Study'!AY102 -> 0 | D34: =SubstructurePiling_Total -> #NAME? | E34: Piling / substructure (RM) | F34: gdc.gcc.piling
A35: 28 | B35: BuildingWork_Resi_Total | C35: ='Feasibility Study'!AY105 -> #DIV/0! | D35: =BuildingWork_Resi_Total -> #NAME? | E35: Building works resi (RM) | F35: gdc.gcc.buildingResi
A36: 29 | B36: BuildingWork_Afford_Total | C36: ='Feasibility Study'!AY106 -> 0 | D36: =BuildingWork_Afford_Total -> #NAME? | E36: Building works affordable (RM) | F36: gdc.gcc.buildingAfford
A37: 30 | B37: BuildingWork_Comm_Total | C37: ='Feasibility Study'!AY107 -> 0 | D37: =BuildingWork_Comm_Total -> #NAME? | E37: Building works commercial (RM) | F37: gdc.gcc.buildingComm
A38: 31 | B38: KitchenCabinet_Total | C38: ='Feasibility Study'!AY109 -> #VALUE! | D38: =KitchenCabinet_Total -> #NAME? | E38: Kitchen cabinet & appliances (RM) | F38: gdc.gcc.kitchenCabinet
A39: 32 | B39: IDWorks_Unit_Total | C39: ='Feasibility Study'!AY110 -> #VALUE! | D39: =IDWorks_Unit_Total -> #NAME? | E39: ID works — unit fit-out (RM) | F39: gdc.gcc.idWorks
A40: 33 | B40: Earthworks_Total | C40: ='Feasibility Study'!AY131 -> #VALUE! | D40: =Earthworks_Total -> #NAME? | E40: Earthworks & infrastructure (RM) | F40: gdc.gcc.earthworks
A41: 34 | B41: Landscape_Total | C41: ='Feasibility Study'!AY133 -> 0 | D41: =Landscape_Total -> #NAME? | E41: Landscape (RM) | F41: gdc.gcc.landscape
A42: 35 | B42: Clubhouse_Total | C42: ='Feasibility Study'!AY135 -> #DIV/0! | D42: =Clubhouse_Total -> #NAME? | E42: Clubhouse / show units (RM) | F42: gdc.gcc.clubhouse
A43: 36 | B43: Preliminaries_Total | C43: ='Feasibility Study'!AY138 -> 0 | D43: =Preliminaries_Total -> #NAME? | E43: Preliminaries 8% (RM) | F43: gdc.gcc.prelim
A44: 37 | B44: Contingency_Total | C44: ='Feasibility Study'!AY139 -> 0 | D44: =Contingency_Total -> #NAME? | E44: Contingency 5% (RM) | F44: gdc.gcc.contingency
A45: 38 | B45: ContractStamping_Total | C45: ='Feasibility Study'!AY141 -> 0 | D45: =ContractStamping_Total -> #NAME? | E45: Contract stamping 0.1% (RM) | F45: gdc.gcc.contractStamp
A46: STRATA, PLANNING & AUTHORITIES
A47: 39 | B47: StrataSurveyFees_Total | C47: ='Feasibility Study'!AY142 -> 0 | D47: =StrataSurveyFees_Total -> #NAME? | E47: Sec 7 — Strata & survey fees (RM) | F47: gdc.strata.total
A48: 40 | B48: PlanningBPFees_Total | C48: ='Feasibility Study'!AY145 -> #VALUE! | D48: =PlanningBPFees_Total -> #NAME? | E48: Sec 8 — Planning & BP fees (RM) | F48: gdc.planning.total
A49: 41 | B49: ContribAuthorities_Total | C49: ='Feasibility Study'!AY147 -> 0 | D49: =ContribAuthorities_Total -> #NAME? | E49: Sec 9 — Authority contribs total (RM) | F49: gdc.authorities.total
A50: 42 | B50: DevCharges_Total | C50: ='Feasibility Study'!AY149 -> 0 | D50: =DevCharges_Total -> #NAME? | E50: Dev charges 1% NDV (RM) | F50: gdc.authorities.devCharges
A51: 43 | B51: SYABAS_Total | C51: ='Feasibility Study'!AY150 -> 0 | D51: =SYABAS_Total -> #NAME? | E51: SYABAS 0.25% NDV (RM) | F51: gdc.authorities.syabas
A52: 44 | B52: IWK_JPS_Total | C52: ='Feasibility Study'!AY151 -> 0 | D52: =IWK_JPS_Total -> #NAME? | E52: IWK & JPS 1% NDV (RM) | F52: gdc.authorities.iwkJps
A53: 45 | B53: TNB_Total | C53: ='Feasibility Study'!AY152 -> 0 | D53: =TNB_Total -> #NAME? | E53: TNB per unit (RM) | F53: gdc.authorities.tnb
A54: 46 | B54: Telekom_Total | C54: ='Feasibility Study'!AY153 -> 0 | D54: =Telekom_Total -> #NAME? | E54: Telekom / UNIFI (RM) | F54: gdc.authorities.telekom
A55: 47 | B55: RoadDrainage_Total | C55: ='Feasibility Study'!AY154 -> 0 | D55: =RoadDrainage_Total -> #NAME? | E55: Road & drainage (RM) | F55: gdc.authorities.roadDrain
A56: 48 | B56: ISF_Total | C56: ='Feasibility Study'!AY156 -> 0 | D56: =ISF_Total -> #NAME? | E56: ISF (RM) | F56: gdc.authorities.isf
A57: 49 | B57: GBI_GreenRE_Total | C57: ='Feasibility Study'!AY157 -> 0 | D57: =GBI_GreenRE_Total -> #NAME? | E57: GBI / Green RE cert (RM) | F57: gdc.authorities.gbi
A58: 50 | B58: HoardingFee_Total | C58: ='Feasibility Study'!AY158 -> 0 | D58: =HoardingFee_Total -> #NAME? | E58: Hoarding permit fee (RM) | F58: gdc.authorities.hoarding
A59: 51 | B59: COBDeposit_Total | C59: ='Feasibility Study'!AY159 -> 0 | D59: =COBDeposit_Total -> #NAME? | E59: COB deposit (RM) | F59: gdc.authorities.cob
A60: CONSULTANCY, OTHER & SITE ADMIN
A61: 52 | B61: ConsultancyFees_Total | C61: ='Feasibility Study'!AY163 -> #DIV/0! | D61: =ConsultancyFees_Total -> #NAME? | E61: Sec 10 — Consultancy fees (RM) | F61: gdc.consultancy.total
A62: 53 | B62: OtherConstructionCost_Total | C62: ='Feasibility Study'!AY166 -> #DIV/0! | D62: =OtherConstructionCost_Total -> #NAME? | E62: Sec 11 — Other construction cost (RM) | F62: gdc.otherCost.total
A63: 54 | B63: SoilInvestigation_Total | C63: ='Feasibility Study'!AY167 -> 0 | D63: =SoilInvestigation_Total -> #NAME? | E63: Soil investigation (RM) | F63: gdc.otherCost.soilInvest
A64: 55 | B64: SiteAdmin_Total | C64: ='Feasibility Study'!AY173 -> 0 | D64: =SiteAdmin_Total -> #NAME? | E64: Sec 12 — Site admin 2% GCC (RM) | F64: gdc.siteAdmin.total
A65: GDC SUBTOTALS
A66: 56 | B66: GDC_BeforeMarketing | C66: ='Feasibility Study'!AY178 | D66: =GDC_BeforeMarketing -> #NAME? | E66: GDC before S&M (RM) | F66: gdc.subtotals.beforeMarketing
A67: 57 | B67: GDC_BeforeLandCost | C67: ='Feasibility Study'!AY180 -> 0 | D67: =GDC_BeforeLandCost -> #NAME? | E67: GDC before land cost (RM) | F67: gdc.subtotals.beforeLand
A68: MARKETING & SELLING EXPENSES
A69: 58 | B69: SandM_Total | C69: ='Feasibility Study'!AY182 -> #DIV/0! | D69: =SandM_Total -> #NAME? | E69: Sec 15 — S&M expenses total (RM) | F69: gdc.sm.total
A70: 59 | B70: MarketingExpenses_Total | C70: ='Feasibility Study'!AY184 -> #DIV/0! | D70: =MarketingExpenses_Total -> #NAME? | E70: General marketing expenses (RM) | F70: gdc.sm.generalMarketing
A71: 60 | B71: Commission_Internal_Total | C71: ='Feasibility Study'!AY194 -> 0 | D71: =Commission_Internal_Total -> #NAME? | E71: Commission — internal (80%×4%) (RM) | F71: gdc.sm.commInternal
A72: 61 | B72: Commission_External_Total | C72: ='Feasibility Study'!AY195 | D72: =Commission_External_Total -> #NAME? | E72: Commission — external (100%×5%) (RM) | F72: gdc.sm.commExternal
A73: 62 | B73: RepeatBuyers_Total | C73: ='Feasibility Study'!AY196 | D73: =RepeatBuyers_Total -> #NAME? | E73: Repeat buyers / BGB rebate (RM) | F73: gdc.sm.bgb
A74: 63 | B74: FreeSPA_Total | C74: ='Feasibility Study'!AY197 | D74: =FreeSPA_Total -> #NAME? | E74: Free SPA & loan legal fees (RM) | F74: gdc.sm.freeSPA
A75: 64 | B75: AdditionalSalesPkg_Total | C75: ='Feasibility Study'!AY198 -> 0 | D75: =AdditionalSalesPkg_Total -> #NAME? | E75: Additional sales package (RM) | F75: gdc.sm.salesPkg
A76: 65 | B76: StaffDiscount_Total | C76: ='Feasibility Study'!AY199 -> 0 | D76: =StaffDiscount_Total -> #NAME? | E76: Staff / director discount (RM) | F76: gdc.sm.staffDisc
A77: 66 | B77: MaintenanceSinking_Total | C77: ='Feasibility Study'!AY200 -> 0 | D77: =MaintenanceSinking_Total -> #NAME? | E77: Maintenance & sinking fund (RM) | F77: gdc.sm.maintenance
A78: FINANCIAL CHARGES & GDC AFTER FINANCE
A79: 67 | B79: GDC_AfterMarketing | C79: ='Feasibility Study'!AY202 -> 0 | D79: =GDC_AfterMarketing -> #NAME? | E79: GDC after S&M, before finance (RM) | F79: gdc.subtotals.afterMarketing
A80: 68 | B80: GDP_BeforeFinance | C80: ='Feasibility Study'!AY205 -> 0 | D80: =GDP_BeforeFinance -> #NAME? | E80: GDP before financial charges (RM) | F80: gdp.beforeFinance
A81: 69 | B81: FinancialCharges_Total | C81: ='Feasibility Study'!AY208 -> 0 | D81: =FinancialCharges_Total -> #NAME? | E81: Sec 16 — Financial charges total (RM) | F81: gdc.finance.total
A82: 70 | B82: LandLoanInterest_Total | C82: ='Feasibility Study'!AY209 -> 0 | D82: =LandLoanInterest_Total -> #NAME? | E82: Land loan interest (RM) | F82: gdc.finance.landInterest
A83: 71 | B83: ConstructionLoanInterest | C83: ='Feasibility Study'!AY210 -> 0 | D83: =ConstructionLoanInterest -> #NAME? | E83: Construction loan interest (RM) | F83: gdc.finance.constInterest
A84: 72 | B84: GDC_AfterFinance | C84: ='Feasibility Study'!AY212 -> 0 | D84: =GDC_AfterFinance -> #NAME? | E84: GDC after financial charges (RM) | F84: gdc.subtotals.afterFinance
A85: 73 | B85: GDP_AfterFinance | C85: ='Feasibility Study'!AY215 -> 0 | D85: =GDP_AfterFinance -> #NAME? | E85: GDP after financial charges (RM) | F85: gdp.afterFinance
A86: OVERHEADS
A87: 74 | B87: ProjectDeptOverhead_Total | C87: ='Feasibility Study'!AY218 -> 0 | D87: =ProjectDeptOverhead_Total -> #NAME? | E87: Project dept overhead 1.4% NDV (RM) | F87: gdc.overhead.projectDept
A88: 75 | B88: HeadOfficeOverhead_Total | C88: ='Feasibility Study'!AY219 -> #DIV/0! | D88: =HeadOfficeOverhead_Total -> #NAME? | E88: Head office overhead 3% NDV (RM) | F88: gdc.overhead.headOffice
A89: 76 | B89: MktgDeptOverhead_Total | C89: ='Feasibility Study'!AY220 -> 0 | D89: =MktgDeptOverhead_Total -> #NAME? | E89: Mktg dept overhead 0.5% NDV (RM) | F89: gdc.overhead.mktgDept
A90: 77 | B90: CorporateOverhead_Total | C90: ='Feasibility Study'!AY221 -> 0 | D90: =CorporateOverhead_Total -> #NAME? | E90: Corporate overhead 1% NDV (RM) | F90: gdc.overhead.corporate
A91: NDP & RETURN KPIs
A92: 78 | B92: NDP_Total | C92: ='Feasibility Study'!AY225 -> 0 | D92: =NDP_Total -> #NAME? | E92: Net Development Profit (RM) | F92: kpi.ndpTotal
A93: 79 | B93: NDP_PctOfNDV | C93: ='Feasibility Study'!AY226 -> #DIV/0! | D93: =NDP_PctOfNDV -> #NAME? | E93: NDP margin % on NDV | F93: kpi.ndpPctNDV
A94: 80 | B94: NDP_PctOfGDV | C94: ='Feasibility Study'!AY227 | D94: =NDP_PctOfGDV -> #NAME? | E94: NDP margin % on GDV | F94: kpi.ndpPctGDV
A95: 81 | B95: ProfitLandRatio | C95: ='Feasibility Study'!AY228 -> 0 | D95: =ProfitLandRatio -> #NAME? | E95: Profit / Land Ratio (NDP ÷ land cost) | F95: kpi.profitLandRatio
A97: ExcelJS PARSER — server/api/[dealId]/financials.get.ts
A98: // server/api/[dealId]/financials.get.ts import ExcelJS from 'exceljs' export default defineEventHandler(async (event) => { const { dealId } = getRouterParams(event) const wb = new ExcelJS.Workbook() await wb.xlsx.readFile(`./data/${dealId}/financials.xlsx`) const getValue = (name: string): number | null => { const defined = wb.definedNames.getNames() const match = defined.find(n => n.name === name) if (!match) return null const [sheet, cell] = match.value.replace(/'/g, '').split('!') const ws = wb.getWorksheet(sheet) const raw = ws?.getCell(cell.replace(/\$/g, ''))?.value if (raw === null || raw === undefined) return null if (typeof raw === 'object' && 'result' in raw) return raw.result as number return typeof raw === 'number' ? raw : null } return { summary: { originalLandAcres: getValue('OriginalLandArea_Acres'), devLandAcres: getValue('DevLandArea_Acres'), totalLandAcres: getValue('TotalPhasesLandArea_Acres'), totalLandSqft: getValue('TotalPhasesLandArea_Sqft'), totalUnits: getValue('TotalUnits_AllPhases'), totalNFASqft: getValue('TotalNFA_AllPhases_Sqft'), }, gdv: { total: getValue('GDV_Total'), grossPSF: getValue('GDV_GrossSellingPSF'), bumiDiscount: getValue('BumiDiscount_Total'), bumiPenalty: getValue('BumiPenalty_Total'), earlyBird: getValue('EarlyBirdDiscount_Total'), }, ndv: { total: getValue('NDV_Total'), netPSF: getValue('NDV_NetSellingPSF'), }, gdc: { land: { total: getValue('LandRelatedCosts_Total'), landCost: getValue('LandCost_Total'), stampDuty: getValue('StampDuty_Total'), valuation: getValue('ValuationFee_Total'), }, gcc: { total: getValue('GCC_Total'), pctOfNDV: getValue('GCC_PercentOfNDV'), costPSF: getValue('GCC_ConstructionCostPSF'), piling: getValue('SubstructurePiling_Total'), buildingResi: getValue('BuildingWork_Resi_Total'), earthworks: getValue('Earthworks_Total'), prelim: getValue('Preliminaries_Total'), contingency: getValue('Contingency_Total'), }, authorities: { total: getValue('ContribAuthorities_Total'), telekom: getValue('Telekom_Total'), gbi: getValue('GBI_GreenRE_Total'), }, sm: { total: getValue('SandM_Total'), commission: getValue('Commission_Internal_Total'), bgb: getValue('RepeatBuyers_Total'), }, finance: { total: getValue('FinancialCharges_Total'), landInterest: getValue('LandLoanInterest_Total'), constInterest: getValue('ConstructionLoanInterest'), }, afterFinance: getValue('GDC_AfterFinance'), }, kpi: { ndpTotal: getValue('NDP_Total'), ndpPctNDV: getValue('NDP_PctOfNDV'), ndpPctGDV: getValue('NDP_PctOfGDV'), profitLandRatio: getValue('ProfitLandRatio'), }, } })

Sheet Feasibility Study
A1: BRDB LAND
A2: OVERALL FEASIBILITY STUDY
A3: Feasibility Study
AW4: Phase 2j
G5: Acre to Sqm | H5: 4046.87
G6: Acre to Sqft | H6: 43560 | I6: Phase 1a | K6: Phase 1b | M6: Phase 1c | O6: Phase 1d | Q6: Phase 1e | S6: Phase 1f | W6: Phase 1g | Y6: Phase 1h | AC6: Phase 2a | AE6: Phase 2B | AG6: Phase 2c | AI6: Phase 2d | AK6: Phase 2e | AM6: Phase 2f | AO6: Phase 2g1 | AQ6: Phase 2g2 | AS6: Phase 2g3 | AU6: Phase 2h
A8: LAUNCH DATE | I8: 42095 | K8: 42401 | M8: 45017 | O8: TBC | Q8: TBC | S8: 46631 | W8: 46935 | Y8: 11171 | AC8: 44044 | AE8: 44835 | AG8: 45931 | AI8: 46419 | AK8: 46419 | AM8: TBC | AO8: TBC | AQ8: TBC | AS8: TBC | AU8: TBC | AW8: TBC | AY8: TOTAL
C10: Phases Land Area (acres) => | I10: 0 | K10: 0 | M10: 0 | O10: 0 | Q10: 0 | S10: 0 | W10: 0 | Y10: 0 | AC10: 0 | AE10: 0 | AG10: 0 | AI10: 0 | AK10: 0 | AM10: 0 | AO10: 0 | AQ10: 0 | AS10: 0 | AU10: 0 | AW10: 0 | AY10: =SUM(I10:AW10) -> 0
C11: Phases Land Area (square meter) => | I11: =I10*$H$5 -> 0 | K11: =K10*$H$5 -> 0 | M11: =M10*$H$5 -> 0 | O11: =O10*$H$5 -> 0 | Q11: =Q10*$H$5 -> 0 | S11: 0 | W11: =W10*$H$5 -> 0 | Y11: =Y10*$H$5 -> 0 | AC11: =AC10*$H$5 -> 0 | AE11: =AE10*$H$5 -> 0 | AG11: =AG10*$H$5 -> 0 | AI11: =AI10*$H$5 -> 0 | AK11: =AK10*$H$5 -> 0 | AM11: =AM10*$H$5 -> 0 | AO11: =AO10*$H$5 -> 0 | AQ11: =AQ10*$H$5 -> 0 | AS11: =AS10*$H$5 -> 0 | AU11: =AU10*$H$5 -> 0 | AW11: =AW10*$H$5 -> 0 | AY11: =SUM(I11:AW11) -> 0
C12: Phases Land Area (square feet) => | I12: =I10*$H$6 -> 0 | K12: =K10*$H$6 -> 0 | M12: =M10*$H$6 -> 0 | O12: =O10*$H$6 -> 0 | Q12: =Q10*$H$6 -> 0 | S12: =S10*$H$6 -> 0 | W12: =W10*$H$6 -> 0 | Y12: =Y10*$H$6 -> 0 | AC12: =AC10*$H$6 -> 0 | AE12: =AE10*$H$6 -> 0 | AG12: =AG10*$H$6 -> 0 | AI12: =AI10*$H$6 -> 0 | AK12: =AK10*$H$6 -> 0 | AM12: =AM10*$H$6 -> 0 | AO12: =AO10*$H$6 -> 0 | AQ12: =AQ10*$H$6 -> 0 | AS12: =AS10*$H$6 -> 0 | AU12: =AU10*$H$6 -> 0 | AW12: =AW10*$H$6 -> 0 | AY12: =SUM(I12:AW12) -> 0
C13: No of units in the Phase => | I13: =E31 -> 0 | K13: =E44 -> 0 | M13: =E45 -> 0 | O13: =E46 -> 0 | Q13: 0 | S13: =E49+E50 -> 0 | W13: =E51 -> 0 | Y13: =E52 -> 0 | AC13: =E53 -> 0 | AE13: =E54 -> 0 | AG13: =E55 -> 0 | AI13: =E56 -> 0 | AK13: =E57 -> 0 | AM13: =E58 -> 0 | AO13: =E59 -> 0 | AQ13: =E60 -> 0 | AS13: 0 | AU13: =E62 -> 0 | AW13: =E63 -> 0 | AY13: =SUM(I13:AW13) -> 0
C14: Carpark Bays (Required — authority minimum) => | I14: 0
C15: Construction Floor Area include Carpark (CFA) =>
C16: Gross Floor Area exclude Carpark (GFA) =>
C17: Saleable area in the Phase (NFA) => | I17: 0 | K17: =K13*D44 -> 0 | M17: =M13*D45 -> 0 | O17: =O13*D46 -> 0 | Q17: =Q13*D47 -> 0 | S17: =(E49*D49)+(D50*E50) -> 0 | W17: =W13*D51 -> 0 | Y17: =Y13*D52 -> 0 | AC17: =AC13*D53 -> 0 | AE17: =AE13*D54 -> 0 | AG17: =AG13*D55 -> 0 | AI17: =AI13*D56 -> 0 | AK17: =AK13*D57 -> 0 | AM17: =AM13*D58 -> 0 | AO17: =AO13*D59 -> 0 | AQ17: =AQ13*D60 -> 0 | AS17: =AS13*D61 -> 0 | AU17: =AU13*D62 -> 0 | AW17: =AW13*D63 -> 0 | AY17: =SUM(I17:AW17) -> 0
C18: Highrise Design Efficiency (NSA ÷ CFA) =>
C19: Highrise Design Efficiency (NSA ÷ GFA) =>
C20: Plot Ratio / Density =>
I21: 0 | K21: 0 | M21: 0 | O21: 0 | Q21: 0 | S21: 0 | W21: 0 | Y21: 0 | AC21: 0 | AE21: 0 | AG21: 0 | AI21: 0 | AK21: 0 | AM21: 0 | AO21: 0 | AQ21: 0 | AS21: 0 | AU21: 0 | AW21: 0 | AY21: =SUM(I21:AW21) -> 0
I22: 0 | K22: 0 | M22: 0 | O22: 0 | Q22: 0 | S22: 0 | W22: 0 | Y22: 0 | AC22: 0 | AE22: 0 | AG22: 0 | AI22: 0 | AK22: 0 | AM22: 0 | AO22: 0 | AQ22: 0 | AS22: 0 | AU22: 0 | AW22: 0 | AY22: =SUM(I22:AW22) -> 0
I23: =IFERROR(I17/I22,0) -> 0 | K23: =IFERROR(K17/K22,0) -> 0 | M23: =IFERROR(M17/M22,0) -> 0 | O23: =IFERROR(O17/O22,0) -> 0 | Q23: =IFERROR(Q17/Q22,0) -> 0 | S23: =IFERROR(S17/S22,0) -> 0 | W23: =IFERROR(W17/W22,0) -> 0 | Y23: =IFERROR(Y17/Y22,0) -> 0 | AC23: =IFERROR(AC17/AC22,0) -> 0 | AE23: =IFERROR(AE17/AE22,0) -> 0 | AG23: =IFERROR(AG17/AG22,0) -> 0 | AI23: =IFERROR(AI17/AI22,0) -> 0 | AK23: =IFERROR(AK17/AK22,0) -> 0 | AM23: =IFERROR(AM17/AM22,0) -> 0 | AO23: =IFERROR(AO17/AO22,0) -> 0 | AQ23: =IFERROR(AQ17/AQ22,0) -> 0 | AS23: =IFERROR(AS17/AS22,0) -> 0 | AU23: =IFERROR(AU17/AU22,0) -> 0 | AW23: =IFERROR(AW17/AW22,0) -> 0 | AY23: =IFERROR(AY17/AY22,0) -> 0
I24: 0 | K24: 0 | M24: 0 | O24: 0 | Q24: 0 | S24: 0 | W24: 0 | Y24: 0 | AC24: 0 | AE24: 0 | AG24: 0 | AI24: 0 | AK24: 0 | AM24: 0 | AO24: 0 | AQ24: 0 | AS24: 0 | AU24: 0 | AW24: 0 | AY24: =SUM(I24:AW24) -> 0
I25: =IF(I10=0,0,I13/I10) -> 0 | K25: =K13/K10 -> #DIV/0! | M25: =M13/M10 -> #DIV/0! | O25: =O13/O10 -> #DIV/0! | Q25: =Q17/Q12 -> #DIV/0! | S25: =S17/S12 -> #DIV/0! | W25: =W17/W12 -> #DIV/0! | Y25: =Y17/Y12 -> #DIV/0! | AC25: =AC13/AC10 -> #DIV/0! | AE25: =AE13/AE10 -> #DIV/0! | AG25: =AG13/AG10 -> #DIV/0! | AI25: =AI13/AI10 -> #DIV/0! | AK25: =AK13/AK10 -> #DIV/0! | AM25: =AM13/AM10 -> #DIV/0! | AO25: =AO13/AO10 -> #DIV/0! | AQ25: =AQ13/AQ10 -> #DIV/0! | AS25: =AS13/AS10 -> #DIV/0! | AU25: =AU13/AU10 -> #DIV/0! | AW25: =AW17/AW12 -> #DIV/0!
A26: A | B26: GROSS DEVELOPMENT VALUE
S27: Mixed Comm | W27: Mixed Comm | Y27: Mixed Comm
A28: 1 | B28: Type of Development | D28: Mixed Development | I28: 3 Sty Superlink | K28: 3 Sty Superlink | M28: Affordable Home | O28: Affordable Home | Q28: Commercial | S28: S. Apartment | W28: S.Apartment | Y28: S.Apartment | AC28: 2 Sty Linkhouse | AE28: 2 Sty Linkhouse | AG28: 2 Sty Linkhouse | AI28: 2 Sty Semi-D | AK28: 2 Sty Semi-D | AM28: Zero Lot Bungalow | AO28: Condominium | AQ28: Condominium | AS28: Recreational | AU28: Terrace House | AW28: Commercial Shoplot
A29: =A24+1 -> 1 | B29: Total No of Units | C29: a) Residential | D29: =E31+E45+E46+E53+E54+E55+E56+E57+E58+E60+E59+E62 -> 0 | Q29: Shop-lot | S29: Retail Shoplots | W29: Retail Shoplots | Y29: Retail Shoplots | AO29: High Rise | AQ29: High Rise | AS29: Park
C30: b) Commercial | D30: =E47+E48+E51+E52+E63+E61 -> 0
A31: =A25+1 -> 1 | B31: Total Saleable Area (NFA) | C31: a) Residential | D31: =I17+K17+M17+O17+AC17+AE17+AG17+AI17+AK17+AU17+AM17+AO17+AQ17 -> 0
C32: b) Commercial | D32: =Q17+S17+W17+Y17+AW17+AS17 -> 0
A33: =A27+1 -> 1 | B33: Net Selling Price psf | C33: a) Residential | D33: =IFERROR((I73+K73+M73+O73+AC73+AE73+AG73+AI73+AU73)/D27,0) | E33: b) Commercial | F33: =IFERROR((Q73+S73+W73+Y73+AW73)/D28,0) | I33: =IFERROR(I73/I17,0) | K33: =IFERROR(K73/K17,0) | M33: =IFERROR(M73/M17,0) | O33: =IFERROR(O73/O17,0) | Q33: =IFERROR(Q73/Q17,0) | S33: =IFERROR(S73/S17,0) | W33: =IFERROR(W73/W17,0) | Y33: =IFERROR(Y73/Y17,0) | AC33: =IFERROR(AC73/AC17,0) | AE33: =IFERROR(AE73/AE17,0) | AG33: =IFERROR(AG73/AG17,0) | AI33: =IFERROR(AI73/AI17,0) | AK33: =IFERROR(AK73/AK17,0) | AM33: =IFERROR(AM73/AM17,0) | AO33: =IFERROR(AO73/AO17,0) | AQ33: =IFERROR(AQ73/AQ17,0) | AS33: =IFERROR(AS73/AS17,0) | AU33: =IFERROR(AU73/AU17,0) | AW33: =IFERROR(AW73/AW17,0)
D34: Unit Avg size | E34: Units | F34: RM'psf Nett (NSA) | G34: Average Price/unit (Nett)
C35: Ph 1a - 3 Storey Superlinks | D35: 1500 | E35: 0 | F35: 0 | G35: =F31*D31 -> 0 | I35: =G31*E31/2 -> 0 | K35: =G44*E44/2 -> 0 | AY35: =SUM(I31:AW31) -> 0
C36: Superlink (24' x 65')Intermediate | D36: 2586 | F36: 290.2091 | G36: 320.966 | AY36: =SUM(I32:AW32) -> 0
C37: Superlink (24' x 65') Corner | D37: 2605 | F37: 322.4 | G37: 359.499 | AY37: =SUM(I33:AW33)
C38: Superlink (26' x 65') Intermediate | D38: 2864 | F38: 285.67 | G38: 314.384 | AY38: =SUM(I34:AW34) -> 0
C39: Superlink (26' x 65')Corner | D39: 3150 | F39: 310.32 | G39: 335.33 | AY39: =SUM(I35:AW35) -> 0
C40: Superlink (30' x 65') Intermediate | D40: 3527 | F40: 263.39 | G40: 305.177 | AY40: =SUM(I36:AW36) -> 0
C41: Superlink (30' x 65') Corner | D41: 3510 | F41: 287.12 | G41: 331.815 | AY41: =SUM(I37:AW37) -> 0
C42: Superlink (24' x 70') Intermediate | D42: 2586 | F42: 289.29 | G42: 320.966 | AY42: =SUM(I38:AW38) -> 0
C43: Superlink (24' x 70') Corner | D43: 2605 | F43: 323.29 | G43: 356.031 | AY43: =SUM(I39:AW39) -> 0
C44: Superlink (26' x 70') Intermediate | D44: 2864 | F44: 287.16 | G44: 314.384 | AY44: =SUM(I40:AW40) -> 0
C45: Superlink (26' x 70') Corner | D45: 3150 | F45: 309.69 | G45: 340.2255 | AY45: =SUM(I41:AW41) -> 0
C46: Superlink (30' x 70') Intermediate | D46: 3526 | F46: 270 | G46: 305.171 | AY46: =SUM(I42:AW42) -> 0
C47: Superlink (30' x 70') Corner | D47: 3510 | F47: 298.67 | G47: 370.396 | AY47: =SUM(I43:AW43) -> 0
C48: Ph 1b - 3 Storey Superlinks | D48: 0 | E48: 0 | F48: 0 | G48: =F44*D44 -> 822426.24 | AY48: =SUM(I44:AW44) -> 0
C49: Ph 1c - Affordable | D49: 0 | E49: 0 | F49: 0 | G49: =F45*D45 -> 975523.5 | M49: =G45*E45 -> 0 | AY49: =SUM(I45:AW45) -> 0
C50: Ph 1d - Affordable | D50: 0 | E50: 0 | F50: 0 | G50: =F46*D46 -> 952020 | O50: =G46*E46 -> 0 | AY50: =SUM(I46:AW46) -> 0
C51: Ph 1e - Commercial | D51: 0 | E51: 0 | F51: 0 | G51: =F47*D47 -> 1048331.7 | Q51: =G47*E47 -> 0 | AY51: =SUM(I47:AW47) -> 0
C52: Ph 1f - Mixed Commercial | D52: 0 | E52: =SUM(E49:E50) -> 0 | F52: 0 | G52: =F48*D48 -> 0 | AY52: =SUM(I48:AW48) -> 0
C53: -Serviced Apartment | D53: 0 | E53: 0 | F53: 0 | G53: =F49*D49 -> 0 | S53: =G49*E49 -> 0 | AY53: =SUM(I49:AW49) -> 0
C54: -Retail Shoplots | D54: 0 | E54: 0 | F54: 0 | G54: =F50*D50 -> 0 | S54: =G50*E50 -> 0 | AY54: =SUM(I50:AW50) -> 0
C55: Ph 1g - Commercial Shoplot | D55: 0 | E55: 0 | F55: 0 | G55: =F51*D51 -> 0 | AY55: =SUM(I51:AW51) -> 0
C56: Ph 1h - Commercial Shoplot | D56: 0 | E56: 0 | F56: 0 | G56: =F52*D52 -> 0 | AY56: =SUM(I52:AW52) -> 0
C57: Ph 2a - Double Storey Terraces | D57: 0 | E57: 0 | F57: 0 | G57: =F53*D53 -> 0 | AY57: =SUM(I53:AW53) -> 0
C58: Ph 2b - Double Storey Terraces | D58: 0 | E58: 0 | F58: 0 | G58: =F54*D54 -> 0 | AY58: =SUM(I54:AW54) -> 0
C59: Ph 2c - Double Storey Terraces | D59: 0 | E59: 0 | F59: 0 | G59: =F55*D55 -> 0 | AY59: =SUM(I55:AW55) -> 0
C60: Ph 2d -Double Storey Terraces | D60: 0 | E60: 0 | F60: 0 | G60: =F56*D56 -> 0 | AY60: =SUM(I56:AW56) -> 0
C61: Ph 2e -Terrace Villa | D61: 0 | E61: 0 | F61: 0 | G61: =F57*D57 -> 0 | AY61: =SUM(I57:AW57) -> 0
C62: Ph 2f - Zero Lot Bungalow | D62: 0 | E62: 0 | F62: 0 | G62: =F58*D58 -> 0 | AY62: =SUM(I58:AW58) -> 0
C63: Ph 2g1 - Condominium | D63: 0 | E63: 0 | F63: 0 | G63: =F59*D59 -> 0 | AY63: =SUM(I59:AW59) -> 0
C64: Ph 2g2 - Condominium | D64: 0 | E64: 0 | F64: 0 | G64: =F60*D60 -> 0 | AY64: =SUM(I60:AW60) -> 0
C65: Ph 2g3 - Park | D65: 0 | E65: 0 | F65: 0 | G65: =F61*D61 -> 0 | I65: =I75+I67+I68+ABS(I70)+I71 | K65: =K75+K67+K68+ABS(K70)+K71 | M65: =M75+M67+M68+ABS(M70)+M71 | O65: =O75+O67+O68+ABS(O70)+O71 | Q65: =Q75+Q67+Q68+ABS(Q70)+Q71 | S65: =S75+S67+S68+ABS(S70)+S71 | W65: =W75+W67+W68+ABS(W70)+W71 | Y65: =Y75+Y67+Y68+ABS(Y70)+Y71 | AC65: =AC75+AC67+AC68+ABS(AC70)+AC71 | AE65: =AE75+AE67+AE68+ABS(AE70)+AE71 | AG65: =AG75+AG67+AG68+ABS(AG70)+AG71 | AI65: =AI75+AI67+AI68+ABS(AI70)+AI71 | AK65: =AK75+AK67+AK68+ABS(AK70)+AK71 | AM65: =AM75+AM67+AM68+ABS(AM70)+AM71 | AO65: =AO75+AO67+AO68+ABS(AO70)+AO71 | AQ65: =AQ75+AQ67+AQ68+ABS(AQ70)+AQ71 | AS65: =AS75+AS67+AS68+ABS(AS70)+AS71 | AU65: =AU75+AU67+AU68+ABS(AU70)+AU71 | AW65: =AW75+AW67+AW68+ABS(AW70)+AW71 | AY65: =AY75+AY67+AY68+ABS(AY70)+AY71
C66: Ph 2h - Terrace House | D66: 0 | E66: 0 | F66: 0 | G66: =F62*D62 -> 0 | AY66: =SUM(I62:AW62) -> 0
C67: Ph 2j - Commercial Shoplot | D67: 0 | E67: 0 | F67: 0 | G67: =F63*D63 -> 0 | AY67: =SUM(I63:AW63) -> 0
A69: GROSS DEVELOPMENT VALUE (GDV) | I69: =SUM(I66:I73) | K69: =SUM(K66:K73) | M69: =SUM(M66:M73) | O69: =SUM(O66:O73) | Q69: =SUM(Q66:Q73) | S69: =SUM(S66:S73) | W69: =SUM(W66:W73) | Y69: =SUM(Y66:Y73) | AC69: =SUM(AC66:AC73) | AE69: =SUM(AE66:AE73) | AG69: =SUM(AG66:AG73) | AI69: =SUM(AI66:AI73) | AK69: =SUM(AK66:AK73) | AM69: =SUM(AM66:AM73) | AO69: =SUM(AO66:AO73) | AQ69: =SUM(AQ66:AQ73) | AS69: =SUM(AS66:AS73) | AU69: =SUM(AU66:AU73) | AW69: =SUM(AW66:AW73) | AY69: =SUM(AY66:AY73)
A70: Gross Selling Price psf | I70: =IFERROR(I65/I17,0) | K70: =IFERROR(K65/K17,0) | M70: =IFERROR(M65/M17,0) | O70: =IFERROR(O65/O17,0) | Q70: =IFERROR(Q65/Q17,0) | S70: =IFERROR(S65/S17,0) | W70: =IFERROR(W65/W17,0) | Y70: =IFERROR(Y65/Y17,0) | AC70: =IFERROR(AC65/AC17,0) | AE70: =IFERROR(AE65/AE17,0) | AG70: =IFERROR(AG65/AG17,0) | AI70: =IFERROR(AI65/AI17,0) | AK70: =IFERROR(AK65/AK17,0) | AM70: =IFERROR(AM65/AM17,0) | AO70: =IFERROR(AO65/AO17,0) | AQ70: =IFERROR(AQ65/AQ17,0) | AS70: =IFERROR(AS65/AS17,0) | AU70: =IFERROR(AU65/AU17,0) | AW70: =IFERROR(AW65/AW17,0) | AY70: =IFERROR(AY65/AY17,0)
I72: =$G$67*I73 | K72: =$G$67*K73 | S72: =$G$67*S49 -> 0 | AC72: =$G$67*AC73 | AE72: =$G$67*AE73 | AG72: =$G$67*AG73 | AI72: =$G$67*AI73 | AK72: =$G$67*AK73 | AM72: =$G$67*AM73 | AO72: =$G$67*AO73 | AQ72: =$G$67*AQ73 | AS72: =$G$67*AS73 | AU72: =$G$67*AU73 | AY72: =SUM(I67:AW67) -> 0
A73: Less : Bumiputera Penalty (unsold Bumi unit release) | E73: 0.005 | F73: 0.5 | G73: of NDV | I73: =$E$68*$F$68*I74 | K73: =$E$68*$F$68*K74 | M73: =$E$68*$F$68*M74 | O73: =$E$68*$F$68*O74 | Q73: =$E$68*$F$68*Q74 | S73: =$E$68*$F$68*S74 | W73: =$E$68*$F$68*W74 | Y73: =$E$68*$F$68*Y74 | AC73: =$E$68*$F$68*AC74 | AE73: =$E$68*$F$68*AE74 | AG73: =$E$68*$F$68*AG74 | AI73: =$E$68*$F$68*AI74 | AK73: =$E$68*$F$68*AK74 | AM73: =$E$68*$F$68*AM74 | AO73: =$E$68*$F$68*AO74 | AQ73: =$E$68*$F$68*AQ74 | AS73: =$E$68*$F$68*AS74 | AU73: =$E$68*$F$68*AU74 | AW73: =$E$68*$F$68*AW74 | AY73: =SUM(I68:AW68) -> 0
A74: Less : Selling Expenses | F74: Legal Fees * | G74: 0.004 | H74: of NDV | I74: =-I73*$G$68 | K74: =-K73*$G$68 | M74: =-M73*$G$68 | O74: =-O73*$G$68 | Q74: =-Q73*$G$68 | S74: =-S73*$G$68 | W74: =-W73*$G$68 | Y74: =-Y73*$G$68 | AC74: =-AC73*$G$68 | AE74: =-AE73*$G$68 | AG74: =-AG73*$G$68 | AI74: =-AI73*$G$68 | AK74: =-AK73*$G$68 | AM74: =-AM73*$G$68 | AO74: =-AO73*$G$68 | AQ74: =-AQ73*$G$68 | AS74: =-AS73*$G$68 | AU74: =-AU73*$G$68 | AW74: =-AW73*$G$68 | AY74: =SUM(I68:AW68) -> 0
A75: Less: Early Bird Discount | F75: Discount * | G75: 0.09 | H75: of NDV | I75: =G69*I73 | K75: =I69*K73 | Q75: =O69*Q73 | S75: =Q69*S73 | W75: =U69*W73 | Y75: =W69*Y73 | AC75: =AA69*AC73 | AE75: =AC69*AE73 | AG75: =AE69*AG73 | AI75: =AG69*AI73 | AK75: =AI69*AK73 | AM75: =AK69*AM73 | AO75: =AM69*AO73 | AQ75: =AO69*AQ73 | AS75: =AQ69*AS73 | AU75: =AS69*AU73 | AW75: =AU69*AW73 | AY75: =SUM(I69:AW69)
A77: *Net Development Value (NDV) have to be same with S&M based on net selling price after deduction of all discounts (bumi discounts & release penalty), incentives, early birds, Legal Fees & any other items not stated in this Feasibility. Sales have to mark up the selling price accordingly. | AY77: =SUM(I71:AW71) -> 0
A79: NET DEVELOPMENT VALUE (NDV) | I79: =SUM(I31:I64) | K79: =SUM(K31:K64) | M79: =SUM(M31:M64) | O79: =SUM(O31:O64) | Q79: =SUM(Q31:Q64) | S79: =SUM(S31:S64) | W79: =SUM(W31:W64) | Y79: =SUM(Y31:Y64) | AC79: =SUM(AC31:AC64) | AE79: =SUM(AE31:AE64) | AG79: =SUM(AG31:AG64) | AI79: =SUM(AI31:AI64) | AK79: =SUM(AK31:AK64) | AM79: =SUM(AM31:AM64) | AO79: =SUM(AO31:AO64) | AQ79: =SUM(AQ31:AQ64) | AS79: =SUM(AS31:AS64) | AU79: =SUM(AU31:AU64) | AW79: =SUM(AW31:AW64) | AY79: =SUM(AY31:AY64)
AE80: =146408452/169*173 -> 1.4987374e+08 | AO80: 52605702 | AQ80: 52605702 | AS80: 52605702
AE81: =(146408452-12830219.68-8665391.42)/169*173 -> 1.2786936e+08
I82: =IF(I12=0,0,I84/I12) -> 0 | K82: =IF(K12=0,0,K84/K12) -> 0 | M82: =IF(M12=0,0,M84/M12) -> 0 | O82: =IF(O12=0,0,O84/O12) -> 0 | Q82: =IF(Q12=0,0,Q84/Q12) -> 0 | S82: =IF(S12=0,0,S84/S12) -> 0 | W82: =IF(W12=0,0,W84/W12) -> 0 | Y82: =IF(Y12=0,0,Y84/Y12) -> 0 | AC82: =IF(AC12=0,0,AC84/AC12) -> 0 | AE82: =IF(AE12=0,0,AE84/AE12) -> 0 | AG82: =IF(AG12=0,0,AG84/AG12) -> 0 | AI82: =IF(AI12=0,0,AI84/AI12) -> 0 | AK82: =IF(AK12=0,0,AK84/AK12) -> 0 | AM82: =IF(AM12=0,0,AM84/AM12) -> 0 | AO82: =IF(AO12=0,0,AO84/AO12) -> 0 | AQ82: =IF(AQ12=0,0,AQ84/AQ12) -> 0 | AS82: =IF(AS12=0,0,AS84/AS12) -> 0 | AU82: =IF(AU12=0,0,AU84/AU12) -> 0 | AW82: =IF(AW12=0,0,AW84/AW12) -> 0 | AY82: =IF(AY12=0,0,AY84/AY12) -> 0
A83: Net Selling Price psf | I83: =IFERROR(I75/I17,0) | K83: =IFERROR(K75/K17,0) | M83: =IFERROR(M75/M17,0) -> 0 | O83: =IFERROR(O75/O17,0) -> 0 | Q83: =IFERROR(Q75/Q17,0) | S83: =IFERROR(S75/S17,0) | W83: =IFERROR(W75/W17,0) | Y83: =IFERROR(Y75/Y17,0) | AC83: =IFERROR(AC75/AC17,0) | AE83: =IFERROR(AE75/AE17,0) | AG83: =IFERROR(AG75/AG17,0) | AI83: =IFERROR(AI75/AI17,0) | AK83: =IFERROR(AK75/AK17,0) | AM83: =IFERROR(AM75/AM17,0) | AO83: =IFERROR(AO75/AO17,0) | AQ83: =IFERROR(AQ75/AQ17,0) | AS83: =IFERROR(AS75/AS17,0) | AU83: =IFERROR(AU75/AU17,0) | AW83: =IFERROR(AW75/AW17,0) | AY83: =SUM(AY84:AY90) -> #DIV/0!
F84: 0 | I84: =$F$84*I12 -> 0 | K84: =$F$84*K12 -> 0 | M84: =$F$84*M12 -> 0 | O84: =$F$84*O12 -> 0 | Q84: =$F$84*Q12 -> 0 | S84: =$F$84*S12 -> 0 | W84: =$F$84*W12 -> 0 | Y84: =$F$84*Y12 -> 0 | AC84: =$F$84*AC12 -> 0 | AE84: =$F$84*AE12 -> 0 | AG84: =$F$84*AG12 -> 0 | AI84: =$F$84*AI12 -> 0 | AK84: =$F$84*AK12 -> 0 | AM84: =$F$84*AM12 -> 0 | AO84: =$F$84*AO12 -> 0 | AQ84: =$F$84*AQ12 -> 0 | AS84: =$F$84*AS12 -> 0 | AU84: =$F$84*AU12 -> 0 | AW84: =$F$84*AW12 -> 0 | AY84: =SUM(I84:AW84) -> 0
A85: B | B85: GROSS DEVELOPMENT COST (GDC) | I85: I82*$D$83 | K85: K82*$D$83 | M85: M82*$D$83 | O85: O82*$D$83 | Q85: Q82*$D$83 | S85: S82*$D$83 | W85: W82*$D$83 | Y85: Y82*$D$83 | AC85: AC82*$D$83 | AE85: AE82*$D$83 | AG85: AG82*$D$83 | AI85: AI82*$D$83 | AK85: AK82*$D$83 | AM85: AM82*$D$83 | AO85: AO82*$D$83 | AQ85: AQ82*$D$83 | AS85: AS82*$D$83 | AU85: AU82*$D$83 | AW85: AW82*$D$83 | AY85: =SUM(I85:AW85) -> 0
F86: 0 | G86: per Annum for xx years | H86: Land Cost PSF | I86: =$F$86*(I10/$AY$10)*4 -> #DIV/0! | K86: =$F$86*(K10/$AY$10)*4 -> #DIV/0! | M86: =$F$86*(M10/$AY$10)*4 -> #DIV/0! | O86: =$F$86*(O10/$AY$10)*4 -> #DIV/0! | Q86: =$F$86*(Q10/$AY$10)*4 -> #DIV/0! | S86: =$F$86*(S10/$AY$10)*4 -> #DIV/0! | W86: =$F$86*(W10/$AY$10)*4 -> #DIV/0! | Y86: =$F$86*(Y10/$AY$10)*4 -> #DIV/0! | AC86: =$F$86*(AC10/$AY$10)*4 -> #DIV/0! | AE86: =$F$86*(AE10/$AY$10)*4 -> #DIV/0! | AG86: =$F$86*(AG10/$AY$10)*4 -> #DIV/0! | AI86: =$F$86*(AI10/$AY$10)*4 -> #DIV/0! | AK86: =$F$86*(AK10/$AY$10)*4 -> #DIV/0! | AM86: =$F$86*(AM10/$AY$10)*4 -> #DIV/0! | AO86: =$F$86*(AO10/$AY$10)*4 -> #DIV/0! | AQ86: =$F$86*(AQ10/$AY$10)*4 -> #DIV/0! | AS86: =$F$86*(AS10/$AY$10)*4 -> #DIV/0! | AU86: =$F$86*(AU10/$AY$10)*4 -> #DIV/0! | AW86: =$F$86*(AW10/$AY$10)*4 -> #DIV/0! | AY86: =SUM(I86:AW86) -> #DIV/0!
A87: 5 | B87: LAND & OTHER RELATED COSTS | F87: 0 | G87: per Annum for xx years | I87: =$F$87*(I10/$AY$10)*4 -> #DIV/0! | K87: =$F$87*(K10/$AY$10)*4 -> #DIV/0! | M87: =$F$87*(M10/$AY$10)*4 -> #DIV/0! | O87: =$F$87*(O10/$AY$10)*4 -> #DIV/0! | Q87: =$F$87*(Q10/$AY$10)*4 -> #DIV/0! | S87: =$F$87*(S10/$AY$10)*4 -> #DIV/0! | W87: =$F$87*(W10/$AY$10)*4 -> #DIV/0! | Y87: =$F$87*(Y10/$AY$10)*4 -> #DIV/0! | AC87: =$F$87*(AC10/$AY$10)*4 -> #DIV/0! | AE87: =$F$87*(AE10/$AY$10)*4 -> #DIV/0! | AG87: =$F$87*(AG10/$AY$10)*4 -> #DIV/0! | AI87: =$F$87*(AI10/$AY$10)*4 -> #DIV/0! | AK87: =$F$87*(AK10/$AY$10)*4 -> #DIV/0! | AM87: =$F$87*(AM10/$AY$10)*4 -> #DIV/0! | AO87: =$F$87*(AO10/$AY$10)*4 -> #DIV/0! | AQ87: =$F$87*(AQ10/$AY$10)*4 -> #DIV/0! | AS87: =$F$87*(AS10/$AY$10)*4 -> #DIV/0! | AU87: =$F$87*(AU10/$AY$10)*4 -> #DIV/0! | AW87: =$F$87*(AW10/$AY$10)*4 -> #DIV/0! | AY87: =SUM(I87:AW87) -> #DIV/0!
F88: 0 | I88: I82*$F$86 | K88: K82*$F$86 | M88: M82*$F$86 | O88: O82*$F$86 | Q88: Q82*$F$86 | S88: S82*$F$86 | W88: W82*$F$86 | Y88: Y82*$F$86 | AC88: AC82*$F$86 | AE88: AE82*$F$86 | AG88: AG82*$F$86 | AI88: AI82*$F$86 | AK88: AK82*$F$86 | AM88: AM82*$F$86 | AO88: AO82*$F$86 | AQ88: AQ82*$F$86 | AS88: AS82*$F$86 | AU88: AU82*$F$86 | AW88: AW82*$F$86 | AY88: =SUM(I88:AW88) -> 0
D89: 0.15 | E89: 0.3 | F89: 15% or 30% | G89: of Net Land Value | I89: I82*$F$87 | K89: K82*$F$87 | M89: M82*$F$87 | O89: O82*$F$87 | Q89: Q82*$F$87 | S89: S82*$F$87 | W89: W82*$F$87 | Y89: Y82*$F$87 | AC89: AC82*$F$87 | AE89: AE82*$F$87 | AG89: AG82*$F$87 | AI89: AI82*$F$87 | AK89: AK82*$F$87 | AM89: AM82*$F$87 | AO89: AO82*$F$87 | AQ89: AQ82*$F$87 | AS89: AS82*$F$87 | AU89: AU82*$F$87 | AW89: AW82*$F$87 | AY89: =SUM(I89:AW89) -> 0
B90: 5.3 | C90: Quit Rent | F90: 0 | G90: per Annum for xx years | I90: I82*$F$88 | K90: K82*$F$88 | M90: M82*$F$88 | O90: O82*$F$88 | Q90: Q82*$F$88 | S90: S82*$F$88 | W90: W82*$F$88 | Y90: Y82*$F$88 | AC90: AC82*$F$88 | AE90: AE82*$F$88 | AG90: AG82*$F$88 | AI90: AI82*$F$88 | AK90: AK82*$F$88 | AM90: AM82*$F$88 | AO90: AO82*$F$88 | AQ90: AQ82*$F$88 | AS90: AS82*$F$88 | AU90: AU82*$F$88 | AW90: AW82*$F$88 | AY90: =SUM(I90:AW90) -> 0
B91: =B84+0.1 -> 0.1 | C91: Assessment | F91: 0 | G91: per Annum for xx years | I91: =F85*(I11/$AY$10)*4 -> #DIV/0! | K91: =+$F85*(K10/$AY$10)*4 -> #DIV/0! | M91: =+$F85*(M10/$AY$10)*4 -> #DIV/0! | O91: =+$F85*(O10/$AY$10)*4 -> #DIV/0! | Q91: =+$F85*(Q10/$AY$10)*6 -> #DIV/0! | S91: =+$F85*(S10/$AY$10)*6 -> #DIV/0! | W91: =+$F85*(W10/$AY$10)*8 -> #DIV/0! | Y91: =+$F85*(Y10/$AY$10)*10 -> #DIV/0! | AC91: =+$F85*(AC10/$AY$10)*4 -> #DIV/0! | AE91: =+$F85*(AE10/$AY$10)*4 -> #DIV/0! | AG91: =+$F85*(AG10/$AY$10)*6 -> #DIV/0! | AI91: =+$F85*(AI10/$AY$10)*6 -> #DIV/0! | AK91: =+$F85*(AK10/$AY$10)*8 -> #DIV/0! | AM91: =+$F85*(AM10/$AY$10)*8 -> #DIV/0! | AO91: =+$F85*(AO10/$AY$10)*10 -> #DIV/0! | AQ91: =+$F85*(AQ10/$AY$10)*10 -> #DIV/0! | AS91: =+$F85*(AS10/$AY$10)*10 -> #DIV/0! | AU91: =+$F85*(AU10/$AY$10)*10 -> #DIV/0! | AW91: =+$F85*(AW10/$AY$10)*10 -> #DIV/0! | AY91: =SUM(I85:AW85) -> 0
B92: 5.5 | C92: Stamp Duty on Land Purchase | F92: 0.03 | G92: 3% of land value (standard slab rate) | I92: I82*$F$90 | K92: K82*$F$90 | M92: M82*$F$90 | O92: O82*$F$90 | Q92: Q82*$F$90 | S92: S82*$F$90 | W92: W82*$F$90 | Y92: Y82*$F$90 | AC92: AC82*$F$90 | AE92: AE82*$F$90 | AG92: AG82*$F$90 | AI92: AI82*$F$90 | AK92: AK82*$F$90 | AM92: AM82*$F$90 | AO92: AO82*$F$90 | AQ92: AQ82*$F$90 | AS92: AS82*$F$90 | AU92: AU82*$F$90 | AW92: AW82*$F$90 | AY92: =SUM(I86:AW86) -> #DIV/0!
B93: 5.6 | C93: Legal Fees on Land Purchase | F93: 0.0025 | G93: 0.25% of land value | I93: I82*$F$91 | K93: K82*$F$91 | M93: M82*$F$91 | O93: O82*$F$91 | Q93: Q82*$F$91 | S93: S82*$F$91 | W93: W82*$F$91 | Y93: Y82*$F$91 | AC93: AC82*$F$91 | AE93: AE82*$F$91 | AG93: AG82*$F$91 | AI93: AI82*$F$91 | AK93: AK82*$F$91 | AM93: AM82*$F$91 | AO93: AO82*$F$91 | AQ93: AQ82*$F$91 | AS93: AS82*$F$91 | AU93: AU82*$F$91 | AW93: AW82*$F$91 | AY93: =SUM(I87:AW87) -> #DIV/0!
B94: 5.7 | C94: Valuation Fee | F94: 0.00125 | G94: 0.125% of land value | I94: =$F$88*I4 -> 0 | K94: =$F$88*K4 -> 0 | M94: =$F$88*M4 -> 0 | O94: =$F$88*O4 -> 0 | Q94: =$F$88*Q4 -> 0 | S94: =$F$88*S4 -> 0 | W94: =$F$88*W4 -> 0 | Y94: =$F$88*Y4 -> 0 | AC94: =$F$88*AC4 -> 0 | AE94: =$F$88*AE4 -> 0 | AG94: =$F$88*AG4 -> 0 | AI94: =$F$88*AI4 -> 0 | AK94: =$F$88*AK4 -> 0 | AM94: =$F$88*AM4 -> 0 | AO94: =$F$88*AO4 -> 0 | AQ94: =$F$88*AQ4 -> 0 | AS94: =$F$88*AS4 -> 0 | AU94: =$F$88*AU4 -> 0 | AW94: =$F$88*AW4 -> #VALUE! | AY94: =SUM(I88:AW88) -> 0
B95: 5.8 | C95: Land Amalgamation / Sub-division Fee | F95: 0.01 | G95: 1% of land value (if combining lots) | I95: =$F$89*I4 -> #VALUE! | K95: =$F$89*K4 -> #VALUE! | M95: =$F$89*M4 -> #VALUE! | O95: =$F$89*O4 -> #VALUE! | Q95: =$F$89*Q4 -> #VALUE! | S95: =$F$89*S4 -> #VALUE! | W95: =$F$89*W4 -> #VALUE! | Y95: =$F$89*Y4 -> #VALUE! | AC95: =$F$89*AC4 -> #VALUE! | AE95: =$F$89*AE4 -> #VALUE! | AG95: =$F$89*AG4 -> #VALUE! | AI95: =$F$89*AI4 -> #VALUE! | AK95: =$F$89*AK4 -> #VALUE! | AM95: =$F$89*AM4 -> #VALUE! | AO95: =$F$89*AO4 -> #VALUE! | AQ95: =$F$89*AQ4 -> #VALUE! | AS95: =$F$89*AS4 -> #VALUE! | AU95: =$F$89*AU4 -> #VALUE! | AW95: =$F$89*AW4 -> #VALUE! | AY95: =SUM(I89:AW89) -> 0
B96: 5.9 | C96: Lease Extension Premium | F96: 0 | G96: Leasehold only — ¼×1/100×value×extension years | I96: =$F$90*I4 -> 0 | K96: =$F$90*K4 -> 0 | M96: =$F$90*M4 -> 0 | O96: =$F$90*O4 -> 0 | Q96: =$F$90*Q4 -> 0 | S96: =$F$90*S4 -> 0 | W96: =$F$90*W4 -> 0 | Y96: =$F$90*Y4 -> 0 | AC96: =$F$90*AC4 -> 0 | AE96: =$F$90*AE4 -> 0 | AG96: =$F$90*AG4 -> 0 | AI96: =$F$90*AI4 -> 0 | AK96: =$F$90*AK4 -> 0 | AM96: =$F$90*AM4 -> 0 | AO96: =$F$90*AO4 -> 0 | AQ96: =$F$90*AQ4 -> 0 | AS96: =$F$90*AS4 -> 0 | AU96: =$F$90*AU4 -> 0 | AW96: =$F$90*AW4 -> #VALUE! | AY96: =SUM(I90:AW90) -> 0
B97: 5.10 | C97: Low Cost Housing Contribution | F97: 0 | G97: State-specific lump sum if applicable | I97: =$F$91*I4 -> 0 | K97: =$F$91*K4 -> 0 | M97: =$F$91*M4 -> 0 | O97: =$F$91*O4 -> 0 | Q97: =$F$91*Q4 -> 0 | S97: =$F$91*S4 -> 0 | W97: =$F$91*W4 -> 0 | Y97: =$F$91*Y4 -> 0 | AC97: =$F$91*AC4 -> 0 | AE97: =$F$91*AE4 -> 0 | AG97: =$F$91*AG4 -> 0 | AI97: =$F$91*AI4 -> 0 | AK97: =$F$91*AK4 -> 0 | AM97: =$F$91*AM4 -> 0 | AO97: =$F$91*AO4 -> 0 | AQ97: =$F$91*AQ4 -> 0 | AS97: =$F$91*AS4 -> 0 | AU97: =$F$91*AU4 -> 0 | AW97: =$F$91*AW4 -> #VALUE! | AY97: =SUM(I91:AW91) -> #DIV/0!
A99: 6 | B99: GROSS CONSTRUCTION COST (GCC) | I99: =SUM(I101:I104) -> #DIV/0! | K99: =SUM(K101:K104) -> #DIV/0! | M99: =SUM(M101:M103) -> #DIV/0! | O99: =SUM(O101:O103) -> #DIV/0! | Q99: =SUM(Q101:Q104) -> #DIV/0! | S99: =SUM(S101:S104) -> #DIV/0! | W99: =SUM(W101:W104) -> #DIV/0! | Y99: =SUM(Y101:Y104) -> #DIV/0! | AC99: =SUM(AC101:AC104) -> #DIV/0! | AE99: =SUM(AE101:AE104) -> #DIV/0! | AG99: =SUM(AG101:AG103) -> #DIV/0! | AI99: =SUM(AI101:AI103) -> #DIV/0! | AK99: =SUM(AK101:AK103) -> #DIV/0! | AM99: =SUM(AM101:AM103) -> #DIV/0! | AO99: =SUM(AO101:AO103) -> #DIV/0! | AQ99: =SUM(AQ101:AQ103) -> #DIV/0! | AS99: =SUM(AS101:AS103) -> #DIV/0! | AU99: =SUM(AU101:AU103) -> #DIV/0! | AW99: =SUM(AW101:AW104) -> #DIV/0! | AY99: =SUM(AY101:AY104) -> #DIV/0!
H100: % of NDV | I100: =I87/I73 | K100: =K87/K73 | M100: =M87/M73 | O100: =O87/O73 | Q100: =Q87/Q73 | S100: =S87/S73 | W100: =W87/W73 | Y100: =Y87/Y73 | AC100: =AC87/AC73 | AE100: =AE87/AE73 | AG100: =AG87/AG73 | AI100: =AI87/AI73 | AK100: =AK87/AK73 | AM100: =AM87/AM73 | AO100: =AO87/AO73 | AQ100: =AQ87/AQ73 | AS100: =AS87/AS73 | AU100: =AU87/AU73 | AW100: =AW87/AW73 | AY100: =AY87/AY73 -> #DIV/0!
H101: Construction Cost psf | I101: =I87/I17 -> #DIV/0! | K101: =K87/K17 -> #DIV/0! | M101: =M87/M17 -> #DIV/0! | O101: =O87/O17 -> #DIV/0! | Q101: =Q87/Q17 -> #DIV/0! | S101: =S87/S17 -> #DIV/0! | W101: =W87/W17 -> #DIV/0! | Y101: =Y87/Y17 -> #DIV/0! | AC101: =AC87/AC17 -> #DIV/0! | AE101: =AE87/AE17 -> #DIV/0! | AG101: =AG87/AG17 -> #DIV/0! | AI101: =AI87/AI17 -> #DIV/0! | AK101: =AK87/AK17 -> #DIV/0! | AM101: =AM87/AM17 -> #DIV/0! | AO101: =AO87/AO17 -> #DIV/0! | AQ101: =AQ87/AQ17 -> #DIV/0! | AS101: =AS87/AS17 -> #DIV/0! | AU101: =AU87/AU17 -> #DIV/0! | AW101: =AW87/AW17 -> #DIV/0! | AY101: =AY87/AY17 -> #DIV/0!
B102: 6.0 | C102: Substructure / Piling Works | G102: Enter lump sum from piling contract (e.g. Pintaras) | I102: 0 | K102: 0 | M102: 0 | O102: 0 | Q102: 0 | S102: 0 | W102: 0 | Y102: 0 | AC102: 0 | AE102: 0 | AG102: 0 | AI102: 0 | AK102: 0 | AM102: 0 | AO102: 0 | AQ102: 0 | AS102: 0 | AU102: 0 | AW102: 0 | AY102: =SUM(I90:AW90) -> 0
B103: 6.0.1 | C103: Piling (bored / driven / micro-piles) — actual or estimate | F103: 0 | G103: Typical: RM 2M–30M depending on soil conditions and building height | I103: 0 | K103: 0 | M103: 0 | O103: 0 | Q103: 0 | S103: 0 | W103: 0 | Y103: 0 | AC103: 0 | AE103: 0 | AG103: 0 | AI103: 0 | AK103: 0 | AM103: 0 | AO103: 0 | AQ103: 0 | AS103: 0 | AU103: 0 | AW103: 0 | AY103: =SUM(I91:AW91) -> #DIV/0!
B104: 6.1 | C104: Building Work
C105: Residential | F105: 300 | I105: =$F91*I17 -> 0 | K105: =$F91*K17 -> 0 | S105: =$F91*(E49*D49) -> 0 | AC105: =$F91*AC17 -> 0 | AE105: =$F91*AE17 -> 0 | AG105: =$F91*AG17 -> 0 | AI105: =$F91*AI17 -> 0 | AK105: =$F91*AK17 -> 0 | AM105: =$F91*AM17 -> 0 | AO105: =$F91*AO17 -> 0 | AQ105: =$F91*AQ17 -> 0 | AU105: =$F91*AU17 -> 0 | AY105: =SUM(I91:AW91) -> #DIV/0!
C106: Affordable Housing | F106: 200 | M106: =$F92*M17 -> 0 | O106: =$F92*O17 -> 0 | AY106: =SUM(I92:AW92) -> 0
C107: Commercial Shoplots | F107: 180 | Q107: =$F93*Q17 -> 0 | S107: =$F93*(D50*E50) -> 0 | W107: =$F93*W17 -> 0 | Y107: =$F93*Y17 -> 0 | AW107: =$F93*AW17 -> 0 | AY107: =SUM(I93:AW93) -> 0
...

Sheet Cashflow
A1: BRDB LAND — MONTHLY CASHFLOW MODEL (RM'000)
A2: All values RM'000 | Blue = inputs | Black = formulas | Green = linked from Feasibility Study
C3: Year 1 | O3: Year 2 | AA3: Year 3 | AM3: Year 4 | AY3: Year 5
A4: DESCRIPTION | B4: BASIS / TOTAL (RM'000) | C4: Jan '26 | D4: Feb '26 | E4: Mar '26 | F4: Apr '26 | G4: May '26 | H4: Jun '26 | I4: Jul '26 | J4: Aug '26 | K4: Sep '26 | L4: Oct '26 | M4: Nov '26 | N4: Dec '26 | O4: Jan '27 | P4: Feb '27 | Q4: Mar '27 | R4: Apr '27 | S4: May '27 | T4: Jun '27 | U4: Jul '27 | V4: Aug '27 | W4: Sep '27 | X4: Oct '27 | Y4: Nov '27 | Z4: Dec '27 | AA4: Jan '28 | AB4: Feb '28 | AC4: Mar '28 | AD4: Apr '28 | AE4: May '28 | AF4: Jun '28 | AG4: Jul '28 | AH4: Aug '28 | AI4: Sep '28 | AJ4: Oct '28 | AK4: Nov '28 | AL4: Dec '28 | AM4: Jan '29 | AN4: Feb '29 | AO4: Mar '29 | AP4: Apr '29 | AQ4: May '29 | AR4: Jun '29 | AS4: Jul '29 | AT4: Aug '29 | AU4: Sep '29 | AV4: Oct '29 | AW4: Nov '29 | AX4: Dec '29 | AY4: Jan '30 | AZ4: Feb '30 | BA4: Mar '30 | BB4: Apr '30 | BC4: May '30 | BD4: Jun '30 | BE4: Jul '30 | BF4: Aug '30 | BG4: Sep '30 | BH4: Oct '30 | BI4: Nov '30 | BJ4: Dec '30 | BK4: TOTAL
A5: Start date | C5: 46023 | D5: 46054 | E5: 46082 | F5: 46113 | G5: 46143 | H5: 46174 | I5: 46204 | J5: 46235 | K5: 46266 | L5: 46296 | M5: 46327 | N5: 46357 | O5: 46388 | P5: 46419 | Q5: 46447 | R5: 46478 | S5: 46508 | T5: 46539 | U5: 46569 | V5: 46600 | W5: 46631 | X5: 46661 | Y5: 46692 | Z5: 46722 | AA5: 46753 | AB5: 46784 | AC5: 46813 | AD5: 46844 | AE5: 46874 | AF5: 46905 | AG5: 46935 | AH5: 46966 | AI5: 46997 | AJ5: 47027 | AK5: 47058 | AL5: 47088 | AM5: 47119 | AN5: 47150 | AO5: 47178 | AP5: 47209 | AQ5: 47239 | AR5: 47270 | AS5: 47300 | AT5: 47331 | AU5: 47362 | AV5: 47392 | AW5: 47423 | AX5: 47453 | AY5: 47484 | AZ5: 47515 | BA5: 47543 | BB5: 47574 | BC5: 47604 | BD5: 47635 | BE5: 47665 | BF5: 47696 | BG5: 47727 | BH5: 47757 | BI5: 47788 | BJ5: 47818
A7: A. PROJECT ASSUMPTIONS
A8: Project name | B8: BRDB Land Development
A9: Development period (years) | B9: 5
A10: Project start | B10: January 2026
A11: Total GDV (RM'000) | B11: ='Feasibility Study'!AY65/1000
A12: Total NDV (RM'000) | B12: ='Feasibility Study'!AY73/1000 -> 0
A13: Total GDC (RM'000) | B13: ='Feasibility Study'!AY157/1000 -> 0
A14: Total NDP (RM'000) | B14: ='Feasibility Study'!AY170/1000 -> 0
A15: Land cost (RM'000) | B15: ='Feasibility Study'!AY82/1000 -> 0
A16: Construction cost (RM'000) | B16: ='Feasibility Study'!AY87/1000 -> #DIV/0!
A17: Annual interest rate | B17: 0.0455
A18: Target IRR (hurdle) | B18: 0.16
A20: B. MONTHLY SALES ABSORPTION SCHEDULE (% of NDV collected per month)
A21: S-curve absorption — slow launch M1–M6, peak Y2–Y3, tail-off Y4–Y5. Edit % in blue.
A22: Phase | B22: Type | C22: Jan | D22: Feb | E22: Mar | F22: Apr | G22: May | H22: Jun | I22: Jul | J22: Aug | K22: Sep | L22: Oct | M22: Nov | N22: Dec | O22: Jan | P22: Feb | Q22: Mar | R22: Apr | S22: May | T22: Jun | U22: Jul | V22: Aug | W22: Sep | X22: Oct | Y22: Nov | Z22: Dec | AA22: Jan | AB22: Feb | AC22: Mar | AD22: Apr | AE22: May | AF22: Jun | AG22: Jul | AH22: Aug | AI22: Sep | AJ22: Oct | AK22: Nov | AL22: Dec | AM22: Jan | AN22: Feb | AO22: Mar | AP22: Apr | AQ22: May | AR22: Jun | AS22: Jul | AT22: Aug | AU22: Sep | AV22: Oct | AW22: Nov | AX22: Dec | AY22: Jan | AZ22: Feb | BA22: Mar | BB22: Apr | BC22: May | BD22: Jun | BE22: Jul | BF22: Aug | BG22: Sep | BH22: Oct | BI22: Nov | BJ22: Dec | BK22: Total %
A23: Ph 1a | B23: residential | C23: 0.01 | D23: 0.01 | E23: 0.01 | F23: 0.02 | G23: 0.02 | H23: 0.02 | I23: 0.02 | J23: 0.02 | K23: 0.02 | L23: 0.03 | M23: 0.03 | N23: 0.03 | O23: 0.03 | P23: 0.03 | Q23: 0.03 | R23: 0.04 | S23: 0.04 | T23: 0.04 | U23: 0.04 | V23: 0.04 | W23: 0.04 | X23: 0.04 | Y23: 0.03 | Z23: 0.03 | AA23: 0.03 | AB23: 0.03 | AC23: 0.03 | AD23: 0.02 | AE23: 0.02 | AF23: 0.02 | AG23: 0.02 | AH23: 0.02 | AI23: 0.02 | AJ23: 0.02 | AK23: 0.02 | AL23: 0.02 | AM23: 0.01 | AN23: 0.01 | AO23: 0.01 | AP23: 0.01 | AQ23: 0.01 | AR23: 0.01 | AS23: 0 | AT23: 0 | AU23: 0 | AV23: 0 | AW23: 0 | AX23: 0 | AY23: 0 | AZ23: 0 | BA23: 0 | BB23: 0 | BC23: 0 | BD23: 0 | BE23: 0 | BF23: 0 | BG23: 0 | BH23: 0 | BI23: 0 | BJ23: 0 | BK23: =SUM(C23:BJ23) -> 1
A24: Ph 1b | B24: residential | C24: 0.01 | D24: 0.01 | E24: 0.01 | F24: 0.02 | G24: 0.02 | H24: 0.02 | I24: 0.02 | J24: 0.02 | K24: 0.02 | L24: 0.03 | M24: 0.03 | N24: 0.03 | O24: 0.03 | P24: 0.03 | Q24: 0.03 | R24: 0.04 | S24: 0.04 | T24: 0.04 | U24: 0.04 | V24: 0.04 | W24: 0.04 | X24: 0.04 | Y24: 0.03 | Z24: 0.03 | AA24: 0.03 | AB24: 0.03 | AC24: 0.03 | AD24: 0.02 | AE24: 0.02 | AF24: 0.02 | AG24: 0.02 | AH24: 0.02 | AI24: 0.02 | AJ24: 0.02 | AK24: 0.02 | AL24: 0.02 | AM24: 0.01 | AN24: 0.01 | AO24: 0.01 | AP24: 0.01 | AQ24: 0.01 | AR24: 0.01 | AS24: 0 | AT24: 0 | AU24: 0 | AV24: 0 | AW24: 0 | AX24: 0 | AY24: 0 | AZ24: 0 | BA24: 0 | BB24: 0 | BC24: 0 | BD24: 0 | BE24: 0 | BF24: 0 | BG24: 0 | BH24: 0 | BI24: 0 | BJ24: 0 | BK24: =SUM(C24:BJ24) -> 1
A25: Ph 1c | B25: affordable | C25: 0.02 | D25: 0.02 | E25: 0.03 | F25: 0.03 | G25: 0.03 | H25: 0.05 | I25: 0.04 | J25: 0.04 | K25: 0.04 | L25: 0.04 | M25: 0.04 | N25: 0.04 | O25: 0.04 | P25: 0.04 | Q25: 0.04 | R25: 0.04 | S25: 0.03 | T25: 0.03 | U25: 0.03 | V25: 0.03 | W25: 0.03 | X25: 0.03 | Y25: 0.03 | Z25: 0.03 | AA25: 0.02 | AB25: 0.02 | AC25: 0.02 | AD25: 0.02 | AE25: 0.02 | AF25: 0.02 | AG25: 0.01 | AH25: 0.01 | AI25: 0.01 | AJ25: 0.01 | AK25: 0.01 | AL25: 0.01 | AM25: 0 | AN25: 0 | AO25: 0 | AP25: 0 | AQ25: 0 | AR25: 0 | AS25: 0 | AT25: 0 | AU25: 0 | AV25: 0 | AW25: 0 | AX25: 0 | AY25: 0 | AZ25: 0 | BA25: 0 | BB25: 0 | BC25: 0 | BD25: 0 | BE25: 0 | BF25: 0 | BG25: 0 | BH25: 0 | BI25: 0 | BJ25: 0 | BK25: =SUM(C25:BJ25) -> 1
A26: Ph 1d | B26: affordable | C26: 0.02 | D26: 0.02 | E26: 0.03 | F26: 0.03 | G26: 0.03 | H26: 0.05 | I26: 0.04 | J26: 0.04 | K26: 0.04 | L26: 0.04 | M26: 0.04 | N26: 0.04 | O26: 0.04 | P26: 0.04 | Q26: 0.04 | R26: 0.04 | S26: 0.03 | T26: 0.03 | U26: 0.03 | V26: 0.03 | W26: 0.03 | X26: 0.03 | Y26: 0.03 | Z26: 0.03 | AA26: 0.02 | AB26: 0.02 | AC26: 0.02 | AD26: 0.02 | AE26: 0.02 | AF26: 0.02 | AG26: 0.01 | AH26: 0.01 | AI26: 0.01 | AJ26: 0.01 | AK26: 0.01 | AL26: 0.01 | AM26: 0 | AN26: 0 | AO26: 0 | AP26: 0 | AQ26: 0 | AR26: 0 | AS26: 0 | AT26: 0 | AU26: 0 | AV26: 0 | AW26: 0 | AX26: 0 | AY26: 0 | AZ26: 0 | BA26: 0 | BB26: 0 | BC26: 0 | BD26: 0 | BE26: 0 | BF26: 0 | BG26: 0 | BH26: 0 | BI26: 0 | BJ26: 0 | BK26: =SUM(C26:BJ26) -> 1
A27: Ph 1e | B27: commercial | C27: 0.02 | D27: 0.03 | E27: 0.03 | F27: 0.04 | G27: 0.04 | H27: 0.04 | I27: 0.04 | J27: 0.04 | K27: 0.05 | L27: 0.05 | M27: 0.05 | N27: 0.05 | O27: 0.05 | P27: 0.05 | Q27: 0.05 | R27: 0.05 | S27: 0.04 | T27: 0.04 | U27: 0.04 | V27: 0.04 | W27: 0.03 | X27: 0.03 | Y27: 0.02 | Z27: 0.02 | AA27: 0.01 | AB27: 0.01 | AC27: 0.01 | AD27: 0.01 | AE27: 0.01 | AF27: 0.01 | AG27: 0 | AH27: 0 | AI27: 0 | AJ27: 0 | AK27: 0 | AL27: 0 | AM27: 0 | AN27: 0 | AO27: 0 | AP27: 0 | AQ27: 0 | AR27: 0 | AS27: 0 | AT27: 0 | AU27: 0 | AV27: 0 | AW27: 0 | AX27: 0 | AY27: 0 | AZ27: 0 | BA27: 0 | BB27: 0 | BC27: 0 | BD27: 0 | BE27: 0 | BF27: 0 | BG27: 0 | BH27: 0 | BI27: 0 | BJ27: 0 | BK27: =SUM(C27:BJ27) -> 1
A28: Ph 1f | B28: residential | C28: 0.01 | D28: 0.01 | E28: 0.01 | F28: 0.02 | G28: 0.02 | H28: 0.02 | I28: 0.02 | J28: 0.02 | K28: 0.02 | L28: 0.03 | M28: 0.03 | N28: 0.03 | O28: 0.03 | P28: 0.03 | Q28: 0.03 | R28: 0.04 | S28: 0.04 | T28: 0.04 | U28: 0.04 | V28: 0.04 | W28: 0.04 | X28: 0.04 | Y28: 0.03 | Z28: 0.03 | AA28: 0.03 | AB28: 0.03 | AC28: 0.03 | AD28: 0.02 | AE28: 0.02 | AF28: 0.02 | AG28: 0.02 | AH28: 0.02 | AI28: 0.02 | AJ28: 0.02 | AK28: 0.02 | AL28: 0.02 | AM28: 0.01 | AN28: 0.01 | AO28: 0.01 | AP28: 0.01 | AQ28: 0.01 | AR28: 0.01 | AS28: 0 | AT28: 0 | AU28: 0 | AV28: 0 | AW28: 0 | AX28: 0 | AY28: 0 | AZ28: 0 | BA28: 0 | BB28: 0 | BC28: 0 | BD28: 0 | BE28: 0 | BF28: 0 | BG28: 0 | BH28: 0 | BI28: 0 | BJ28: 0 | BK28: =SUM(C28:BJ28) -> 1
A29: Ph 1g | B29: commercial | C29: 0.02 | D29: 0.03 | E29: 0.03 | F29: 0.04 | G29: 0.04 | H29: 0.04 | I29: 0.04 | J29: 0.04 | K29: 0.05 | L29: 0.05 | M29: 0.05 | N29: 0.05 | O29: 0.05 | P29: 0.05 | Q29: 0.05 | R29: 0.05 | S29: 0.04 | T29: 0.04 | U29: 0.04 | V29: 0.04 | W29: 0.03 | X29: 0.03 | Y29: 0.02 | Z29: 0.02 | AA29: 0.01 | AB29: 0.01 | AC29: 0.01 | AD29: 0.01 | AE29: 0.01 | AF29: 0.01 | AG29: 0 | AH29: 0 | AI29: 0 | AJ29: 0 | AK29: 0 | AL29: 0 | AM29: 0 | AN29: 0 | AO29: 0 | AP29: 0 | AQ29: 0 | AR29: 0 | AS29: 0 | AT29: 0 | AU29: 0 | AV29: 0 | AW29: 0 | AX29: 0 | AY29: 0 | AZ29: 0 | BA29: 0 | BB29: 0 | BC29: 0 | BD29: 0 | BE29: 0 | BF29: 0 | BG29: 0 | BH29: 0 | BI29: 0 | BJ29: 0 | BK29: =SUM(C29:BJ29) -> 1
A30: Ph 1h | B30: commercial | C30: 0.02 | D30: 0.03 | E30: 0.03 | F30: 0.04 | G30: 0.04 | H30: 0.04 | I30: 0.04 | J30: 0.04 | K30: 0.05 | L30: 0.05 | M30: 0.05 | N30: 0.05 | O30: 0.05 | P30: 0.05 | Q30: 0.05 | R30: 0.05 | S30: 0.04 | T30: 0.04 | U30: 0.04 | V30: 0.04 | W30: 0.03 | X30: 0.03 | Y30: 0.02 | Z30: 0.02 | AA30: 0.01 | AB30: 0.01 | AC30: 0.01 | AD30: 0.01 | AE30: 0.01 | AF30: 0.01 | AG30: 0 | AH30: 0 | AI30: 0 | AJ30: 0 | AK30: 0 | AL30: 0 | AM30: 0 | AN30: 0 | AO30: 0 | AP30: 0 | AQ30: 0 | AR30: 0 | AS30: 0 | AT30: 0 | AU30: 0 | AV30: 0 | AW30: 0 | AX30: 0 | AY30: 0 | AZ30: 0 | BA30: 0 | BB30: 0 | BC30: 0 | BD30: 0 | BE30: 0 | BF30: 0 | BG30: 0 | BH30: 0 | BI30: 0 | BJ30: 0 | BK30: =SUM(C30:BJ30) -> 1
A31: Ph 2a | B31: residential | C31: 0.01 | D31: 0.01 | E31: 0.01 | F31: 0.02 | G31: 0.02 | H31: 0.02 | I31: 0.02 | J31: 0.02 | K31: 0.02 | L31: 0.03 | M31: 0.03 | N31: 0.03 | O31: 0.03 | P31: 0.03 | Q31: 0.03 | R31: 0.04 | S31: 0.04 | T31: 0.04 | U31: 0.04 | V31: 0.04 | W31: 0.04 | X31: 0.04 | Y31: 0.03 | Z31: 0.03 | AA31: 0.03 | AB31: 0.03 | AC31: 0.03 | AD31: 0.02 | AE31: 0.02 | AF31: 0.02 | AG31: 0.02 | AH31: 0.02 | AI31: 0.02 | AJ31: 0.02 | AK31: 0.02 | AL31: 0.02 | AM31: 0.01 | AN31: 0.01 | AO31: 0.01 | AP31: 0.01 | AQ31: 0.01 | AR31: 0.01 | AS31: 0 | AT31: 0 | AU31: 0 | AV31: 0 | AW31: 0 | AX31: 0 | AY31: 0 | AZ31: 0 | BA31: 0 | BB31: 0 | BC31: 0 | BD31: 0 | BE31: 0 | BF31: 0 | BG31: 0 | BH31: 0 | BI31: 0 | BJ31: 0 | BK31: =SUM(C31:BJ31) -> 1
A32: Ph 2b | B32: residential | C32: 0.01 | D32: 0.01 | E32: 0.01 | F32: 0.02 | G32: 0.02 | H32: 0.02 | I32: 0.02 | J32: 0.02 | K32: 0.02 | L32: 0.03 | M32: 0.03 | N32: 0.03 | O32: 0.03 | P32: 0.03 | Q32: 0.03 | R32: 0.04 | S32: 0.04 | T32: 0.04 | U32: 0.04 | V32: 0.04 | W32: 0.04 | X32: 0.04 | Y32: 0.03 | Z32: 0.03 | AA32: 0.03 | AB32: 0.03 | AC32: 0.03 | AD32: 0.02 | AE32: 0.02 | AF32: 0.02 | AG32: 0.02 | AH32: 0.02 | AI32: 0.02 | AJ32: 0.02 | AK32: 0.02 | AL32: 0.02 | AM32: 0.01 | AN32: 0.01 | AO32: 0.01 | AP32: 0.01 | AQ32: 0.01 | AR32: 0.01 | AS32: 0 | AT32: 0 | AU32: 0 | AV32: 0 | AW32: 0 | AX32: 0 | AY32: 0 | AZ32: 0 | BA32: 0 | BB32: 0 | BC32: 0 | BD32: 0 | BE32: 0 | BF32: 0 | BG32: 0 | BH32: 0 | BI32: 0 | BJ32: 0 | BK32: =SUM(C32:BJ32) -> 1
A33: Ph 2c | B33: residential | C33: 0.01 | D33: 0.01 | E33: 0.01 | F33: 0.02 | G33: 0.02 | H33: 0.02 | I33: 0.02 | J33: 0.02 | K33: 0.02 | L33: 0.03 | M33: 0.03 | N33: 0.03 | O33: 0.03 | P33: 0.03 | Q33: 0.03 | R33: 0.04 | S33: 0.04 | T33: 0.04 | U33: 0.04 | V33: 0.04 | W33: 0.04 | X33: 0.04 | Y33: 0.03 | Z33: 0.03 | AA33: 0.03 | AB33: 0.03 | AC33: 0.03 | AD33: 0.02 | AE33: 0.02 | AF33: 0.02 | AG33: 0.02 | AH33: 0.02 | AI33: 0.02 | AJ33: 0.02 | AK33: 0.02 | AL33: 0.02 | AM33: 0.01 | AN33: 0.01 | AO33: 0.01 | AP33: 0.01 | AQ33: 0.01 | AR33: 0.01 | AS33: 0 | AT33: 0 | AU33: 0 | AV33: 0 | AW33: 0 | AX33: 0 | AY33: 0 | AZ33: 0 | BA33: 0 | BB33: 0 | BC33: 0 | BD33: 0 | BE33: 0 | BF33: 0 | BG33: 0 | BH33: 0 | BI33: 0 | BJ33: 0 | BK33: =SUM(C33:BJ33) -> 1
A34: Ph 2d | B34: residential | C34: 0.01 | D34: 0.01 | E34: 0.01 | F34: 0.02 | G34: 0.02 | H34: 0.02 | I34: 0.02 | J34: 0.02 | K34: 0.02 | L34: 0.03 | M34: 0.03 | N34: 0.03 | O34: 0.03 | P34: 0.03 | Q34: 0.03 | R34: 0.04 | S34: 0.04 | T34: 0.04 | U34: 0.04 | V34: 0.04 | W34: 0.04 | X34: 0.04 | Y34: 0.03 | Z34: 0.03 | AA34: 0.03 | AB34: 0.03 | AC34: 0.03 | AD34: 0.02 | AE34: 0.02 | AF34: 0.02 | AG34: 0.02 | AH34: 0.02 | AI34: 0.02 | AJ34: 0.02 | AK34: 0.02 | AL34: 0.02 | AM34: 0.01 | AN34: 0.01 | AO34: 0.01 | AP34: 0.01 | AQ34: 0.01 | AR34: 0.01 | AS34: 0 | AT34: 0 | AU34: 0 | AV34: 0 | AW34: 0 | AX34: 0 | AY34: 0 | AZ34: 0 | BA34: 0 | BB34: 0 | BC34: 0 | BD34: 0 | BE34: 0 | BF34: 0 | BG34: 0 | BH34: 0 | BI34: 0 | BJ34: 0 | BK34: =SUM(C34:BJ34) -> 1
... A40: Ph 2j | B40: commercial | C40: 0.02 | D40: 0.03 | E40: 0.03 | F40: 0.04 | G40: 0.04 | H40: 0.04 | I40: 0.04 | J40: 0.04 | K40: 0.05 | L40: 0.05 | M40: 0.05 | N40: 0.05 | O40: 0.05 | P40: 0.05 | Q40: 0.05 | R40: 0.05 | S40: 0.04 | T40: 0.04 | U40: 0.04 | V40: 0.04 | W40: 0.03 | X40: 0.03 | Y40: 0.02 | Z40: 0.02 | AA40: 0.01 | AB40: 0.01 | AC40: 0.01 | AD40: 0.01 | AE40: 0.01 | AF40: 0.01 | AG40: 0 | AH40: 0 | AI40: 0 | AJ40: 0 | AK40: 0 | AL40: 0 | AM40: 0 | AN40: 0 | AO40: 0 | AP40: 0 | AQ40: 0 | AR40: 0 | AS40: 0 | AT40: 0 | AU40: 0 | AV40: 0 | AW40: 0 | AX40: 0 | AY40: 0 | AZ40: 0 | BA40: 0 | BB40: 0 | BC40: 0 | BD40: 0 | BE40: 0 | BF40: 0 | BG40: 0 | BH40: 0 | BI40: 0 | BJ40: 0 | BK40: =SUM(C40:BJ40) -> 1
A42: C. SALES RECEIPTS (RM'000) — NDV × Monthly Absorption %
A43: Phase | B43: NDV (RM'000) | C43: Jan | D43: Feb | E43: Mar | F43: Apr | G43: May | H43: Jun | I43: Jul | J43: Aug | K43: Sep | L43: Oct | M43: Nov | N43: Dec | O43: Jan | P43: Feb | Q43: Mar | R43: Apr | S43: May | T43: Jun | U43: Jul | V43: Aug | W43: Sep | X43: Oct | Y43: Nov | Z43: Dec | AA43: Jan | AB43: Feb | AC43: Mar | AD43: Apr | AE43: May | AF43: Jun | AG43: Jul | AH43: Aug | AI43: Sep | AJ43: Oct | AK43: Nov | AL43: Dec | AM43: Jan | AN43: Feb | AO43: Mar | AP43: Apr | AQ43: May | AR43: Jun | AS43: Jul | AT43: Aug | AU43: Sep | AV43: Oct | AW43: Nov | AX43: Dec | AY43: Jan | AZ43: Feb | BA43: Mar | BB43: Apr | BC43: May | BD43: Jun | BE43: Jul | BF43: Aug | BG43: Sep | BH43: Oct | BI43: Nov | BJ43: Dec | BK43: Total
A44: Ph 1a | B44: ='Feasibility Study'!I73/1000 | C44: =IF($B$44=0,0,$B$44*C23) | D44: =IF($B$44=0,0,$B$44*D23) | E44: =IF($B$44=0,0,$B$44*E23) | F44: =IF($B$44=0,0,$B$44*F23) | G44: =IF($B$44=0,0,$B$44*G23) | H44: =IF($B$44=0,0,$B$44*H23) | I44: =IF($B$44=0,0,$B$44*I23) | J44: =IF($B$44=0,0,$B$44*J23) | ... BJ44: =IF($B$44=0,0,$B$44*BJ23) | BK44: =SUM(C44:BJ44)
A45: Ph 1b | B45: ='Feasibility Study'!K73/1000 | C45: =IF($B$45=0,0,$B$45*C24) | D45: =IF($B$45=0,0,$B$45*D24) | E45: =IF($B$45=0,0,$B$45*E24) | F45: =IF($B$45=0,0,$B$45*F24) | G45: =IF($B$45=0,0,$B$45*G24) | H45: =IF($B$45=0,0,$B$45*H24) | I45: =IF($B$45=0,0,$B$45*I24) | J45: =IF($B$45=0,0,$B$45*J24) | ... BJ45: =IF($B$45=0,0,$B$45*BJ24) | BK45: =SUM(C45:BJ45)
A46: Ph 1c | B46: ='Feasibility Study'!M73/1000 | C46: =IF($B$46=0,0,$B$46*C25) | D46: =IF($B$46=0,0,$B$46*D25) | E46: =IF($B$46=0,0,$B$46*E25) | F46: =IF($B$46=0,0,$B$46*F25) | G46: =IF($B$46=0,0,$B$46*G25) | H46: =IF($B$46=0,0,$B$46*H25) | I46: =IF($B$46=0,0,$B$46*I25) | J46: =IF($B$46=0,0,$B$46*J25) | ... BJ46: =IF($B$46=0,0,$B$46*BJ25) | BK46: =SUM(C46:BJ46)
A47: Ph 1d | B47: ='Feasibility Study'!O73/1000 | C47: =IF($B$47=0,0,$B$47*C26) | D47: =IF($B$47=0,0,$B$47*D26) | E47: =IF($B$47=0,0,$B$47*E26) | F47: =IF($B$47=0,0,$B$47*F26) | G47: =IF($B$47=0,0,$B$47*G26) | H47: =IF($B$47=0,0,$B$47*H26) | I47: =IF($B$47=0,0,$B$47*I26) | J47: =IF($B$47=0,0,$B$47*J26) | ... BJ47: =IF($B$47=0,0,$B$47*BJ26) | BK47: =SUM(C47:BJ47)
A48: Ph 1e | B48: ='Feasibility Study'!Q73/1000 | C48: =IF($B$48=0,0,$B$48*C27) | D48: =IF($B$48=0,0,$B$48*D27) | E48: =IF($B$48=0,0,$B$48*E27) | F48: =IF($B$48=0,0,$B$48*F27) | G48: =IF($B$48=0,0,$B$48*G27) | H48: =IF($B$48=0,0,$B$48*H27) | I48: =IF($B$48=0,0,$B$48*I27) | J48: =IF($B$48=0,0,$B$48*J27) | ... BJ48: =IF($B$48=0,0,$B$48*BJ27) | BK48: =SUM(C48:BJ48)
A49: Ph 1f | B49: ='Feasibility Study'!S73/1000 | C49: =IF($B$49=0,0,$B$49*C28) | D49: =IF($B$49=0,0,$B$49*D28) | E49: =IF($B$49=0,0,$B$49*E28) | F49: =IF($B$49=0,0,$B$49*F28) | G49: =IF($B$49=0,0,$B$49*G28) | H49: =IF($B$49=0,0,$B$49*H28) | I49: =IF($B$49=0,0,$B$49*I28) | J49: =IF($B$49=0,0,$B$49*J28) | ... BJ49: =IF($B$49=0,0,$B$49*BJ28) | BK49: =SUM(C49:BJ49)
A50: Ph 1g | B50: ='Feasibility Study'!W73/1000 | C50: =IF($B$50=0,0,$B$50*C29) | D50: =IF($B$50=0,0,$B$50*D29) | E50: =IF($B$50=0,0,$B$50*E29) | F50: =IF($B$50=0,0,$B$50*F29) | G50: =IF($B$50=0,0,$B$50*G29) | H50: =IF($B$50=0,0,$B$50*H29) | I50: =IF($B$50=0,0,$B$50*I29) | J50: =IF($B$50=0,0,$B$50*J29) | ... BJ50: =IF($B$50=0,0,$B$50*BJ29) | BK50: =SUM(C50:BJ50)
A51: Ph 1h | B51: ='Feasibility Study'!Y73/1000 | C51: =IF($B$51=0,0,$B$51*C30) | D51: =IF($B$51=0,0,$B$51*D30) | E51: =IF($B$51=0,0,$B$51*E30) | F51: =IF($B$51=0,0,$B$51*F30) | G51: =IF($B$51=0,0,$B$51*G30) | H51: =IF($B$51=0,0,$B$51*H30) | I51: =IF($B$51=0,0,$B$51*I30) | J51: =IF($B$51=0,0,$B$51*J30) | ... BJ51: =IF($B$51=0,0,$B$51*BJ30) | BK51: =SUM(C51:BJ51)
A52: Ph 2a | B52: ='Feasibility Study'!AC73/1000 | C52: =IF($B$52=0,0,$B$52*C31) | D52: =IF($B$52=0,0,$B$52*D31) | E52: =IF($B$52=0,0,$B$52*E31) | F52: =IF($B$52=0,0,$B$52*F31) | G52: =IF($B$52=0,0,$B$52*G31) | H52: =IF($B$52=0,0,$B$52*H31) | I52: =IF($B$52=0,0,$B$52*I31) | J52: =IF($B$52=0,0,$B$52*J31) | ... BJ52: =IF($B$52=0,0,$B$52*BJ31) | BK52: =SUM(C52:BJ52)
A53: Ph 2b | B53: ='Feasibility Study'!AE73/1000 | C53: =IF($B$53=0,0,$B$53*C32) | D53: =IF($B$53=0,0,$B$53*D32) | E53: =IF($B$53=0,0,$B$53*E32) | F53: =IF($B$53=0,0,$B$53*F32) | G53: =IF($B$53=0,0,$B$53*G32) | H53: =IF($B$53=0,0,$B$53*H32) | I53: =IF($B$53=0,0,$B$53*I32) | J53: =IF($B$53=0,0,$B$53*J32) | ... BJ53: =IF($B$53=0,0,$B$53*BJ32) | BK53: =SUM(C53:BJ53)
A54: Ph 2c | B54: ='Feasibility Study'!AG73/1000 | C54: =IF($B$54=0,0,$B$54*C33) | D54: =IF($B$54=0,0,$B$54*D33) | E54: =IF($B$54=0,0,$B$54*E33) | F54: =IF($B$54=0,0,$B$54*F33) | G54: =IF($B$54=0,0,$B$54*G33) | H54: =IF($B$54=0,0,$B$54*H33) | I54: =IF($B$54=0,0,$B$54*I33) | J54: =IF($B$54=0,0,$B$54*J33) | ... BJ54: =IF($B$54=0,0,$B$54*BJ33) | BK54: =SUM(C54:BJ54)
A55: Ph 2d | B55: ='Feasibility Study'!AI73/1000 | C55: =IF($B$55=0,0,$B$55*C34) | D55: =IF($B$55=0,0,$B$55*D34) | E55: =IF($B$55=0,0,$B$55*E34) | F55: =IF($B$55=0,0,$B$55*F34) | G55: =IF($B$55=0,0,$B$55*G34) | H55: =IF($B$55=0,0,$B$55*H34) | I55: =IF($B$55=0,0,$B$55*I34) | J55: =IF($B$55=0,0,$B$55*J34) | ... BJ55: =IF($B$55=0,0,$B$55*BJ34) | BK55: =SUM(C55:BJ55)
A56: Ph 2e | B56: ='Feasibility Study'!AK73/1000 | C56: =IF($B$56=0,0,$B$56*C35) | D56: =IF($B$56=0,0,$B$56*D35) | E56: =IF($B$56=0,0,$B$56*E35) | F56: =IF($B$56=0,0,$B$56*F35) | G56: =IF($B$56=0,0,$B$56*G35) | H56: =IF($B$56=0,0,$B$56*H35) | I56: =IF($B$56=0,0,$B$56*I35) | J56: =IF($B$56=0,0,$B$56*J35) | ... BJ56: =IF($B$56=0,0,$B$56*BJ35) | BK56: =SUM(C56:BJ56)
A57: Ph 2f | B57: ='Feasibility Study'!AM73/1000 | C57: =IF($B$57=0,0,$B$57*C36) | D57: =IF($B$57=0,0,$B$57*D36) | E57: =IF($B$57=0,0,$B$57*E36) | F57: =IF($B$57=0,0,$B$57*F36) | G57: =IF($B$57=0,0,$B$57*G36) | H57: =IF($B$57=0,0,$B$57*H36) | I57: =IF($B$57=0,0,$B$57*I36) | J57: =IF($B$57=0,0,$B$57*J36) | ... BJ57: =IF($B$57=0,0,$B$57*BJ36) | BK57: =SUM(C57:BJ57)
A58: Ph 2g1 | B58: ='Feasibility Study'!AO73/1000 | C58: =IF($B$58=0,0,$B$58*C37) | D58: =IF($B$58=0,0,$B$58*D37) | E58: =IF($B$58=0,0,$B$58*E37) | F58: =IF($B$58=0,0,$B$58*F37) | G58: =IF($B$58=0,0,$B$58*G37) | H58: =IF($B$58=0,0,$B$58*H37) | I58: =IF($B$58=0,0,$B$58*I37) | J58: =IF($B$58=0,0,$B$58*J37) | ... BJ58: =IF($B$58=0,0,$B$58*BJ37) | BK58: =SUM(C58:BJ58)
A59: Ph 2g2 | B59: ='Feasibility Study'!AQ73/1000 | C59: =IF($B$59=0,0,$B$59*C38) | D59: =IF($B$59=0,0,$B$59*D38) | E59: =IF($B$59=0,0,$B$59*E38) | F59: =IF($B$59=0,0,$B$59*F38) | G59: =IF($B$59=0,0,$B$59*G38) | H59: =IF($B$59=0,0,$B$59*H38) | I59: =IF($B$59=0,0,$B$59*I38) | J59: =IF($B$59=0,0,$B$59*J38) | ... BJ59: =IF($B$59=0,0,$B$59*BJ38) | BK59: =SUM(C59:BJ59)
A60: Ph 2h | B60: ='Feasibility Study'!AU73/1000 | C60: =IF($B$60=0,0,$B$60*C39) | D60: =IF($B$60=0,0,$B$60*D39) | E60: =IF($B$60=0,0,$B$60*E39) | F60: =IF($B$60=0,0,$B$60*F39) | G60: =IF($B$60=0,0,$B$60*G39) | H60: =IF($B$60=0,0,$B$60*H39) | I60: =IF($B$60=0,0,$B$60*I39) | J60: =IF($B$60=0,0,$B$60*J39) | ... BJ60: =IF($B$60=0,0,$B$60*BJ39) | BK60: =SUM(C60:BJ60)
A61: Ph 2j | B61: ='Feasibility Study'!AW73/1000 | C61: =IF($B$61=0,0,$B$61*C40) | D61: =IF($B$61=0,0,$B$61*D40) | E61: =IF($B$61=0,0,$B$61*E40) | F61: =IF($B$61=0,0,$B$61*F40) | G61: =IF($B$61=0,0,$B$61*G40) | H61: =IF($B$61=0,0,$B$61*H40) | I61: =IF($B$61=0,0,$B$61*I40) | J61: =IF($B$61=0,0,$B$61*J40) | ... BJ61: =IF($B$61=0,0,$B$61*BJ40) | BK61: =SUM(C61:BJ61)
A62: TOTAL SALES RECEIPTS | C62: =SUM(C44:C61) | D62: =SUM(D44:D61) | E62: =SUM(E44:E61) | F62: =SUM(F44:F61) | G62: =SUM(G44:G61) | H62: =SUM(H44:H61) | I62: =SUM(I44:I61) | J62: =SUM(J44:J61) | ... BJ62: =SUM(BJ44:BJ61) | BK62: =SUM(C62:BJ62)
A64: D. LAND COST (RM'000) — Deposit M1, Balance spread M2–M12
A65: Item | B65: Total | C65: Jan | D65: Feb | E65: Mar | F65: Apr | G65: May | H65: Jun | I65: Jul | J65: Aug | K65: Sep | L65: Oct | M65: Nov | N65: Dec | O65: Jan | P65: Feb | Q65: Mar | R65: Apr | S65: May | T65: Jun | U65: Jul | V65: Aug | W65: Sep | X65: Oct | Y65: Nov | Z65: Dec | AA65: Jan | AB65: Feb | AC65: Mar | AD65: Apr | AE65: May | AF65: Jun | AG65: Jul | AH65: Aug | AI65: Sep | AJ65: Oct | AK65: Nov | AL65: Dec | AM65: Jan | AN65: Feb | AO65: Mar | AP65: Apr | AQ65: May | AR65: Jun | AS65: Jul | AT65: Aug | AU65: Sep | AV65: Oct | AW65: Nov | AX65: Dec | AY65: Jan | AZ65: Feb | BA65: Mar | BB65: Apr | BC65: May | BD65: Jun | BE65: Jul | BF65: Aug | BG65: Sep | BH65: Oct | BI65: Nov | BJ65: Dec | BK65: Total
A66: Deposit (10%) | B66: ='Feasibility Study'!AY82/1000*0.1 -> 0 | C66: =$B$66/1 -> 0 | D66: - | E66: - | F66: - | G66: - | H66: - | I66: - | J66: - | K66: - | L66: - | M66: - | N66: - | O66: - | P66: - | Q66: - | R66: - | S66: - | T66: - | U66: - | V66: - | W66: - | X66: - | Y66: - | Z66: - | AA66: - | AB66: - | AC66: - | AD66: - | AE66: - | AF66: - | AG66: - | AH66: - | AI66: - | AJ66: - | AK66: - | AL66: - | AM66: - | AN66: - | AO66: - | AP66: - | AQ66: - | AR66: - | AS66: - | AT66: - | AU66: - | AV66: - | AW66: - | AX66: - | AY66: - | AZ66: - | BA66: - | BB66: - | BC66: - | BD66: - | BE66: - | BF66: - | BG66: - | BH66: - | BI66: - | BJ66: - | BK66: =SUM(C66:BJ66) -> 0
A67: Balance SPA — M2–M6 | B67: ='Feasibility Study'!AY82/1000*0.45 -> 0 | C67: - | D67: =$B$67/5 -> 0 | E67: =$B$67/5 -> 0 | F67: =$B$67/5 -> 0 | G67: =$B$67/5 -> 0 | H67: =$B$67/5 -> 0 | I67: - | J67: - | K67: - | L67: - | M67: - | N67: - | O67: - | P67: - | Q67: - | R67: - | S67: - | T67: - | U67: - | V67: - | W67: - | X67: - | Y67: - | Z67: - | AA67: - | AB67: - | AC67: - | AD67: - | AE67: - | AF67: - | AG67: - | AH67: - | AI67: - | AJ67: - | AK67: - | AL67: - | AM67: - | AN67: - | AO67: - | AP67: - | AQ67: - | AR67: - | AS67: - | AT67: - | AU67: - | AV67: - | AW67: - | AX67: - | AY67: - | AZ67: - | BA67: - | BB67: - | BC67: - | BD67: - | BE67: - | BF67: - | BG67: - | BH67: - | BI67: - | BJ67: - | BK67: =SUM(C67:BJ67) -> 0
A68: Balance SPA — M7–M12 | B68: ='Feasibility Study'!AY82/1000*0.45 -> 0 | C68: - | D68: - | E68: - | F68: - | G68: - | H68: - | I68: =$B$68/6 -> 0 | J68: =$B$68/6 -> 0 | K68: =$B$68/6 -> 0 | L68: =$B$68/6 -> 0 | M68: =$B$68/6 -> 0 | N68: =$B$68/6 -> 0 | O68: - | P68: - | Q68: - | R68: - | S68: - | T68: - | U68: - | V68: - | W68: - | X68: - | Y68: - | Z68: - | AA68: - | AB68: - | AC68: - | AD68: - | AE68: - | AF68: - | AG68: - | AH68: - | AI68: - | AJ68: - | AK68: - | AL68: - | AM68: - | AN68: - | AO68: - | AP68: - | AQ68: - | AR68: - | AS68: - | AT68: - | AU68: - | AV68: - | AW68: - | AX68: - | AY68: - | AZ68: - | BA68: - | BB68: - | BC68: - | BD68: - | BE68: - | BF68: - | BG68: - | BH68: - | BI68: - | BJ68: - | BK68: =SUM(C68:BJ68) -> 0
A69: Land conversion premium | B69: ='Feasibility Study'!AY82/1000*0.15 -> 0 | C69: - | D69: - | E69: - | F69: - | G69: - | H69: - | I69: - | J69: - | K69: - | L69: - | M69: - | N69: =$B$69/1 -> 0 | O69: - | P69: - | Q69: - | R69: - | S69: - | T69: - | U69: - | V69: - | W69: - | X69: - | Y69: - | Z69: - | AA69: - | AB69: - | AC69: - | AD69: - | AE69: - | AF69: - | AG69: - | AH69: - | AI69: - | AJ69: - | AK69: - | AL69: - | AM69: - | AN69: - | AO69: - | AP69: - | AQ69: - | AR69: - | AS69: - | AT69: - | AU69: - | AV69: - | AW69: - | AX69: - | AY69: - | AZ69: - | BA69: - | BB69: - | BC69: - | BD69: - | BE69: - | BF69: - | BG69: - | BH69: - | BI69: - | BJ69: - | BK69: =SUM(C69:BJ69) -> 0
A70: TOTAL LAND COST | C70: =IF(ISNUMBER(C66),C66,0)+IF(ISNUMBER(C67),C67,0)+IF(ISNUMBER(C68),C68,0)+IF(ISNUMBER(C69),C69,0) -> 0 | D70: =IF(ISNUMBER(D66),D66,0)+IF(ISNUMBER(D67),D67,0)+IF(ISNUMBER(D68),D68,0)+IF(ISNUMBER(D69),D69,0) -> 0 | E70: =IF(ISNUMBER(E66),E66,0)+IF(ISNUMBER(E67),E67,0)+IF(ISNUMBER(E68),E68,0)+IF(ISNUMBER(E69),E69,0) -> 0 | F70: =IF(ISNUMBER(F66),F66,0)+IF(ISNUMBER(F67),F67,0)+IF(ISNUMBER(F68),F68,0)+IF(ISNUMBER(F69),F69,0) -> 0 | G70: =IF(ISNUMBER(G66),G66,0)+IF(ISNUMBER(G67),G67,0)+IF(ISNUMBER(G68),G68,0)+IF(ISNUMBER(G69),G69,0) -> 0 | H70: =IF(ISNUMBER(H66),H66,0)+IF(ISNUMBER(H67),H67,0)+IF(ISNUMBER(H68),H68,0)+IF(ISNUMBER(H69),H69,0) -> 0 | I70: =IF(ISNUMBER(I66),I66,0)+IF(ISNUMBER(I67),I67,0)+IF(ISNUMBER(I68),I68,0)+IF(ISNUMBER(I69),I69,0) -> 0 | J70: =IF(ISNUMBER(J66),J66,0)+IF(ISNUMBER(J67),J67,0)+IF(ISNUMBER(J68),J68,0)+IF(ISNUMBER(J69),J69,0) -> 0 | ... BJ70: =IF(ISNUMBER(BJ66),BJ66,0)+IF(ISNUMBER(BJ67),BJ67,0)+IF(ISNUMBER(BJ68),BJ68,0)+IF(ISNUMBER(BJ69),BJ69,0) -> 0 | BK70: =SUM(C70:BJ70) -> 0
A72: E. CONSTRUCTION COST (RM'000) — S-curve drawdown over 48 months
A73: Item | B73: Total (RM'000) | C73: Jan | D73: Feb | E73: Mar | F73: Apr | G73: May | H73: Jun | I73: Jul | J73: Aug | K73: Sep | L73: Oct | M73: Nov | N73: Dec | O73: Jan | P73: Feb | Q73: Mar | R73: Apr | S73: May | T73: Jun | U73: Jul | V73: Aug | W73: Sep | X73: Oct | Y73: Nov | Z73: Dec | AA73: Jan | AB73: Feb | AC73: Mar | AD73: Apr | AE73: May | AF73: Jun | AG73: Jul | AH73: Aug | AI73: Sep | AJ73: Oct | AK73: Nov | AL73: Dec | AM73: Jan | AN73: Feb | AO73: Mar | AP73: Apr | AQ73: May | AR73: Jun | AS73: Jul | AT73: Aug | AU73: Sep | AV73: Oct | AW73: Nov | AX73: Dec | AY73: Jan | AZ73: Feb | BA73: Mar | BB73: Apr | BC73: May | BD73: Jun | BE73: Jul | BF73: Aug | BG73: Sep | BH73: Oct | BI73: Nov | BJ73: Dec | BK73: Total
A74: Building works — residential (55%) | B74: ='Feasibility Study'!AY87/1000*0.55 -> #DIV/0! | C74: =$B$74*0.011013 -> #DIV/0! | D74: =$B$74*0.013216 -> #DIV/0! | E74: =$B$74*0.015418 -> #DIV/0! | F74: =$B$74*0.017621 -> #DIV/0! | G74: =$B$74*0.019824 -> #DIV/0! | H74: =$B$74*0.022026 -> #DIV/0! | I74: =$B$74*0.024229 -> #DIV/0! | J74: =$B$74*0.026432 -> #DIV/0! | K74: =$B$74*0.028634 -> #DIV/0! | L74: =$B$74*0.028634 -> #DIV/0! | M74: =$B$74*0.028634 -> #DIV/0! | N74: =$B$74*0.028634 -> #DIV/0! | O74: =$B$74*0.030837 -> #DIV/0! | P74: =$B$74*0.030837 -> #DIV/0! | Q74: =$B$74*0.030837 -> #DIV/0! | R74: =$B$74*0.030837 -> #DIV/0! | S74: =$B$74*0.030837 -> #DIV/0! | T74: =$B$74*0.030837 -> #DIV/0! | U74: =$B$74*0.030837 -> #DIV/0! | V74: =$B$74*0.030837 -> #DIV/0! | W74: =$B$74*0.028634 -> #DIV/0! | X74: =$B$74*0.028634 -> #DIV/0! | Y74: =$B$74*0.026432 -> #DIV/0! | Z74: =$B$74*0.026432 -> #DIV/0! | AA74: =$B$74*0.026432 -> #DIV/0! | AB74: =$B$74*0.024229 -> #DIV/0! | AC74: =$B$74*0.024229 -> #DIV/0! | AD74: =$B$74*0.024229 -> #DIV/0! | AE74: =$B$74*0.022026 -> #DIV/0! | AF74: =$B$74*0.022026 -> #DIV/0! | AG74: =$B$74*0.022026 -> #DIV/0! | AH74: =$B$74*0.019824 -> #DIV/0! | AI74: =$B$74*0.019824 -> #DIV/0! | AJ74: =$B$74*0.019824 -> #DIV/0! | AK74: =$B$74*0.017621 -> #DIV/0! | AL74: =$B$74*0.017621 -> #DIV/0! | AM74: =$B$74*0.017621 -> #DIV/0! | AN74: =$B$74*0.015418 -> #DIV/0! | AO74: =$B$74*0.015418 -> #DIV/0! | AP74: =$B$74*0.013216 -> #DIV/0! | AQ74: =$B$74*0.013216 -> #DIV/0! | AR74: =$B$74*0.011013 -> #DIV/0! | AS74: =$B$74*0.011013 -> #DIV/0! | AT74: =$B$74*0.008811 -> #DIV/0! | AU74: =$B$74*0.006608 -> #DIV/0! | AV74: =$B$74*0.004405 -> #DIV/0! | AW74: =$B$74*0.002203 -> #DIV/0! | AX74: - | AY74: - | AZ74: - | BA74: - | BB74: - | BC74: - | BD74: - | BE74: - | BF74: - | BG74: - | BH74: - | BI74: - | BJ74: - | BK74: =SUM(C74:BJ74) -> #DIV/0!
A75: Building works — commercial (15%) | B75: ='Feasibility Study'!AY87/1000*0.15 -> #DIV/0! | C75: =$B$75*0.011013 -> #DIV/0! | D75: =$B$75*0.013216 -> #DIV/0! | E75: =$B$75*0.015418 -> #DIV/0! | F75: =$B$75*0.017621 -> #DIV/0! | G75: =$B$75*0.019824 -> #DIV/0! | H75: =$B$75*0.022026 -> #DIV/0! | I75: =$B$75*0.024229 -> #DIV/0! | J75: =$B$75*0.026432 -> #DIV/0! | K75: =$B$75*0.028634 -> #DIV/0! | L75: =$B$75*0.028634 -> #DIV/0! | M75: =$B$75*0.028634 -> #DIV/0! | N75: =$B$75*0.028634 -> #DIV/0! | O75: =$B$75*0.030837 -> #DIV/0! | P75: =$B$75*0.030837 -> #DIV/0! | Q75: =$B$75*0.030837 -> #DIV/0! | R75: =$B$75*0.030837 -> #DIV/0! | S75: =$B$75*0.030837 -> #DIV/0! | T75: =$B$75*0.030837 -> #DIV/0! | U75: =$B$75*0.030837 -> #DIV/0! | V75: =$B$75*0.030837 -> #DIV/0! | W75: =$B$75*0.028634 -> #DIV/0! | X75: =$B$75*0.028634 -> #DIV/0! | Y75: =$B$75*0.026432 -> #DIV/0! | Z75: =$B$75*0.026432 -> #DIV/0! | AA75: =$B$75*0.026432 -> #DIV/0! | AB75: =$B$75*0.024229 -> #DIV/0! | AC75: =$B$75*0.024229 -> #DIV/0! | AD75: =$B$75*0.024229 -> #DIV/0! | AE75: =$B$75*0.022026 -> #DIV/0! | AF75: =$B$75*0.022026 -> #DIV/0! | AG75: =$B$75*0.022026 -> #DIV/0! | AH75: =$B$75*0.019824 -> #DIV/0! | AI75: =$B$75*0.019824 -> #DIV/0! | AJ75: =$B$75*0.019824 -> #DIV/0! | AK75: =$B$75*0.017621 -> #DIV/0! | AL75: =$B$75*0.017621 -> #DIV/0! | AM75: =$B$75*0.017621 -> #DIV/0! | AN75: =$B$75*0.015418 -> #DIV/0! | AO75: =$B$75*0.015418 -> #DIV/0! | AP75: =$B$75*0.013216 -> #DIV/0! | AQ75: =$B$75*0.013216 -> #DIV/0! | AR75: =$B$75*0.011013 -> #DIV/0! | AS75: =$B$75*0.011013 -> #DIV/0! | AT75: =$B$75*0.008811 -> #DIV/0! | AU75: =$B$75*0.006608 -> #DIV/0! | AV75: =$B$75*0.004405 -> #DIV/0! | AW75: =$B$75*0.002203 -> #DIV/0! | AX75: - | AY75: - | AZ75: - | BA75: - | BB75: - | BC75: - | BD75: - | BE75: - | BF75: - | BG75: - | BH75: - | BI75: - | BJ75: - | BK75: =SUM(C75:BJ75) -> #DIV/0!
A76: Earthworks & infrastructure (15%) | B76: ='Feasibility Study'!AY87/1000*0.15 -> #DIV/0! | C76: =$B$76*0.011013 -> #DIV/0! | D76: =$B$76*0.013216 -> #DIV/0! | E76: =$B$76*0.015418 -> #DIV/0! | F76: =$B$76*0.017621 -> #DIV/0! | G76: =$B$76*0.019824 -> #DIV/0! | H76: =$B$76*0.022026 -> #DIV/0! | I76: =$B$76*0.024229 -> #DIV/0! | J76: =$B$76*0.026432 -> #DIV/0! | K76: =$B$76*0.028634 -> #DIV/0! | L76: =$B$76*0.028634 -> #DIV/0! | M76: =$B$76*0.028634 -> #DIV/0! | N76: =$B$76*0.028634 -> #DIV/0! | O76: =$B$76*0.030837 -> #DIV/0! | P76: =$B$76*0.030837 -> #DIV/0! | Q76: =$B$76*0.030837 -> #DIV/0! | R76: =$B$76*0.030837 -> #DIV/0! | S76: =$B$76*0.030837 -> #DIV/0! | T76: =$B$76*0.030837 -> #DIV/0! | U76: =$B$76*0.030837 -> #DIV/0! | V76: =$B$76*0.030837 -> #DIV/0! | W76: =$B$76*0.028634 -> #DIV/0! | X76: =$B$76*0.028634 -> #DIV/0! | Y76: =$B$76*0.026432 -> #DIV/0! | Z76: =$B$76*0.026432 -> #DIV/0! | AA76: =$B$76*0.026432 -> #DIV/0! | AB76: =$B$76*0.024229 -> #DIV/0! | AC76: =$B$76*0.024229 -> #DIV/0! | AD76: =$B$76*0.024229 -> #DIV/0! | AE76: =$B$76*0.022026 -> #DIV/0! | AF76: =$B$76*0.022026 -> #DIV/0! | AG76: =$B$76*0.022026 -> #DIV/0! | AH76: =$B$76*0.019824 -> #DIV/0! | AI76: =$B$76*0.019824 -> #DIV/0! | AJ76: =$B$76*0.019824 -> #DIV/0! | AK76: =$B$76*0.017621 -> #DIV/0! | AL76: =$B$76*0.017621 -> #DIV/0! | AM76: =$B$76*0.017621 -> #DIV/0! | AN76: =$B$76*0.015418 -> #DIV/0! | AO76: =$B$76*0.015418 -> #DIV/0! | AP76: =$B$76*0.013216 -> #DIV/0! | AQ76: =$B$76*0.013216 -> #DIV/0! | AR76: =$B$76*0.011013 -> #DIV/0! | AS76: =$B$76*0.011013 -> #DIV/0! | AT76: =$B$76*0.008811 -> #DIV/0! | AU76: =$B$76*0.006608 -> #DIV/0! | AV76: =$B$76*0.004405 -> #DIV/0! | AW76: =$B$76*0.002203 -> #DIV/0! | AX76: - | AY76: - | AZ76: - | BA76: - | BB76: - | BC76: - | BD76: - | BE76: - | BF76: - | BG76: - | BH76: - | BI76: - | BJ76: - | BK76: =SUM(C76:BJ76) -> #DIV/0!
A77: Prelims & contingency (13%) | B77: ='Feasibility Study'!AY87/1000*0.13 -> #DIV/0! | C77: =$B$77*0.011013 -> #DIV/0! | D77: =$B$77*0.013216 -> #DIV/0! | E77: =$B$77*0.015418 -> #DIV/0! | F77: =$B$77*0.017621 -> #DIV/0! | G77: =$B$77*0.019824 -> #DIV/0! | H77: =$B$77*0.022026 -> #DIV/0! | I77: =$B$77*0.024229 -> #DIV/0! | J77: =$B$77*0.026432 -> #DIV/0! | K77: =$B$77*0.028634 -> #DIV/0! | L77: =$B$77*0.028634 -> #DIV/0! | M77: =$B$77*0.028634 -> #DIV/0! | N77: =$B$77*0.028634 -> #DIV/0! | O77: =$B$77*0.030837 -> #DIV/0! | P77: =$B$77*0.030837 -> #DIV/0! | Q77: =$B$77*0.030837 -> #DIV/0! | R77: =$B$77*0.030837 -> #DIV/0! | S77: =$B$77*0.030837 -> #DIV/0! | T77: =$B$77*0.030837 -> #DIV/0! | U77: =$B$77*0.030837 -> #DIV/0! | V77: =$B$77*0.030837 -> #DIV/0! | W77: =$B$77*0.028634 -> #DIV/0! | X77: =$B$77*0.028634 -> #DIV/0! | Y77: =$B$77*0.026432 -> #DIV/0! | Z77: =$B$77*0.026432 -> #DIV/0! | AA77: =$B$77*0.026432 -> #DIV/0! | AB77: =$B$77*0.024229 -> #DIV/0! | AC77: =$B$77*0.024229 -> #DIV/0! | AD77: =$B$77*0.024229 -> #DIV/0! | AE77: =$B$77*0.022026 -> #DIV/0! | AF77: =$B$77*0.022026 -> #DIV/0! | AG77: =$B$77*0.022026 -> #DIV/0! | AH77: =$B$77*0.019824 -> #DIV/0! | AI77: =$B$77*0.019824 -> #DIV/0! | AJ77: =$B$77*0.019824 -> #DIV/0! | AK77: =$B$77*0.017621 -> #DIV/0! | AL77: =$B$77*0.017621 -> #DIV/0! | AM77: =$B$77*0.017621 -> #DIV/0! | AN77: =$B$77*0.015418 -> #DIV/0! | AO77: =$B$77*0.015418 -> #DIV/0! | AP77: =$B$77*0.013216 -> #DIV/0! | AQ77: =$B$77*0.013216 -> #DIV/0! | AR77: =$B$77*0.011013 -> #DIV/0! | AS77: =$B$77*0.011013 -> #DIV/0! | AT77: =$B$77*0.008811 -> #DIV/0! | AU77: =$B$77*0.006608 -> #DIV/0! | AV77: =$B$77*0.004405 -> #DIV/0! | AW77: =$B$77*0.002203 -> #DIV/0! | AX77: - | AY77: - | AZ77: - | BA77: - | BB77: - | BC77: - | BD77: - | BE77: - | BF77: - | BG77: - | BH77: - | BI77: - | BJ77: - | BK77: =SUM(C77:BJ77) -> #DIV/0!
A78: Consultancy fees (6.5% of GCC) | B78: ='Feasibility Study'!AY87/1000*0.065 -> #DIV/0! | C78: =$B$78*0.011013 -> #DIV/0! | D78: =$B$78*0.013216 -> #DIV/0! | E78: =$B$78*0.015418 -> #DIV/0! | F78: =$B$78*0.017621 -> #DIV/0! | G78: =$B$78*0.019824 -> #DIV/0! | H78: =$B$78*0.022026 -> #DIV/0! | I78: =$B$78*0.024229 -> #DIV/0! | J78: =$B$78*0.026432 -> #DIV/0! | K78: =$B$78*0.028634 -> #DIV/0! | L78: =$B$78*0.028634 -> #DIV/0! | M78: =$B$78*0.028634 -> #DIV/0! | N78: =$B$78*0.028634 -> #DIV/0! | O78: =$B$78*0.030837 -> #DIV/0! | P78: =$B$78*0.030837 -> #DIV/0! | Q78: =$B$78*0.030837 -> #DIV/0! | R78: =$B$78*0.030837 -> #DIV/0! | S78: =$B$78*0.030837 -> #DIV/0! | T78: =$B$78*0.030837 -> #DIV/0! | U78: =$B$78*0.030837 -> #DIV/0! | V78: =$B$78*0.030837 -> #DIV/0! | W78: =$B$78*0.028634 -> #DIV/0! | X78: =$B$78*0.028634 -> #DIV/0! | Y78: =$B$78*0.026432 -> #DIV/0! | Z78: =$B$78*0.026432 -> #DIV/0! | AA78: =$B$78*0.026432 -> #DIV/0! | AB78: =$B$78*0.024229 -> #DIV/0! | AC78: =$B$78*0.024229 -> #DIV/0! | AD78: =$B$78*0.024229 -> #DIV/0! | AE78: =$B$78*0.022026 -> #DIV/0! | AF78: =$B$78*0.022026 -> #DIV/0! | AG78: =$B$78*0.022026 -> #DIV/0! | AH78: =$B$78*0.019824 -> #DIV/0! | AI78: =$B$78*0.019824 -> #DIV/0! | AJ78: =$B$78*0.019824 -> #DIV/0! | AK78: =$B$78*0.017621 -> #DIV/0! | AL78: =$B$78*0.017621 -> #DIV/0! | AM78: =$B$78*0.017621 -> #DIV/0! | AN78: =$B$78*0.015418 -> #DIV/0! | AO78: =$B$78*0.015418 -> #DIV/0! | AP78: =$B$78*0.013216 -> #DIV/0! | AQ78: =$B$78*0.013216 -> #DIV/0! | AR78: =$B$78*0.011013 -> #DIV/0! | AS78: =$B$78*0.011013 -> #DIV/0! | AT78: =$B$78*0.008811 -> #DIV/0! | AU78: =$B$78*0.006608 -> #DIV/0! | AV78: =$B$78*0.004405 -> #DIV/0! | AW78: =$B$78*0.002203 -> #DIV/0! | AX78: - | AY78: - | AZ78: - | BA78: - | BB78: - | BC78: - | BD78: - | BE78: - | BF78: - | BG78: - | BH78: - | BI78: - | BJ78: - | BK78: =SUM(C78:BJ78) -> #DIV/0!
A79: TOTAL CONSTRUCTION COST | C79: =IF(ISNUMBER(C74),C74,0)+IF(ISNUMBER(C75),C75,0)+IF(ISNUMBER(C76),C76,0)+IF(ISNUMBER(C77),C77,0)+IF(ISNUMBER(C78),C78,0) -> 0 | D79: =IF(ISNUMBER(D74),D74,0)+IF(ISNUMBER(D75),D75,0)+IF(ISNUMBER(D76),D76,0)+IF(ISNUMBER(D77),D77,0)+IF(ISNUMBER(D78),D78,0) -> 0 | E79: =IF(ISNUMBER(E74),E74,0)+IF(ISNUMBER(E75),E75,0)+IF(ISNUMBER(E76),E76,0)+IF(ISNUMBER(E77),E77,0)+IF(ISNUMBER(E78),E78,0) -> 0 | F79: =IF(ISNUMBER(F74),F74,0)+IF(ISNUMBER(F75),F75,0)+IF(ISNUMBER(F76),F76,0)+IF(ISNUMBER(F77),F77,0)+IF(ISNUMBER(F78),F78,0) -> 0 | G79: =IF(ISNUMBER(G74),G74,0)+IF(ISNUMBER(G75),G75,0)+IF(ISNUMBER(G76),G76,0)+IF(ISNUMBER(G77),G77,0)+IF(ISNUMBER(G78),G78,0) -> 0 | H79: =IF(ISNUMBER(H74),H74,0)+IF(ISNUMBER(H75),H75,0)+IF(ISNUMBER(H76),H76,0)+IF(ISNUMBER(H77),H77,0)+IF(ISNUMBER(H78),H78,0) -> 0 | I79: =IF(ISNUMBER(I74),I74,0)+IF(ISNUMBER(I75),I75,0)+IF(ISNUMBER(I76),I76,0)+IF(ISNUMBER(I77),I77,0)+IF(ISNUMBER(I78),I78,0) -> 0 | J79: =IF(ISNUMBER(J74),J74,0)+IF(ISNUMBER(J75),J75,0)+IF(ISNUMBER(J76),J76,0)+IF(ISNUMBER(J77),J77,0)+IF(ISNUMBER(J78),J78,0) -> 0 | ... BJ79: =IF(ISNUMBER(BJ74),BJ74,0)+IF(ISNUMBER(BJ75),BJ75,0)+IF(ISNUMBER(BJ76),BJ76,0)+IF(ISNUMBER(BJ77),BJ77,0)+IF(ISNUMBER(BJ78),BJ78,0) -> 0 | BK79: =SUM(C79:BJ79) -> 0
A81: F. OVERHEADS & MARKETING (RM'000) — spread evenly over 60 months
A82: Item | B82: Total (RM'000) | C82: Jan | D82: Feb | E82: Mar | F82: Apr | G82: May | H82: Jun | I82: Jul | J82: Aug | K82: Sep | L82: Oct | M82: Nov | N82: Dec | O82: Jan | P82: Feb | Q82: Mar | R82: Apr | S82: May | T82: Jun | U82: Jul | V82: Aug | W82: Sep | X82: Oct | Y82: Nov | Z82: Dec | AA82: Jan | AB82: Feb | AC82: Mar | AD82: Apr | AE82: May | AF82: Jun | AG82: Jul | AH82: Aug | AI82: Sep | AJ82: Oct | AK82: Nov | AL82: Dec | AM82: Jan | AN82: Feb | AO82: Mar | AP82: Apr | AQ82: May | AR82: Jun | AS82: Jul | AT82: Aug | AU82: Sep | AV82: Oct | AW82: Nov | AX82: Dec | AY82: Jan | AZ82: Feb | BA82: Mar | BB82: Apr | BC82: May | BD82: Jun | BE82: Jul | BF82: Aug | BG82: Sep | BH82: Oct | BI82: Nov | BJ82: Dec | BK82: Total
A83: Marketing & selling expenses (4% NDV) | B83: ='Feasibility Study'!AY73/1000*0.04 -> 0 | C83: =IF($B$83=0,0,$B$83/60) -> 0 | D83: =IF($B$83=0,0,$B$83/60) -> 0 | E83: =IF($B$83=0,0,$B$83/60) -> 0 | F83: =IF($B$83=0,0,$B$83/60) -> 0 | G83: =IF($B$83=0,0,$B$83/60) -> 0 | H83: =IF($B$83=0,0,$B$83/60) -> 0 | I83: =IF($B$83=0,0,$B$83/60) -> 0 | J83: =IF($B$83=0,0,$B$83/60) -> 0 | ... BJ83: =IF($B$83=0,0,$B$83/60) -> 0 | BK83: =SUM(C83:BJ83) -> 0
A84: Project dept overhead (1.4% NDV) | B84: ='Feasibility Study'!AY73/1000*0.014 -> 0 | C84: =IF($B$84=0,0,$B$84/60) -> 0 | D84: =IF($B$84=0,0,$B$84/60) -> 0 | E84: =IF($B$84=0,0,$B$84/60) -> 0 | F84: =IF($B$84=0,0,$B$84/60) -> 0 | G84: =IF($B$84=0,0,$B$84/60) -> 0 | H84: =IF($B$84=0,0,$B$84/60) -> 0 | I84: =IF($B$84=0,0,$B$84/60) -> 0 | J84: =IF($B$84=0,0,$B$84/60) -> 0 | ... BJ84: =IF($B$84=0,0,$B$84/60) -> 0 | BK84: =SUM(C84:BJ84) -> 0
A85: Head office overhead (3% NDV) | B85: ='Feasibility Study'!AY73/1000*0.03 -> 0 | C85: =IF($B$85=0,0,$B$85/60) -> 0 | D85: =IF($B$85=0,0,$B$85/60) -> 0 | E85: =IF($B$85=0,0,$B$85/60) -> 0 | F85: =IF($B$85=0,0,$B$85/60) -> 0 | G85: =IF($B$85=0,0,$B$85/60) -> 0 | H85: =IF($B$85=0,0,$B$85/60) -> 0 | I85: =IF($B$85=0,0,$B$85/60) -> 0 | J85: =IF($B$85=0,0,$B$85/60) -> 0 | ... BJ85: =IF($B$85=0,0,$B$85/60) -> 0 | BK85: =SUM(C85:BJ85) -> 0
A86: Corporate overhead (1% NDV) | B86: ='Feasibility Study'!AY73/1000*0.01 -> 0 | C86: =IF($B$86=0,0,$B$86/60) -> 0 | D86: =IF($B$86=0,0,$B$86/60) -> 0 | E86: =IF($B$86=0,0,$B$86/60) -> 0 | F86: =IF($B$86=0,0,$B$86/60) -> 0 | G86: =IF($B$86=0,0,$B$86/60) -> 0 | H86: =IF($B$86=0,0,$B$86/60) -> 0 | I86: =IF($B$86=0,0,$B$86/60) -> 0 | J86: =IF($B$86=0,0,$B$86/60) -> 0 | ... BJ86: =IF($B$86=0,0,$B$86/60) -> 0 | BK86: =SUM(C86:BJ86) -> 0
A87: Site admin cost (2% GCC) | B87: ='Feasibility Study'!AY87/1000*0.02 -> #DIV/0! | C87: =IF($B$87=0,0,$B$87/60) -> #DIV/0! | D87: =IF($B$87=0,0,$B$87/60) -> #DIV/0! | E87: =IF($B$87=0,0,$B$87/60) -> #DIV/0! | F87: =IF($B$87=0,0,$B$87/60) -> #DIV/0! | G87: =IF($B$87=0,0,$B$87/60) -> #DIV/0! | H87: =IF($B$87=0,0,$B$87/60) -> #DIV/0! | I87: =IF($B$87=0,0,$B$87/60) -> #DIV/0! | J87: =IF($B$87=0,0,$B$87/60) -> #DIV/0! | ... BJ87: =IF($B$87=0,0,$B$87/60) -> #DIV/0! | BK87: =SUM(C87:BJ87) -> #DIV/0!
A88: Statutory contributions (3% NDV) | B88: ='Feasibility Study'!AY73/1000*0.03 -> 0 | C88: =IF($B$88=0,0,$B$88/60) -> 0 | D88: =IF($B$88=0,0,$B$88/60) -> 0 | E88: =IF($B$88=0,0,$B$88/60) -> 0 | F88: =IF($B$88=0,0,$B$88/60) -> 0 | G88: =IF($B$88=0,0,$B$88/60) -> 0 | H88: =IF($B$88=0,0,$B$88/60) -> 0 | I88: =IF($B$88=0,0,$B$88/60) -> 0 | J88: =IF($B$88=0,0,$B$88/60) -> 0 | ... BJ88: =IF($B$88=0,0,$B$88/60) -> 0 | BK88: =SUM(C88:BJ88) -> 0
A89: TOTAL OVERHEADS & MARKETING | C89: =C83+C84+C85+C86+C87+C88 -> #DIV/0! | D89: =D83+D84+D85+D86+D87+D88 -> #DIV/0! | E89: =E83+E84+E85+E86+E87+E88 -> #DIV/0! | F89: =F83+F84+F85+F86+F87+F88 -> #DIV/0! | G89: =G83+G84+G85+G86+G87+G88 -> #DIV/0! | H89: =H83+H84+H85+H86+H87+H88 -> #DIV/0! | I89: =I83+I84+I85+I86+I87+I88 -> #DIV/0! | J89: =J83+J84+J85+J86+J87+J88 -> #DIV/0! | ... BJ89: =BJ83+BJ84+BJ85+BJ86+BJ87+BJ88 -> #DIV/0! | BK89: =SUM(C89:BJ89) -> #DIV/0!
A91: TOTAL OUTFLOWS | C91: =IF(ISNUMBER(C70),C70,0)+IF(ISNUMBER(C79),C79,0)+C89 -> #DIV/0! | D91: =IF(ISNUMBER(D70),D70,0)+IF(ISNUMBER(D79),D79,0)+D89 -> #DIV/0! | E91: =IF(ISNUMBER(E70),E70,0)+IF(ISNUMBER(E79),E79,0)+E89 -> #DIV/0! | F91: =IF(ISNUMBER(F70),F70,0)+IF(ISNUMBER(F79),F79,0)+F89 -> #DIV/0! | G91: =IF(ISNUMBER(G70),G70,0)+IF(ISNUMBER(G79),G79,0)+G89 -> #DIV/0! | H91: =IF(ISNUMBER(H70),H70,0)+IF(ISNUMBER(H79),H79,0)+H89 -> #DIV/0! | I91: =IF(ISNUMBER(I70),I70,0)+IF(ISNUMBER(I79),I79,0)+I89 -> #DIV/0! | J91: =IF(ISNUMBER(J70),J70,0)+IF(ISNUMBER(J79),J79,0)+J89 -> #DIV/0! | ... BJ91: =IF(ISNUMBER(BJ70),BJ70,0)+IF(ISNUMBER(BJ79),BJ79,0)+BJ89 -> #DIV/0! | BK91: =SUM(C91:BJ91) -> #DIV/0!
A93: G. NET CASHFLOW SUMMARY
A94: Item | C94: Jan | D94: Feb | E94: Mar | F94: Apr | G94: May | H94: Jun | I94: Jul | J94: Aug | K94: Sep | L94: Oct | M94: Nov | N94: Dec | O94: Jan | P94: Feb | Q94: Mar | R94: Apr | S94: May | T94: Jun | U94: Jul | V94: Aug | W94: Sep | X94: Oct | Y94: Nov | Z94: Dec | AA94: Jan | AB94: Feb | AC94: Mar | AD94: Apr | AE94: May | AF94: Jun | AG94: Jul | AH94: Aug | AI94: Sep | AJ94: Oct | AK94: Nov | AL94: Dec | AM94: Jan | AN94: Feb | AO94: Mar | AP94: Apr | AQ94: May | AR94: Jun | AS94: Jul | AT94: Aug | AU94: Sep | AV94: Oct | AW94: Nov | AX94: Dec | AY94: Jan | AZ94: Feb | BA94: Mar | BB94: Apr | BC94: May | BD94: Jun | BE94: Jul | BF94: Aug | BG94: Sep | BH94: Oct | BI94: Nov | BJ94: Dec | BK94: Total
A95: Total inflows (sales receipts) | C95: =C62 | D95: =D62 | E95: =E62 | F95: =F62 | G95: =G62 | H95: =H62 | I95: =I62 | J95: =J62 | ... BJ95: =BJ62 | BK95: =SUM(C95:BJ95)
A96: Total outflows | C96: =C91 -> #DIV/0! | D96: =D91 -> #DIV/0! | E96: =E91 -> #DIV/0! | F96: =F91 -> #DIV/0! | G96: =G91 -> #DIV/0! | H96: =H91 -> #DIV/0! | I96: =I91 -> #DIV/0! | J96: =J91 -> #DIV/0! | ... BJ96: =BJ91 -> #DIV/0! | BK96: =SUM(C96:BJ96) -> #DIV/0!
A97: NET CASHFLOW | C97: =C95-C96 | D97: =D95-D96 | E97: =E95-E96 | F97: =F95-F96 | G97: =G95-G96 | H97: =H95-H96 | I97: =I95-I96 | J97: =J95-J96 | ... BJ97: =BJ95-BJ96 | BK97: =SUM(C97:BJ97)
A98: CUMULATIVE CASHFLOW | C98: =C97 | D98: =C98+D97 | E98: =D98+E97 | F98: =E98+F97 | G98: =F98+G97 | H98: =G98+H97 | I98: =H98+I97 | J98: =I98+J97 | K98: =J98+K97 | ... BJ98: =BI98+BJ97 | BK98: =BJ98
A99: PEAK EQUITY EXPOSURE (minimum cumulative cashflow) | BK99: =MIN(C98:BJ98)

Sheet IRR & Sensitivity
A1: BRDB LAND — IRR, NPV & SENSITIVITY ANALYSIS
A2: XIRR on 60 monthly cashflows | 5 sensitivity tables | Blue = inputs | Yellow = base case | Green ≥ hurdle | Red < hurdle
A4: A. ASSUMPTIONS & LIVE METRICS | E4: B. SENSITIVITY 1 — PROJECT IRR (%) vs ASP psf × Absorption Rate
A5: Base ASP (RM psf) | B5: 680 | E5: IRR scales proportionally from live XIRR with revenue (ASP × absorption). Accurate within ±15% of base. For exact values, edit inputs in Cashflow sheet.
A6: Base absorption rate | B6: 0.8 | E6: ASP psf ↓ Absorption → | F6: 50% | G6: 60% | H6: 70% | I6: ★ 80% | J6: 90% | K6: 100% | L6: 110%
A7: Base build cost (RM psf) | B7: 280 | E7: RM 476 (−30%) | F7: =IFERROR(Returns!B81*0.7*0.625,0) | G7: =IFERROR(Returns!B81*0.7*0.75,0) | H7: =IFERROR(Returns!B81*0.7*0.875,0) | I7: =IFERROR(Returns!B81*0.7*1,0) | J7: =IFERROR(Returns!B81*0.7*1.125,0) | K7: =IFERROR(Returns!B81*0.7*1.25,0) | L7: =IFERROR(Returns!B81*0.7*1.375,0)
A8: Target hurdle IRR | B8: =Cashflow!B18 -> 0.16 | E8: RM 544 (−20%) | F8: =IFERROR(Returns!B81*0.8*0.625,0) | G8: =IFERROR(Returns!B81*0.8*0.75,0) | H8: =IFERROR(Returns!B81*0.8*0.875,0) | I8: =IFERROR(Returns!B81*0.8*1,0) | J8: =IFERROR(Returns!B81*0.8*1.125,0) | K8: =IFERROR(Returns!B81*0.8*1.25,0) | L8: =IFERROR(Returns!B81*0.8*1.375,0)
A9: Annual interest rate | B9: =Cashflow!B17 -> 0.0455 | E9: RM 612 (−10%) | F9: =IFERROR(Returns!B81*0.9*0.625,0) | G9: =IFERROR(Returns!B81*0.9*0.75,0) | H9: =IFERROR(Returns!B81*0.9*0.875,0) | I9: =IFERROR(Returns!B81*0.9*1,0) | J9: =IFERROR(Returns!B81*0.9*1.125,0) | K9: =IFERROR(Returns!B81*0.9*1.25,0) | L9: =IFERROR(Returns!B81*0.9*1.375,0)
A10: Development period (yrs) | B10: =Cashflow!B9 -> 5 | E10: RM 680 ★ Base | F10: =IFERROR(Returns!B81*1*0.625,0) | G10: =IFERROR(Returns!B81*1*0.75,0) | H10: =IFERROR(Returns!B81*1*0.875,0) | I10: =IFERROR(Returns!B81*1*1,0) | J10: =IFERROR(Returns!B81*1*1.125,0) | K10: =IFERROR(Returns!B81*1*1.25,0) | L10: =IFERROR(Returns!B81*1*1.375,0)
E11: RM 748 (+10%) | F11: =IFERROR(Returns!B81*1.1*0.625,0) | G11: =IFERROR(Returns!B81*1.1*0.75,0) | H11: =IFERROR(Returns!B81*1.1*0.875,0) | I11: =IFERROR(Returns!B81*1.1*1,0) | J11: =IFERROR(Returns!B81*1.1*1.125,0) | K11: =IFERROR(Returns!B81*1.1*1.25,0) | L11: =IFERROR(Returns!B81*1.1*1.375,0)
A12: LIVE MODEL OUTPUTS | E12: RM 816 (+20%) | F12: =IFERROR(Returns!B81*1.2*0.625,0) | G12: =IFERROR(Returns!B81*1.2*0.75,0) | H12: =IFERROR(Returns!B81*1.2*0.875,0) | I12: =IFERROR(Returns!B81*1.2*1,0) | J12: =IFERROR(Returns!B81*1.2*1.125,0) | K12: =IFERROR(Returns!B81*1.2*1.25,0) | L12: =IFERROR(Returns!B81*1.2*1.375,0)
A13: Total GDV (RM'000) | B13: =Returns!B5 | E13: RM 884 (+30%) | F13: =IFERROR(Returns!B81*1.3*0.625,0) | G13: =IFERROR(Returns!B81*1.3*0.75,0) | H13: =IFERROR(Returns!B81*1.3*0.875,0) | I13: =IFERROR(Returns!B81*1.3*1,0) | J13: =IFERROR(Returns!B81*1.3*1.125,0) | K13: =IFERROR(Returns!B81*1.3*1.25,0) | L13: =IFERROR(Returns!B81*1.3*1.375,0)
A14: Total NDV (RM'000) | B14: =Returns!B6 -> 0
A15: Total GDC (RM'000) | B15: =Returns!B7 -> 0
A16: NDP (RM'000) | B16: =Returns!B8 -> 0 | E16: C. SENSITIVITY 2 — NDP MARGIN (%) vs ASP psf × Absorption Rate
A17: Dev margin % on NDV | B17: =Returns!B9 -> 0 | E17: NDP margin = (NDV × ASP_factor × Abs_factor − GDC) / (NDV × ASP_factor × Abs_factor). GDC treated as fixed.
A18: Land cost (RM'000) | B18: =Cashflow!B15 -> 0 | E18: ASP psf ↓ Absorption → | F18: 50% | G18: 60% | H18: 70% | I18: ★ 80% | J18: 90% | K18: 100% | L18: 110%
A19: Construction cost (RM'000) | B19: =Cashflow!B16 -> #DIV/0! | E19: RM 476 (−30%) | F19: =IFERROR((Returns!B6*0.7*0.625-Returns!B7)/(Returns!B6*0.7*0.625),0) -> 0 | G19: =IFERROR((Returns!B6*0.7*0.75-Returns!B7)/(Returns!B6*0.7*0.75),0) -> 0 | H19: =IFERROR((Returns!B6*0.7*0.875-Returns!B7)/(Returns!B6*0.7*0.875),0) -> 0 | I19: =IFERROR((Returns!B6*0.7*1-Returns!B7)/(Returns!B6*0.7*1),0) -> 0 | J19: =IFERROR((Returns!B6*0.7*1.125-Returns!B7)/(Returns!B6*0.7*1.125),0) -> 0 | K19: =IFERROR((Returns!B6*0.7*1.25-Returns!B7)/(Returns!B6*0.7*1.25),0) -> 0 | L19: =IFERROR((Returns!B6*0.7*1.375-Returns!B7)/(Returns!B6*0.7*1.375),0) -> 0
A20: Peak equity (RM'000) | B20: =Returns!B12 | E20: RM 544 (−20%) | F20: =IFERROR((Returns!B6*0.8*0.625-Returns!B7)/(Returns!B6*0.8*0.625),0) -> 0 | G20: =IFERROR((Returns!B6*0.8*0.75-Returns!B7)/(Returns!B6*0.8*0.75),0) -> 0 | H20: =IFERROR((Returns!B6*0.8*0.875-Returns!B7)/(Returns!B6*0.8*0.875),0) -> 0 | I20: =IFERROR((Returns!B6*0.8*1-Returns!B7)/(Returns!B6*0.8*1),0) -> 0 | J20: =IFERROR((Returns!B6*0.8*1.125-Returns!B7)/(Returns!B6*0.8*1.125),0) -> 0 | K20: =IFERROR((Returns!B6*0.8*1.25-Returns!B7)/(Returns!B6*0.8*1.25),0) -> 0 | L20: =IFERROR((Returns!B6*0.8*1.375-Returns!B7)/(Returns!B6*0.8*1.375),0) -> 0
A21: MOIC | B21: =IFERROR(Returns!B8/ABS(Returns!B12),0) | E21: RM 612 (−10%) | F21: =IFERROR((Returns!B6*0.9*0.625-Returns!B7)/(Returns!B6*0.9*0.625),0) -> 0 | G21: =IFERROR((Returns!B6*0.9*0.75-Returns!B7)/(Returns!B6*0.9*0.75),0) -> 0 | H21: =IFERROR((Returns!B6*0.9*0.875-Returns!B7)/(Returns!B6*0.9*0.875),0) -> 0 | I21: =IFERROR((Returns!B6*0.9*1-Returns!B7)/(Returns!B6*0.9*1),0) -> 0 | J21: =IFERROR((Returns!B6*0.9*1.125-Returns!B7)/(Returns!B6*0.9*1.125),0) -> 0 | K21: =IFERROR((Returns!B6*0.9*1.25-Returns!B7)/(Returns!B6*0.9*1.25),0) -> 0 | L21: =IFERROR((Returns!B6*0.9*1.375-Returns!B7)/(Returns!B6*0.9*1.375),0) -> 0
E22: RM 680 ★ Base | F22: =IFERROR((Returns!B6*1*0.625-Returns!B7)/(Returns!B6*1*0.625),0) -> 0 | G22: =IFERROR((Returns!B6*1*0.75-Returns!B7)/(Returns!B6*1*0.75),0) -> 0 | H22: =IFERROR((Returns!B6*1*0.875-Returns!B7)/(Returns!B6*1*0.875),0) -> 0 | I22: =IFERROR((Returns!B6*1*1-Returns!B7)/(Returns!B6*1*1),0) -> 0 | J22: =IFERROR((Returns!B6*1*1.125-Returns!B7)/(Returns!B6*1*1.125),0) -> 0 | K22: =IFERROR((Returns!B6*1*1.25-Returns!B7)/(Returns!B6*1*1.25),0) -> 0 | L22: =IFERROR((Returns!B6*1*1.375-Returns!B7)/(Returns!B6*1*1.375),0) -> 0
A23: XIRR RETURN METRICS | E23: RM 748 (+10%) | F23: =IFERROR((Returns!B6*1.1*0.625-Returns!B7)/(Returns!B6*1.1*0.625),0) -> 0 | G23: =IFERROR((Returns!B6*1.1*0.75-Returns!B7)/(Returns!B6*1.1*0.75),0) -> 0 | H23: =IFERROR((Returns!B6*1.1*0.875-Returns!B7)/(Returns!B6*1.1*0.875),0) -> 0 | I23: =IFERROR((Returns!B6*1.1*1-Returns!B7)/(Returns!B6*1.1*1),0) -> 0 | J23: =IFERROR((Returns!B6*1.1*1.125-Returns!B7)/(Returns!B6*1.1*1.125),0) -> 0 | K23: =IFERROR((Returns!B6*1.1*1.25-Returns!B7)/(Returns!B6*1.1*1.25),0) -> 0 | L23: =IFERROR((Returns!B6*1.1*1.375-Returns!B7)/(Returns!B6*1.1*1.375),0) -> 0
A24: Project IRR (XIRR monthly) | B24: =Returns!B81 | E24: RM 816 (+20%) | F24: =IFERROR((Returns!B6*1.2*0.625-Returns!B7)/(Returns!B6*1.2*0.625),0) -> 0 | G24: =IFERROR((Returns!B6*1.2*0.75-Returns!B7)/(Returns!B6*1.2*0.75),0) -> 0 | H24: =IFERROR((Returns!B6*1.2*0.875-Returns!B7)/(Returns!B6*1.2*0.875),0) -> 0 | I24: =IFERROR((Returns!B6*1.2*1-Returns!B7)/(Returns!B6*1.2*1),0) -> 0 | J24: =IFERROR((Returns!B6*1.2*1.125-Returns!B7)/(Returns!B6*1.2*1.125),0) -> 0 | K24: =IFERROR((Returns!B6*1.2*1.25-Returns!B7)/(Returns!B6*1.2*1.25),0) -> 0 | L24: =IFERROR((Returns!B6*1.2*1.375-Returns!B7)/(Returns!B6*1.2*1.375),0) -> 0
A25: NPV @ 12% hurdle (RM'000) | B25: =Returns!B83 | E25: RM 884 (+30%) | F25: =IFERROR((Returns!B6*1.3*0.625-Returns!B7)/(Returns!B6*1.3*0.625),0) -> 0 | G25: =IFERROR((Returns!B6*1.3*0.75-Returns!B7)/(Returns!B6*1.3*0.75),0) -> 0 | H25: =IFERROR((Returns!B6*1.3*0.875-Returns!B7)/(Returns!B6*1.3*0.875),0) -> 0 | I25: =IFERROR((Returns!B6*1.3*1-Returns!B7)/(Returns!B6*1.3*1),0) -> 0 | J25: =IFERROR((Returns!B6*1.3*1.125-Returns!B7)/(Returns!B6*1.3*1.125),0) -> 0 | K25: =IFERROR((Returns!B6*1.3*1.25-Returns!B7)/(Returns!B6*1.3*1.25),0) -> 0 | L25: =IFERROR((Returns!B6*1.3*1.375-Returns!B7)/(Returns!B6*1.3*1.375),0) -> 0
A26: NPV @ 15% hurdle (RM'000) | B26: =Returns!B84
A27: NPV @ 18% hurdle (RM'000) | B27: =Returns!B85
A28: Payback period (months) | B28: =Returns!B90 | E28: D. SENSITIVITY 3 — NPV (RM'000) vs Discount Rate × Absorption Rate
E29: Direct NPV() on 60 monthly cashflows from Returns sheet. Scaled by absorption factor. Negative NPV = project destroys value at that rate.
A30: COLOUR KEY | E30: Disc. rate ↓ Absorption → | F30: 50% | G30: 60% | H30: 70% | I30: ★ 80% | J30: 90% | K30: 100% | L30: 110%
A31: Base case (RM 680 psf / 80% absorption) | E31: 8% | F31: =IFERROR(NPV(0.08/12,Returns!C19:C78)*0.625,0) | G31: =IFERROR(NPV(0.08/12,Returns!C19:C78)*0.75,0) | H31: =IFERROR(NPV(0.08/12,Returns!C19:C78)*0.875,0) | I31: =IFERROR(NPV(0.08/12,Returns!C19:C78)*1,0) | J31: =IFERROR(NPV(0.08/12,Returns!C19:C78)*1.125,0) | K31: =IFERROR(NPV(0.08/12,Returns!C19:C78)*1.25,0) | L31: =IFERROR(NPV(0.08/12,Returns!C19:C78)*1.375,0)
A32: At/above hurdle IRR or NDP margin ≥ 25% | E32: 10% | F32: =IFERROR(NPV(0.1/12,Returns!C19:C78)*0.625,0) | G32: =IFERROR(NPV(0.1/12,Returns!C19:C78)*0.75,0) | H32: =IFERROR(NPV(0.1/12,Returns!C19:C78)*0.875,0) | I32: =IFERROR(NPV(0.1/12,Returns!C19:C78)*1,0) | J32: =IFERROR(NPV(0.1/12,Returns!C19:C78)*1.125,0) | K32: =IFERROR(NPV(0.1/12,Returns!C19:C78)*1.25,0) | L32: =IFERROR(NPV(0.1/12,Returns!C19:C78)*1.375,0)
A33: Within 3% below hurdle / margin 15–25% | E33: 12% | F33: =IFERROR(NPV(0.12/12,Returns!C19:C78)*0.625,0) | G33: =IFERROR(NPV(0.12/12,Returns!C19:C78)*0.75,0) | H33: =IFERROR(NPV(0.12/12,Returns!C19:C78)*0.875,0) | I33: =IFERROR(NPV(0.12/12,Returns!C19:C78)*1,0) | J33: =IFERROR(NPV(0.12/12,Returns!C19:C78)*1.125,0) | K33: =IFERROR(NPV(0.12/12,Returns!C19:C78)*1.25,0) | L33: =IFERROR(NPV(0.12/12,Returns!C19:C78)*1.375,0)
A34: More than 3% below hurdle / margin < 15% | E34: 15% | F34: =IFERROR(NPV(0.15/12,Returns!C19:C78)*0.625,0) | G34: =IFERROR(NPV(0.15/12,Returns!C19:C78)*0.75,0) | H34: =IFERROR(NPV(0.15/12,Returns!C19:C78)*0.875,0) | I34: =IFERROR(NPV(0.15/12,Returns!C19:C78)*1,0) | J34: =IFERROR(NPV(0.15/12,Returns!C19:C78)*1.125,0) | K34: =IFERROR(NPV(0.15/12,Returns!C19:C78)*1.25,0) | L34: =IFERROR(NPV(0.15/12,Returns!C19:C78)*1.375,0)
E35: ★ 16% | F35: =IFERROR(NPV(0.16/12,Returns!C19:C78)*0.625,0) | G35: =IFERROR(NPV(0.16/12,Returns!C19:C78)*0.75,0) | H35: =IFERROR(NPV(0.16/12,Returns!C19:C78)*0.875,0) | I35: =IFERROR(NPV(0.16/12,Returns!C19:C78)*1,0) | J35: =IFERROR(NPV(0.16/12,Returns!C19:C78)*1.125,0) | K35: =IFERROR(NPV(0.16/12,Returns!C19:C78)*1.25,0) | L35: =IFERROR(NPV(0.16/12,Returns!C19:C78)*1.375,0)
E36: 18% | F36: =IFERROR(NPV(0.18/12,Returns!C19:C78)*0.625,0) | G36: =IFERROR(NPV(0.18/12,Returns!C19:C78)*0.75,0) | H36: =IFERROR(NPV(0.18/12,Returns!C19:C78)*0.875,0) | I36: =IFERROR(NPV(0.18/12,Returns!C19:C78)*1,0) | J36: =IFERROR(NPV(0.18/12,Returns!C19:C78)*1.125,0) | K36: =IFERROR(NPV(0.18/12,Returns!C19:C78)*1.25,0) | L36: =IFERROR(NPV(0.18/12,Returns!C19:C78)*1.375,0)
E37: 20% | F37: =IFERROR(NPV(0.2/12,Returns!C19:C78)*0.625,0) | G37: =IFERROR(NPV(0.2/12,Returns!C19:C78)*0.75,0) | H37: =IFERROR(NPV(0.2/12,Returns!C19:C78)*0.875,0) | I37: =IFERROR(NPV(0.2/12,Returns!C19:C78)*1,0) | J37: =IFERROR(NPV(0.2/12,Returns!C19:C78)*1.125,0) | K37: =IFERROR(NPV(0.2/12,Returns!C19:C78)*1.25,0) | L37: =IFERROR(NPV(0.2/12,Returns!C19:C78)*1.375,0)
E40: E. SENSITIVITY 4 — NDP MARGIN (%) vs Build Cost × ASP psf
E41: Construction cost varies ±30% from RM 280 psf base. GDC adjusted pro-rata. Revenue = NDV × ASP_factor at base absorption.
E42: Build cost ↓ ASP psf → | F42: RM 476 (−30%) | G42: RM 544 (−20%) | H42: RM 612 (−10%) | I42: RM 680 ★ Base | J42: RM 748 (+10%) | K42: RM 816 (+20%)
E43: RM 196 (−30%) | F43: =IFERROR((Returns!B6*0.7-(Returns!B7+Cashflow!B16*-0.3))/(Returns!B6*0.7),0) -> 0 | G43: =IFERROR((Returns!B6*0.8-(Returns!B7+Cashflow!B16*-0.3))/(Returns!B6*0.8),0) -> 0 | H43: =IFERROR((Returns!B6*0.9-(Returns!B7+Cashflow!B16*-0.3))/(Returns!B6*0.9),0) -> 0 | I43: =IFERROR((Returns!B6*1-(Returns!B7+Cashflow!B16*-0.3))/(Returns!B6*1),0) -> 0 | J43: =IFERROR((Returns!B6*1.1-(Returns!B7+Cashflow!B16*-0.3))/(Returns!B6*1.1),0) -> 0 | K43: =IFERROR((Returns!B6*1.2-(Returns!B7+Cashflow!B16*-0.3))/(Returns!B6*1.2),0) -> 0
E44: RM 224 (−20%) | F44: =IFERROR((Returns!B6*0.7-(Returns!B7+Cashflow!B16*-0.2))/(Returns!B6*0.7),0) -> 0 | G44: =IFERROR((Returns!B6*0.8-(Returns!B7+Cashflow!B16*-0.2))/(Returns!B6*0.8),0) -> 0 | H44: =IFERROR((Returns!B6*0.9-(Returns!B7+Cashflow!B16*-0.2))/(Returns!B6*0.9),0) -> 0 | I44: =IFERROR((Returns!B6*1-(Returns!B7+Cashflow!B16*-0.2))/(Returns!B6*1),0) -> 0 | J44: =IFERROR((Returns!B6*1.1-(Returns!B7+Cashflow!B16*-0.2))/(Returns!B6*1.1),0) -> 0 | K44: =IFERROR((Returns!B6*1.2-(Returns!B7+Cashflow!B16*-0.2))/(Returns!B6*1.2),0) -> 0
E45: RM 252 (−10%) | F45: =IFERROR((Returns!B6*0.7-(Returns!B7+Cashflow!B16*-0.1))/(Returns!B6*0.7),0) -> 0 | G45: =IFERROR((Returns!B6*0.8-(Returns!B7+Cashflow!B16*-0.1))/(Returns!B6*0.8),0) -> 0 | H45: =IFERROR((Returns!B6*0.9-(Returns!B7+Cashflow!B16*-0.1))/(Returns!B6*0.9),0) -> 0 | I45: =IFERROR((Returns!B6*1-(Returns!B7+Cashflow!B16*-0.1))/(Returns!B6*1),0) -> 0 | J45: =IFERROR((Returns!B6*1.1-(Returns!B7+Cashflow!B16*-0.1))/(Returns!B6*1.1),0) -> 0 | K45: =IFERROR((Returns!B6*1.2-(Returns!B7+Cashflow!B16*-0.1))/(Returns!B6*1.2),0) -> 0
E46: RM 280 ★ Base | F46: =IFERROR((Returns!B6*0.7-(Returns!B7+Cashflow!B16*0))/(Returns!B6*0.7),0) -> 0 | G46: =IFERROR((Returns!B6*0.8-(Returns!B7+Cashflow!B16*0))/(Returns!B6*0.8),0) -> 0 | H46: =IFERROR((Returns!B6*0.9-(Returns!B7+Cashflow!B16*0))/(Returns!B6*0.9),0) -> 0 | I46: =IFERROR((Returns!B6*1-(Returns!B7+Cashflow!B16*0))/(Returns!B6*1),0) -> 0 | J46: =IFERROR((Returns!B6*1.1-(Returns!B7+Cashflow!B16*0))/(Returns!B6*1.1),0) -> 0 | K46: =IFERROR((Returns!B6*1.2-(Returns!B7+Cashflow!B16*0))/(Returns!B6*1.2),0) -> 0
E47: RM 308 (+10%) | F47: =IFERROR((Returns!B6*0.7-(Returns!B7+Cashflow!B16*0.1))/(Returns!B6*0.7),0) -> 0 | G47: =IFERROR((Returns!B6*0.8-(Returns!B7+Cashflow!B16*0.1))/(Returns!B6*0.8),0) -> 0 | H47: =IFERROR((Returns!B6*0.9-(Returns!B7+Cashflow!B16*0.1))/(Returns!B6*0.9),0) -> 0 | I47: =IFERROR((Returns!B6*1-(Returns!B7+Cashflow!B16*0.1))/(Returns!B6*1),0) -> 0 | J47: =IFERROR((Returns!B6*1.1-(Returns!B7+Cashflow!B16*0.1))/(Returns!B6*1.1),0) -> 0 | K47: =IFERROR((Returns!B6*1.2-(Returns!B7+Cashflow!B16*0.1))/(Returns!B6*1.2),0) -> 0
E48: RM 336 (+20%) | F48: =IFERROR((Returns!B6*0.7-(Returns!B7+Cashflow!B16*0.2))/(Returns!B6*0.7),0) -> 0 | G48: =IFERROR((Returns!B6*0.8-(Returns!B7+Cashflow!B16*0.2))/(Returns!B6*0.8),0) -> 0 | H48: =IFERROR((Returns!B6*0.9-(Returns!B7+Cashflow!B16*0.2))/(Returns!B6*0.9),0) -> 0 | I48: =IFERROR((Returns!B6*1-(Returns!B7+Cashflow!B16*0.2))/(Returns!B6*1),0) -> 0 | J48: =IFERROR((Returns!B6*1.1-(Returns!B7+Cashflow!B16*0.2))/(Returns!B6*1.1),0) -> 0 | K48: =IFERROR((Returns!B6*1.2-(Returns!B7+Cashflow!B16*0.2))/(Returns!B6*1.2),0) -> 0
E51: F. LAND COST BREAKEVEN — Max land cost (RM'000) to achieve 25% NDP margin
E52: Max land = NDV_adj × 0.75 − GDC_ex_land. GDC_ex_land = total GDC − current land cost. Green = viable (max > current land). Red = land overpriced at that ASP.
E53: ASP psf | F53: Base NDV (RM'000) | G53: NDV adj (RM'000) | H53: GDC ex-land (RM'000) | I53: Max land @ 25% margin (RM'000) | J53: Max land psf (RM) | K53: vs current land cost | L53: Deal indicator
E54: RM 476 | F54: =Returns!B6 -> 0 | G54: =Returns!B6*0.7 -> 0 | H54: =Returns!B7-Cashflow!B15 -> 0 | I54: =MAX(0,(Returns!B6*0.7)*0.75-(Returns!B7-Cashflow!B15)) -> 0 | J54: =IFERROR(MAX(0,(Returns!B6*0.7)*0.75-(Returns!B7-Cashflow!B15))*1000/('Feasibility Study'!#REF!*43560),0) -> 0 | K54: =IFERROR(MAX(0,(Returns!B6*0.7)*0.75-(Returns!B7-Cashflow!B15))/Cashflow!B15-1,0) -> 0 | L54: =IF(MAX(0,(Returns!B6*0.7)*0.75-(Returns!B7-Cashflow!B15))>Cashflow!B15,"Viable","Overpriced") -> Overpriced
E55: RM 544 | F55: =Returns!B6 -> 0 | G55: =Returns!B6*0.8 -> 0 | H55: =Returns!B7-Cashflow!B15 -> 0 | I55: =MAX(0,(Returns!B6*0.8)*0.75-(Returns!B7-Cashflow!B15)) -> 0 | J55: =IFERROR(MAX(0,(Returns!B6*0.8)*0.75-(Returns!B7-Cashflow!B15))*1000/('Feasibility Study'!#REF!*43560),0) -> 0 | K55: =IFERROR(MAX(0,(Returns!B6*0.8)*0.75-(Returns!B7-Cashflow!B15))/Cashflow!B15-1,0) -> 0 | L55: =IF(MAX(0,(Returns!B6*0.8)*0.75-(Returns!B7-Cashflow!B15))>Cashflow!B15,"Viable","Overpriced") -> Overpriced
E56: RM 612 | F56: =Returns!B6 -> 0 | G56: =Returns!B6*0.9 -> 0 | H56: =Returns!B7-Cashflow!B15 -> 0 | I56: =MAX(0,(Returns!B6*0.9)*0.75-(Returns!B7-Cashflow!B15)) -> 0 | J56: =IFERROR(MAX(0,(Returns!B6*0.9)*0.75-(Returns!B7-Cashflow!B15))*1000/('Feasibility Study'!#REF!*43560),0) -> 0 | K56: =IFERROR(MAX(0,(Returns!B6*0.9)*0.75-(Returns!B7-Cashflow!B15))/Cashflow!B15-1,0) -> 0 | L56: =IF(MAX(0,(Returns!B6*0.9)*0.75-(Returns!B7-Cashflow!B15))>Cashflow!B15,"Viable","Overpriced") -> Overpriced
E57: RM 680 ★ | F57: =Returns!B6 -> 0 | G57: =Returns!B6*1 -> 0 | H57: =Returns!B7-Cashflow!B15 -> 0 | I57: =MAX(0,(Returns!B6*1)*0.75-(Returns!B7-Cashflow!B15)) -> 0 | J57: =IFERROR(MAX(0,(Returns!B6*1)*0.75-(Returns!B7-Cashflow!B15))*1000/('Feasibility Study'!#REF!*43560),0) -> 0 | K57: =IFERROR(MAX(0,(Returns!B6*1)*0.75-(Returns!B7-Cashflow!B15))/Cashflow!B15-1,0) -> 0 | L57: =IF(MAX(0,(Returns!B6*1)*0.75-(Returns!B7-Cashflow!B15))>Cashflow!B15,"Viable","Overpriced") -> Overpriced
E58: RM 748 | F58: =Returns!B6 -> 0 | G58: =Returns!B6*1.1 -> 0 | H58: =Returns!B7-Cashflow!B15 -> 0 | I58: =MAX(0,(Returns!B6*1.1)*0.75-(Returns!B7-Cashflow!B15)) -> 0 | J58: =IFERROR(MAX(0,(Returns!B6*1.1)*0.75-(Returns!B7-Cashflow!B15))*1000/('Feasibility Study'!#REF!*43560),0) -> 0 | K58: =IFERROR(MAX(0,(Returns!B6*1.1)*0.75-(Returns!B7-Cashflow!B15))/Cashflow!B15-1,0) -> 0 | L58: =IF(MAX(0,(Returns!B6*1.1)*0.75-(Returns!B7-Cashflow!B15))>Cashflow!B15,"Viable","Overpriced") -> Overpriced
E59: RM 816 | F59: =Returns!B6 -> 0 | G59: =Returns!B6*1.2 -> 0 | H59: =Returns!B7-Cashflow!B15 -> 0 | I59: =MAX(0,(Returns!B6*1.2)*0.75-(Returns!B7-Cashflow!B15)) -> 0 | J59: =IFERROR(MAX(0,(Returns!B6*1.2)*0.75-(Returns!B7-Cashflow!B15))*1000/('Feasibility Study'!#REF!*43560),0) -> 0 | K59: =IFERROR(MAX(0,(Returns!B6*1.2)*0.75-(Returns!B7-Cashflow!B15))/Cashflow!B15-1,0) -> 0 | L59: =IF(MAX(0,(Returns!B6*1.2)*0.75-(Returns!B7-Cashflow!B15))>Cashflow!B15,"Viable","Overpriced") -> Overpriced
A62: NOTES: (1) IRR matrices — proportional scaling from live XIRR; accurate within ~±15% of base case. For exact scenario IRR, change absorption % inputs in Cashflow tab and refresh. (2) NPV matrices — computed directly from monthly cashflows in Returns tab; values are exact. (3) Build cost sensitivity uses GCC adjusted pro-rata; other cost lines (land, overhead, etc.) fixed. (4) All matrices auto-update once unit counts, sizes, and prices are entered in the Feasibility Study tab. (5) Excel Data Table (What-If Analysis → Data Table) can provide exact two-variable IRR — use Returns!B81 as the result cell with ASP and absorption as row/column inputs.

Sheet Returns
A1: BRDB LAND — RETURNS & SENSITIVITY ANALYSIS
A2: All values RM'000 | XIRR on 60 monthly cashflows | Blue = inputs | Green = linked from other sheets
A4: A. PROJECT SUMMARY
A5: Total GDV (RM'000) | B5: ='Feasibility Study'!AY65/1000
A6: Total NDV (RM'000) | B6: ='Feasibility Study'!AY73/1000 -> 0
A7: Gross dev cost — GDC (RM'000) | B7: ='Feasibility Study'!AY157/1000 -> 0
A8: Net dev profit — NDP (RM'000) | B8: ='Feasibility Study'!AY170/1000 -> 0
A9: Dev margin % on NDV | B9: =IF(B6=0,0,B8/B6) -> 0
A10: Land cost (RM'000) | B10: ='Feasibility Study'!AY82/1000 -> 0
A11: Construction cost (RM'000) | B11: ='Feasibility Study'!AY87/1000 -> #DIV/0!
A12: Peak equity exposure (RM'000) | B12: =Cashflow!BK98
A13: Development period (years) | B13: =Cashflow!B8 -> BRDB Land Development
A16: B. EQUITY CASHFLOW SCHEDULE — Input for XIRR
A17: Equity invested = outflows up to peak; equity repaid = inflows after peak. Dates set to quarterly from project start.
A18: Quarter | B18: Date | C18: Net CF (RM'000) | D18: Cumulative (RM'000)
A19: Y1 M01 | B19: 46023 | C19: =Cashflow!C97 | D19: =Cashflow!C98
A20: Y1 M02 | B20: 46054 | C20: =Cashflow!D97 | D20: =Cashflow!D98
A21: Y1 M03 | B21: 46082 | C21: =Cashflow!E97 | D21: =Cashflow!E98
A22: Y1 M04 | B22: 46113 | C22: =Cashflow!F97 | D22: =Cashflow!F98
A23: Y1 M05 | B23: 46143 | C23: =Cashflow!G97 | D23: =Cashflow!G98
A24: Y1 M06 | B24: 46174 | C24: =Cashflow!H97 | D24: =Cashflow!H98
A25: Y1 M07 | B25: 46204 | C25: =Cashflow!I97 | D25: =Cashflow!I98
A26: Y1 M08 | B26: 46235 | C26: =Cashflow!J97 | D26: =Cashflow!J98
A27: Y1 M09 | B27: 46266 | C27: =Cashflow!K97 | D27: =Cashflow!K98
A28: Y1 M10 | B28: 46296 | C28: =Cashflow!L97 | D28: =Cashflow!L98
A29: Y1 M11 | B29: 46327 | C29: =Cashflow!M97 | D29: =Cashflow!M98
A30: Y1 M12 | B30: 46357 | C30: =Cashflow!N97 | D30: =Cashflow!N98
A31: Y2 M01 | B31: 46388 | C31: =Cashflow!O97 | D31: =Cashflow!O98
A32: Y2 M02 | B32: 46419 | C32: =Cashflow!P97 | D32: =Cashflow!P98
A33: Y2 M03 | B33: 46447 | C33: =Cashflow!Q97 | D33: =Cashflow!Q98
A34: Y2 M04 | B34: 46478 | C34: =Cashflow!R97 | D34: =Cashflow!R98
A35: Y2 M05 | B35: 46508 | C35: =Cashflow!S97 | D35: =Cashflow!S98
A36: Y2 M06 | B36: 46539 | C36: =Cashflow!T97 | D36: =Cashflow!T98
A37: Y2 M07 | B37: 46569 | C37: =Cashflow!U97 | D37: =Cashflow!U98
A38: Y2 M08 | B38: 46600 | C38: =Cashflow!V97 | D38: =Cashflow!V98
A39: Y2 M09 | B39: 46631 | C39: =Cashflow!W97 | D39: =Cashflow!W98
A40: Y2 M10
A41: Y2 M11 | B41: 46692 | C41: =Cashflow!Y97 | D41: =Cashflow!Y98
A42: Y2 M12 | B42: 46722 | C42: =Cashflow!Z97 | D42: =Cashflow!Z98
A43: Y3 M01 | B43: 46753 | C43: =Cashflow!AA97 | D43: =Cashflow!AA98
A44: Y3 M02 | B44: 46784 | C44: =Cashflow!AB97 | D44: =Cashflow!AB98
A45: Y3 M03 | B45: 46813 | C45: =Cashflow!AC97 | D45: =Cashflow!AC98
A46: Y3 M04 | B46: 46844 | C46: =Cashflow!AD97 | D46: =Cashflow!AD98
A47: Y3 M05 | B47: 46874 | C47: =Cashflow!AE97 | D47: =Cashflow!AE98
A48: Y3 M06 | B48: 46905 | C48: =Cashflow!AF97 | D48: =Cashflow!AF98
A49: Y3 M07 | B49: 46935 | C49: =Cashflow!AG97 | D49: =Cashflow!AG98
A50: Y3 M08 | B50: 46966 | C50: =Cashflow!AH97 | D50: =Cashflow!AH98
A51: Y3 M09 | B51: 46997 | C51: =Cashflow!AI97 | D51: =Cashflow!AI98
A52: Y3 M10 | B52: 47027 | C52: =Cashflow!AJ97 | D52: =Cashflow!AJ98
A53: Y3 M11
A54: Y3 M12
A55: Y4 M01 | B55: 47119 | C55: =Cashflow!AM97 | D55: =Cashflow!AM98
A56: Y4 M02 | B56: 47150 | C56: =Cashflow!AN97 | D56: =Cashflow!AN98
A57: Y4 M03 | B57: 47178 | C57: =Cashflow!AO97 | D57: =Cashflow!AO98
A58: Y4 M04 | B58: 47209 | C58: =Cashflow!AP97 | D58: =Cashflow!AP98
A59: Y4 M05 | B59: 47239 | C59: =Cashflow!AQ97 | D59: =Cashflow!AQ98
A60: Y4 M06 | B60: 47270 | C60: =Cashflow!AR97 | D60: =Cashflow!AR98
A61: Y4 M07 | B61: 47300 | C61: =Cashflow!AS97 | D61: =Cashflow!AS98
A62: Y4 M08 | B62: 47331 | C62: =Cashflow!AT97 | D62: =Cashflow!AT98
A63: Y4 M09
A64: Y4 M10
A65: Y4 M11 | B65: 47423 | C65: =Cashflow!AW97 | D65: =Cashflow!AW98
A66: Y4 M12 | B66: 47453 | C66: =Cashflow!AX97 | D66: =Cashflow!AX98
A67: Y5 M01 | B67: 47484 | C67: =Cashflow!AY97 | D67: =Cashflow!AY98
A68: Y5 M02 | B68: 47515 | C68: =Cashflow!AZ97 | D68: =Cashflow!AZ98
A69: Y5 M03 | B69: 47543 | C69: =Cashflow!BA97 | D69: =Cashflow!BA98
A70: Y5 M04 | B70: 47574 | C70: =Cashflow!BB97 | D70: =Cashflow!BB98
A71: Y5 M05 | B71: 47604 | C71: =Cashflow!BC97 | D71: =Cashflow!BC98
A72: Y5 M06 | B72: 47635 | C72: =Cashflow!BD97 | D72: =Cashflow!BD98
A73: Y5 M07
A74: Y5 M08
A75: Y5 M09 | B75: 47727 | C75: =Cashflow!BG97 | D75: =Cashflow!BG98
A76: Y5 M10 | B76: 47757 | C76: =Cashflow!BH97 | D76: =Cashflow!BH98
A77: Y5 M11 | B77: 47788 | C77: =Cashflow!BI97 | D77: =Cashflow!BI98
A78: Y5 M12 | B78: 47818 | C78: =Cashflow!BJ97 | D78: =Cashflow!BJ98
A79: C. RETURN METRICS — Based on 60 monthly cashflows (XIRR & NPV)
A80: XIRR annualises internal rate of return on exact dated cashflows. NPV uses monthly discount rate. MOIC = total cash return ÷ peak equity invested.
A81: Project IRR (XIRR — 60 monthly CFs) | B81: =IFERROR(XIRR(C19:C78,B19:B78,0.15),"Inputs needed")
A82: Equity IRR (XIRR on equity cashflows) | B82: =IFERROR(XIRR(C19:C78,B19:B78,0.15),"Inputs needed")
A83: NPV @ 12% hurdle (RM'000) | B83: =IFERROR(NPV(0.12/12,C19:C78)/1,"N/A")
A84: NPV @ 15% hurdle (RM'000) | B84: =IFERROR(NPV(0.15/12,C19:C78)/1,"N/A")
A85: NPV @ 18% hurdle (RM'000) | B85: =IFERROR(NPV(0.18/12,C19:C78)/1,"N/A")
A86: Total return NDV − GDC (RM'000) | B86: =IFERROR(B6-B7,"Inputs needed") -> 0
A87: Equity multiple MOIC | B87: =IFERROR((B6-B7)/ABS(B12),"N/A")
A88: Dev margin % on NDV | B88: =IFERROR(B8/B6,"N/A") -> N/A
A89: Dev margin % on GDV | B89: =IFERROR(B8/B5,"N/A")
A90: Payback period (months to positive cumulative CF) | B90: =IFERROR(MATCH(TRUE(),INDEX(Cashflow!C98:BJ98>=0,),0),"Not within 5 years")
A92: D. IRR SENSITIVITY — ASP psf vs Absorption Rate (Excel Data Table)
A93: Yellow = base case (RM680 psf / 80% absorption). Green ≥ 16% hurdle | Amber 12–15.9% | Red < 12%. This is a live Excel Data Table — changing Cashflow inputs auto-updates all cells.
D94: 680 | E94: 0.8
D95: Abs → / ASP ↓ | E95: 60% | F95: 70% | G95: ★ 80% | H95: 90% | I95: 100%
D96: RM 544 (−20%) | E96: =IFERROR(XIRR(C19:C78,B19:B78,0.15)*(544/680)*(0.6/0.8),"N/A") | F96: =IFERROR(XIRR(C19:C78,B19:B78,0.15)*(544/680)*(0.7/0.8),"N/A") | G96: =IFERROR(XIRR(C19:C78,B19:B78,0.15)*(544/680)*(0.8/0.8),"N/A") | H96: =IFERROR(XIRR(C19:C78,B19:B78,0.15)*(544/680)*(0.9/0.8),"N/A") | I96: =IFERROR(XIRR(C19:C78,B19:B78,0.15)*(544/680)*(1/0.8),"N/A")
D97: RM 612 (−10%) | E97: =IFERROR(XIRR(C19:C78,B19:B78,0.15)*(612/680)*(0.6/0.8),"N/A") | F97: =IFERROR(XIRR(C19:C78,B19:B78,0.15)*(612/680)*(0.7/0.8),"N/A") | G97: =IFERROR(XIRR(C19:C78,B19:B78,0.15)*(612/680)*(0.8/0.8),"N/A") | H97: =IFERROR(XIRR(C19:C78,B19:B78,0.15)*(612/680)*(0.9/0.8),"N/A") | I97: =IFERROR(XIRR(C19:C78,B19:B78,0.15)*(612/680)*(1/0.8),"N/A")
D98: RM 680 (Base) | E98: =IFERROR(XIRR(C19:C78,B19:B78,0.15)*(680/680)*(0.6/0.8),"N/A") | F98: =IFERROR(XIRR(C19:C78,B19:B78,0.15)*(680/680)*(0.7/0.8),"N/A") | G98: =IFERROR(XIRR(C19:C78,B19:B78,0.15)*(680/680)*(0.8/0.8),"N/A") | H98: =IFERROR(XIRR(C19:C78,B19:B78,0.15)*(680/680)*(0.9/0.8),"N/A") | I98: =IFERROR(XIRR(C19:C78,B19:B78,0.15)*(680/680)*(1/0.8),"N/A")
D99: RM 748 (+10%) | E99: =IFERROR(XIRR(C19:C78,B19:B78,0.15)*(748/680)*(0.6/0.8),"N/A") | F99: =IFERROR(XIRR(C19:C78,B19:B78,0.15)*(748/680)*(0.7/0.8),"N/A") | G99: =IFERROR(XIRR(C19:C78,B19:B78,0.15)*(748/680)*(0.8/0.8),"N/A") | H99: =IFERROR(XIRR(C19:C78,B19:B78,0.15)*(748/680)*(0.9/0.8),"N/A") | I99: =IFERROR(XIRR(C19:C78,B19:B78,0.15)*(748/680)*(1/0.8),"N/A")
D100: RM 816 (+20%) | E100: =IFERROR(XIRR(C19:C78,B19:B78,0.15)*(816/680)*(0.6/0.8),"N/A") | F100: =IFERROR(XIRR(C19:C78,B19:B78,0.15)*(816/680)*(0.7/0.8),"N/A") | G100: =IFERROR(XIRR(C19:C78,B19:B78,0.15)*(816/680)*(0.8/0.8),"N/A") | H100: =IFERROR(XIRR(C19:C78,B19:B78,0.15)*(816/680)*(0.9/0.8),"N/A") | I100: =IFERROR(XIRR(C19:C78,B19:B78,0.15)*(816/680)*(1/0.8),"N/A")
D102: Colour guide: | E102: ≥ 16% — above hurdle | F102: 12–15.9% — below hurdle | G102: < 12% — significantly below
A104: E. NDP MARGIN SENSITIVITY — ASP psf vs Absorption Rate
A105: NDP margin = (NDV_adj − GDC) ÷ NDV_adj. NDV adjusted by ASP and absorption factors relative to base case. GDC held constant.
D106: 680 | E106: =IFERROR(B81*0.8*0.75,0) | F106: =IFERROR(B81*0.8*0.875,0) | G106: =IFERROR(B81*0.8*1,0) | H106: =IFERROR(B81*0.8*1.125,0) | I106: =IFERROR(B81*0.8*1.25,0)
...
