Workbook
Name x: #N/A

Sheet Feasibility Study
A1: BRDB Development Sdn Bhd
A2: Feasibility Study
A3: Lot 1423, Jalan Desa Sentosa KL | G3: Acre to Sqm | H3: 4046.87
G4: Acre to Sqft | H4: 43560 | I4: Jalan Desa Sentosa | K4: Phase 1b | M4: Phase 1c | O4: Phase 1d | Q4: Phase 1e | S4: Phase 1f | W4: Phase 1g | Y4: Phase 1h | AC4: Phase 2a | AE4: Phase 2B | AG4: Phase 2c | AI4: Phase 2d | AK4: Phase 2e | AM4: Phase 2f | AO4: Phase 2g1 | AQ4: Phase 2g2 | AS4: Phase 2g3 | AU4: Phase 2h
A6: LAUNCH DATE | I6: TBC | K6: TBC | M6: TBC | O6: TBC | Q6: TBC | S6: TBC | W6: TBC | Y6: TBC | AC6: TBC | AE6: TBC | AG6: TBC | AI6: TBC | AK6: TBC | AM6: TBC | AO6: TBC | AQ6: TBC | AS6: TBC | AU6: TBC | AW6: TBC | AY6: TOTAL
C8: Phases Land Area (acres) => | I8: 2.938 | K8: 0 | M8: 0 | O8: 0 | Q8: 0 | S8: 0 | W8: 0 | Y8: 0 | AC8: 0 | AE8: 0 | AG8: 0 | AI8: 0 | AK8: 0 | AM8: 0 | AO8: 0 | AQ8: 0 | AS8: 0 | AU8: 0 | AW8: 0 | AY8: =SUM(I8:AW8) -> 2.938
C9: Phases Land Area (square meter) => | I9: =I8*$H$3 -> 11889.704 | K9: =K8*$H$3 -> 0 | M9: =M8*$H$3 -> 0 | O9: =O8*$H$3 -> 0 | Q9: =Q8*$H$3 -> 0 | S9: =S8*$H$3 -> 0 | W9: =W8*$H$3 -> 0 | Y9: =Y8*$H$3 -> 0 | AC9: =AC8*$H$3 -> 0 | AE9: =AE8*$H$3 -> 0 | AG9: =AG8*$H$3 -> 0 | AI9: =AI8*$H$3 -> 0 | AK9: =AK8*$H$3 -> 0 | AM9: =AM8*$H$3 -> 0 | AO9: =AO8*$H$3 -> 0 | AQ9: =AQ8*$H$3 -> 0 | AS9: =AS8*$H$3 -> 0 | AU9: =AU8*$H$3 -> 0 | AW9: =AW8*$H$3 -> 0 | AY9: =SUM(I9:AW9) -> 11889.704
C10: Phases Land Area (square feet) => | I10: =I8*$H$4 -> 127979.28 | K10: =K8*$H$4 -> 0 | M10: =M8*$H$4 -> 0 | O10: =O8*$H$4 -> 0 | Q10: =Q8*$H$4 -> 0 | S10: =S8*$H$4 -> 0 | W10: =W8*$H$4 -> 0 | Y10: =Y8*$H$4 -> 0 | AC10: =AC8*$H$4 -> 0 | AE10: =AE8*$H$4 -> 0 | AG10: =AG8*$H$4 -> 0 | AI10: =AI8*$H$4 -> 0 | AK10: =AK8*$H$4 -> 0 | AM10: =AM8*$H$4 -> 0 | AO10: =AO8*$H$4 -> 0 | AQ10: =AQ8*$H$4 -> 0 | AS10: =AS8*$H$4 -> 0 | AU10: =AU8*$H$4 -> 0 | AW10: =AW8*$H$4 -> 0 | AY10: =SUM(I10:AW10) -> 127979.28
C11: No of units in the Phase => | I11: =E36 -> 84 | K11: =#REF! -> #REF! | M11: =#REF! -> #REF! | O11: =#REF! -> #REF! | Q11: 0 | S11: =#REF!+#REF! -> #REF! | W11: =#REF! -> #REF! | Y11: =#REF! -> #REF! | AC11: =#REF! -> #REF! | AE11: =#REF! -> #REF! | AG11: =#REF! -> #REF! | AI11: =#REF! -> #REF! | AK11: =#REF! -> #REF! | AM11: =#REF! -> #REF! | AO11: =#REF! -> #REF! | AQ11: =#REF! -> #REF! | AS11: 0 | AU11: =#REF! -> #REF! | AW11: =#REF! -> #REF! | AY11: =SUM(I11:AW11) -> #REF!
C12: Carpark Bays => | I12: 344 | K12: 0 | M12: 0 | O12: 0 | Q12: 0 | S12: 0
C13: Typical Apartment Floor => | I13: 44
C14: Construction Floor Area include Carpark (CFA) => | I14: 653039
C15: Gross Floor Area exclude Carpark (GFA) => | I15: 378439 | M15: 1
C16: Net Floor/Saleable area (NFA) => | I16: =G36 -> 294000 | M16: =M11*#REF! -> #REF! | O16: =O11*#REF! -> #REF! | Q16: =Q11*#REF! -> #REF! | S16: =(#REF!*#REF!)+(#REF!*#REF!) -> #REF! | W16: =W11*#REF! -> #REF! | Y16: =Y11*#REF! -> #REF! | AC16: =AC11*#REF! -> #REF! | AE16: =AE11*#REF! -> #REF! | AG16: =AG11*#REF! -> #REF! | AI16: =AI11*#REF! -> #REF! | AK16: =AK11*#REF! -> #REF! | AM16: =AM11*#REF! -> #REF! | AO16: =AO11*#REF! -> #REF! | AQ16: =AQ11*#REF! -> #REF! | AS16: =AS11*#REF! -> #REF! | AU16: =AU11*#REF! -> #REF! | AW16: =AW11*#REF! -> #REF! | AY16: =SUM(I16:AW16) -> #REF!
C17: Plot Ratio (commercial) / Density (per acres) => | I17: =I15/I10 -> 2.9570334 | K17: =K11/K8 -> #REF! | M17: =M11/M8 -> #REF! | O17: =O11/O8 -> #REF! | Q17: =Q16/Q10 -> #REF! | S17: =S16/S10 -> #REF! | W17: =W16/W10 -> #REF! | Y17: =Y16/Y10 -> #REF! | AC17: =AC11/AC8 -> #REF! | AE17: =AE11/AE8 -> #REF! | AG17: =AG11/AG8 -> #REF! | AI17: =AI11/AI8 -> #REF! | AK17: =AK11/AK8 -> #REF! | AM17: =AM11/AM8 -> #REF! | AO17: =AO11/AO8 -> #REF! | AQ17: =AQ11/AQ8 -> #REF! | AS17: =AS11/AS8 -> #DIV/0! | AU17: =AU11/AU8 -> #REF! | AW17: =AW16/AW10 -> #REF!
C19: Summary | H19: %
C20: Net Development Value (NDV) => | G20: =F36 -> 600 | H20: =I20/$I$20 -> 1 | I20: =I61 -> 176400000
C21: Land Cost => | G21: =F72 -> 100 | H21: =-I21/$I$20 -> 0.084952244 | I21: =-I69 -> -14985576
C22: Construction Cost => | G22: =I81 -> 352.47134 | H22: =-I22/$I$20 -> 0.58745224 | I22: =-I79 -> -1.0362657e+08
C23: Soft Cost => | G23: =-I23/I16 -> 48.442244 | H23: =-I23/$I$20 -> 0.080737073 | I23: =-I103-I106-I109-I122-I125-I129-I132 -> -14242020
C24: Finance Cost => | H24: =-I24/$I$20 -> 0.030626209 | I24: =-I144 -> -5402463.3
C25: Net Development Profit (NDP) => | I25: =SUM(I20:I24) -> 38143367
H26: Net Profit Margin | I26: =I25/I20 -> 0.21623224
A28: A | B28: GROSS DEVELOPMENT VALUE
S29: Mixed Comm | W29: Mixed Comm | Y29: Mixed Comm
A30: 1 | B30: Type of Development | I30: Condominium | K30: 3 Sty Superlink | M30: Affordable Home | O30: Affordable Home | Q30: Commercial | S30: S. Apartment | W30: S.Apartment | Y30: S.Apartment | AC30: 2 Sty Linkhouse | AE30: 2 Sty Linkhouse | AG30: 2 Sty Linkhouse | AI30: 2 Sty Semi-D | AK30: 2 Sty Semi-D | AM30: Zero Lot Bungalow | AO30: Condominium | AQ30: Condominium | AS30: Recreational | AU30: Terrace House | AW30: Commercial Shoplot
A31: =A30+1 -> 2 | B31: Total No of Units | C31: a) Residential | D31: =E36 -> 84 | Q31: Shop-lot | S31: Retail Shoplots | W31: Retail Shoplots | Y31: Retail Shoplots | AO31: High Rise | AQ31: High Rise | AS31: Park
A32: =A31+1 -> 3 | B32: Net Floor/Saleable Area (NFA) | C32: a) Residential | D32: =E36*D36 -> 294000
A33: =A32+1 -> 4 | B33: Net Selling Price psf | C33: a) Residential | D33: =F36 -> 600 | K33: =K61/K16 -> #REF! | M33: =M61/M16 -> #REF! | O33: =O61/O16 -> #REF! | Q33: =Q61/Q16 -> #REF! | S33: =S61/S16 -> #REF! | W33: =W61/W16 -> #REF! | Y33: =Y61/Y16 -> #REF! | AC33: =AC61/AC16 -> #REF! | AE33: =AE61/AE16 -> #REF! | AG33: =AG61/AG16 -> #REF! | AI33: =AI61/AI16 -> #REF! | AK33: =AK61/AK16 -> #REF! | AM33: =AM61/AM16 -> #REF! | AO33: =AO61/AO16 -> #REF! | AQ33: =AQ61/AQ16 -> #REF! | AS33: =AS61/AS16 -> #REF! | AU33: =AU61/AU16 -> #REF! | AW33: =AW61/AW16 -> #REF!
D34: Unit Avg size | E34: Units | F34: RM'psf (Nett to Dev) | G34: Total NFA | H34: Average Price/unit (Nett)
C35: Condominium | K35: =#REF!*#REF!/2 -> #REF! | AY35: =SUM(I35:AW35) -> #REF!
C36: Typical Apartment (2 units per floor) | D36: 3500 | E36: 84 | F36: 600 | G36: =E36*D36 -> 294000 | H36: =D36*F36 -> 2100000
A38: GROSS DEVELOPMENT VALUE (GDV) | I38: =SUM(I40:I61) -> 220229268 | K38: =SUM(K39:K61) -> #REF! | M38: =SUM(M39:M61) -> #REF! | O38: =SUM(O39:O61) -> #REF! | Q38: =SUM(Q39:Q61) -> #REF! | S38: =SUM(S39:S61) -> #REF! | W38: =SUM(W39:W61) -> #REF! | Y38: =SUM(Y39:Y61) -> #REF! | AC38: =SUM(AC39:AC61) -> #REF! | AE38: =SUM(AE39:AE61) -> #REF! | AG38: =SUM(AG39:AG61) -> #REF! | AI38: =SUM(AI39:AI61) -> #REF! | AK38: =SUM(AK39:AK61) -> #REF! | AM38: =SUM(AM39:AM61) -> #REF! | AO38: =SUM(AO39:AO61) -> #REF! | AQ38: =SUM(AQ39:AQ61) -> #REF! | AS38: =SUM(AS39:AS61) -> #REF! | AU38: =SUM(AU39:AU61) -> #REF! | AW38: =SUM(AW39:AW61) -> #REF! | AY38: =SUM(AY39:AY61) -> #REF!
A39: 1 | B39: MARKETING & SELLING EXPENSES | I39: =SUM(I40:I60) -> 43829268 | K39: =#REF!+#REF! -> #REF! | M39: =#REF! -> #REF! | O39: =#REF! -> #REF! | Q39: =#REF! -> #REF! | S39: =#REF! -> #REF! | W39: =#REF! -> #REF! | Y39: =#REF! -> #REF! | AC39: =#REF! -> #REF! | AE39: =#REF! -> #REF! | AG39: =#REF! -> #REF! | AI39: =#REF! -> #REF! | AK39: =#REF! -> #REF! | AM39: =#REF! -> #REF! | AO39: =#REF! -> #REF! | AQ39: =#REF! -> #REF! | AS39: =#REF! -> #REF! | AU39: =#REF! -> #REF! | AW39: =#REF! -> #REF! | AY39: =#REF! -> #REF!
A40: 1.1 | B40: Marketing Expenses
B41: General Marketing Expenses | F41: 0.01 | G41: of NDV | I41: =$F$41*I61 -> 1764000 | K41: =$F$41*K61 -> #REF! | M41: =$F$41*M61 -> 0 | O41: =$F$41*O61 -> 0 | Q41: =$F$41*Q61 -> 0 | S41: =$F$41*S61 -> 0 | W41: =$F$41*W61 -> 0 | Y41: =$F$41*Y61 -> 0 | AC41: =$F$41*AC61 -> 0 | AE41: =$F$41*AE61 -> 0 | AG41: =$F$41*AG61 -> 0 | AI41: =$F$41*AI61 -> 0 | AK41: =$F$41*AK61 -> 0 | AM41: =$F$41*AM61 -> 0 | AO41: =$F$41*AO61 -> 0 | AQ41: =$F$41*AQ61 -> 0 | AS41: =$F$41*AS61 -> 0 | AU41: =$F$41*AU61 -> 0 | AW41: =$F$41*AW61 -> 0 | AY41: =SUM(I41:AW41) -> #REF!
B42: Architectural Models | AY42: =SUM(I42:AW42) -> 0
B43: Market Research | AY43: =SUM(I43:AW43) -> 0
B44: Construction Sales Gallery | AY44: =SUM(I44:AW44) -> 0
B45: Yenom Final Acc SG,G/Houseinc landscape | D45: =2400000+2600000 -> 5000000 | AY45: =SUM(I45:AW45) -> 0
B46: Construction of Show units (inc. ID) or I.D & Landscape cost for actual unit at site | AY46: =SUM(I46:AW46) -> 0
B47: Running & maintainance Cost of Sales Gallery & Show unit
A49: 1.2 | B49: Selling Expenses
B50: VIP Discount/Discount/Early Bird | F50: 0.09 | G50: of GDV | I50: =F50*SUM(I40:I49,I51:I61) -> 18184068
B51: Commission & Brokerage | F51: 0.03 | G51: of NDV | I51: =F51*I61 -> 5292000
B52: Repeat Buyers/BGB | F52: 0.03 | G52: of NDV | I52: =F52*$I$61 -> 5292000
B53: Director/Staff Discount | F53: 0.03 | G53: of NDV | I53: =F53*$I$61 -> 5292000
B54: Free SPA & Loan Legal Fees | F54: 5000 | G54: /unit | I54: =F54*E36 -> 420000
B55: Bumi Discount | F55: 0.07 | G55: 0.5 | I55: =F55*I61*50% -> 6174000
B56: Maintenance & Sinking Fund | F56: 0.4 | G56: 12 months | I56: =F56*D32*12 -> 1411200
A59: *Net Development Value (NDV) have to be same with S&M based on net selling price after deduction of all discounts (bumi discounts & release penalty), incentives, early birds, Legal Fees & any other items not stated in this Feasibility. Sales have to mark up the selling price accordingly. | AY59: =SUM(I59:AW59) -> 0
A61: NET DEVELOPMENT VALUE (NDV) | I61: =H36*E36 -> 176400000 | K61: =SUM(K35:K37) -> #REF! | M61: =SUM(M35:M37) -> 0 | O61: =SUM(O35:O37) -> 0 | Q61: =SUM(Q35:Q37) -> 0 | S61: =SUM(S35:S37) -> 0 | W61: =SUM(W35:W37) -> 0 | Y61: =SUM(Y35:Y37) -> 0 | AC61: =SUM(AC35:AC37) -> 0 | AE61: =SUM(AE35:AE37) -> 0 | AG61: =SUM(AG35:AG37) -> 0 | AI61: =SUM(AI35:AI37) -> 0 | AK61: =SUM(AK35:AK37) -> 0 | AM61: =SUM(AM35:AM37) -> 0 | AO61: =SUM(AO35:AO37) -> 0 | AQ61: =SUM(AQ35:AQ37) -> 0 | AS61: =SUM(AS35:AS37) -> 0 | AU61: =SUM(AU35:AU37) -> 0 | AW61: =SUM(AW35:AW37) -> 0 | AY61: =SUM(AY35:AY37) -> #REF!
AE62: =146408452/169*173 -> 1.4987374e+08 | AO62: 52605702 | AQ62: 52605702 | AS62: 52605702
AE63: =(146408452-12830219.68-8665391.42)/169*173 -> 1.2786936e+08
A64: Net Selling Price psf | I64: =I61/I16 -> 600 | K64: =K60/K15 -> #DIV/0! | M64: =M60/M15 -> 0 | O64: =O60/O15 -> #DIV/0! | Q64: =Q60/Q15 -> #DIV/0! | S64: =S60/S15 -> #DIV/0! | W64: =W60/W15 -> #DIV/0! | Y64: =Y60/Y15 -> #DIV/0! | AC64: =AC60/AC15 -> #DIV/0! | AE64: =AE60/AE15 -> #DIV/0! | AG64: =AG60/AG15 -> #DIV/0! | AI64: =AI60/AI15 -> #DIV/0! | AK64: =AK60/AK15 -> #DIV/0! | AM64: =AM60/AM15 -> #DIV/0! | AO64: =AO60/AO15 -> #DIV/0! | AQ64: =AQ60/AQ15 -> #DIV/0! | AS64: =AS60/AS15 -> #DIV/0! | AU64: =AU60/AU15 -> #DIV/0! | AW64: =AW60/AW15 -> #DIV/0! | AY64: =AY60/AY15 -> #DIV/0!
K65: =K61/K16 -> #REF! | M65: =M61/M16 -> #REF! | O65: =O61/O16 -> #REF! | Q65: =Q61/Q16 -> #REF! | S65: =S61/S16 -> #REF! | W65: =W61/W16 -> #REF! | Y65: =Y61/Y16 -> #REF! | AC65: =AC61/AC16 -> #REF! | AE65: =AE61/AE16 -> #REF! | AG65: =AG61/AG16 -> #REF! | AI65: =AI61/AI16 -> #REF! | AK65: =AK61/AK16 -> #REF! | AM65: =AM61/AM16 -> #REF! | AO65: =AO61/AO16 -> #REF! | AQ65: =AQ61/AQ16 -> #REF! | AS65: =AS61/AS16 -> #REF! | AU65: =AU61/AU16 -> #REF! | AW65: =AW61/AW16 -> #REF! | AY65: =AY61/AY16 -> #REF!
A67: B | B67: GROSS DEVELOPMENT COST (GDC)
K68: =K72/K10 -> #DIV/0! | M68: =M72/M10 -> #DIV/0! | O68: =O72/O10 -> #DIV/0! | Q68: =Q72/Q10 -> #DIV/0! | S68: =S72/S10 -> #DIV/0! | W68: =W72/W10 -> #DIV/0! | Y68: =Y72/Y10 -> #DIV/0! | AC68: =AC72/AC10 -> #DIV/0! | AE68: =AE72/AE10 -> #DIV/0! | AG68: =AG72/AG10 -> #DIV/0! | AI68: =AI72/AI10 -> #DIV/0! | AK68: =AK72/AK10 -> #DIV/0! | AM68: =AM72/AM10 -> #DIV/0! | AO68: =AO72/AO10 -> #DIV/0! | AQ68: =AQ72/AQ10 -> #DIV/0! | AS68: =AS72/AS10 -> #DIV/0! | AU68: =AU72/AU10 -> #DIV/0! | AW68: =AW72/AW10 -> #DIV/0! | AY68: =AY72/AY10 -> 100
A69: 2 | B69: LAND & OTHER RELATED COSTS | I69: =SUM(I72:I76) -> 14985576 | K69: =SUM(K72:K76) -> 0 | M69: =SUM(M72:M76) -> 0 | O69: =SUM(O72:O76) -> 0 | Q69: =SUM(Q72:Q76) -> 0 | S69: =SUM(S72:S76) -> 0 | W69: =SUM(W72:W76) -> 0 | Y69: =SUM(Y72:Y76) -> 0 | AC69: =SUM(AC72:AC76) -> 0 | AE69: =SUM(AE72:AE76) -> 0 | AG69: =SUM(AG72:AG76) -> 0 | AI69: =SUM(AI72:AI76) -> 0 | AK69: =SUM(AK72:AK76) -> 0 | AM69: =SUM(AM72:AM76) -> 0 | AO69: =SUM(AO72:AO76) -> 0 | AQ69: =SUM(AQ72:AQ76) -> 0 | AS69: =SUM(AS72:AS76) -> 0 | AU69: =SUM(AU72:AU76) -> 0 | AW69: =SUM(AW72:AW76) -> 0 | AY69: =SUM(AY72:AY76) -> 14729617
H70: % of NDV | I70: =I69/I61 -> 0.084952244
H71: Land & Other Related Cost psf | I71: =I69/I10 -> 117.09377
B72: 5.1 | C72: Land Cost | F72: 100 | I72: =$F$72*I10 -> 12797928 | K72: =$F$72*K10 -> 0 | M72: =$F$72*M10 -> 0 | O72: =$F$72*O10 -> 0 | Q72: =$F$72*Q10 -> 0 | S72: =$F$72*S10 -> 0 | W72: =$F$72*W10 -> 0 | Y72: =$F$72*Y10 -> 0 | AC72: =$F$72*AC10 -> 0 | AE72: =$F$72*AE10 -> 0 | AG72: =$F$72*AG10 -> 0 | AI72: =$F$72*AI10 -> 0 | AK72: =$F$72*AK10 -> 0 | AM72: =$F$72*AM10 -> 0 | AO72: =$F$72*AO10 -> 0 | AQ72: =$F$72*AQ10 -> 0 | AS72: =$F$72*AS10 -> 0 | AU72: =$F$72*AU10 -> 0 | AW72: =$F$72*AW10 -> 0 | AY72: =SUM(I72:AW72) -> 12797928
B73: =B72+0.1 -> 5.2 | C73: Land Conversion Premium | D73: 0.15 | E73: 0.3 | F73: 15% or 30% | G73: of Net Land Value | I73: =I72*$D$73 -> 1919689.2 | K73: =K72*$D$73 -> 0 | M73: =M72*$D$73 -> 0 | O73: =O72*$D$73 -> 0 | Q73: =Q72*$E$73 -> 0 | S73: =S72*$E$73 -> 0 | W73: =W72*$E$73 -> 0 | Y73: =Y72*$E$73 -> 0 | AC73: =AC72*$D$73 -> 0 | AE73: =AE72*$D$73 -> 0 | AG73: =AG72*$D$73 -> 0 | AI73: =AI72*$D$73 -> 0 | AK73: =AK72*$D$73 -> 0 | AM73: =AM72*$D$73 -> 0 | AO73: =AO72*$D$73 -> 0 | AQ73: =AQ72*$D$73 -> 0 | AS73: =AS72*$D$73 -> 0 | AU73: =AU72*$D$73 -> 0 | AW73: =AW72*$D$73 -> 0 | AY73: =SUM(I73:AW73) -> 1919689.2
B74: 5.3 | C74: Legal Fees | F74: 0.02 | G74: of Net Land Value | I74: =F74*I72 -> 255958.56
B75: 5.4 | C75: Quit Rent | F75: 2000 | G75: per Annum for 4 years | I75: =F75*4 -> 8000 | K75: =+$F75*(K8/$AY$8)*4 -> 0 | M75: =+$F75*(M8/$AY$8)*4 -> 0 | O75: =+$F75*(O8/$AY$8)*4 -> 0 | Q75: =+$F75*(Q8/$AY$8)*6 -> 0 | S75: =+$F75*(S8/$AY$8)*6 -> 0 | W75: =+$F75*(W8/$AY$8)*8 -> 0 | Y75: =+$F75*(Y8/$AY$8)*10 -> 0 | AC75: =+$F75*(AC8/$AY$8)*4 -> 0 | AE75: =+$F75*(AE8/$AY$8)*4 -> 0 | AG75: =+$F75*(AG8/$AY$8)*6 -> 0 | AI75: =+$F75*(AI8/$AY$8)*6 -> 0 | AK75: =+$F75*(AK8/$AY$8)*8 -> 0 | AM75: =+$F75*(AM8/$AY$8)*8 -> 0 | AO75: =+$F75*(AO8/$AY$8)*10 -> 0 | AQ75: =+$F75*(AQ8/$AY$8)*10 -> 0 | AS75: =+$F75*(AS8/$AY$8)*10 -> 0 | AU75: =+$F75*(AU8/$AY$8)*10 -> 0 | AW75: =+$F75*(AW8/$AY$8)*10 -> 0 | AY75: =SUM(I75:AW75) -> 8000
B76: 5.5 | C76: Assessment | F76: 1000 | G76: per Annum for 4 years | I76: =F76*4 -> 4000 | K76: =+$F76*(K8/$AY$8)*4 -> 0 | M76: =+$F76*(M8/$AY$8)*4 -> 0 | O76: =+$F76*(O8/$AY$8)*4 -> 0 | Q76: =+$F76*(Q8/$AY$8)*6 -> 0 | S76: =+$F76*(S8/$AY$8)*6 -> 0 | W76: =+$F76*(W8/$AY$8)*8 -> 0 | Y76: =+$F76*(Y8/$AY$8)*10 -> 0 | AC76: =+$F76*(AC8/$AY$8)*4 -> 0 | AE76: =+$F76*(AE8/$AY$8)*4 -> 0 | AG76: =+$F76*(AG8/$AY$8)*6 -> 0 | AI76: =+$F76*(AI8/$AY$8)*6 -> 0 | AK76: =+$F76*(AK8/$AY$8)*8 -> 0 | AM76: =+$F76*(AM8/$AY$8)*8 -> 0 | AO76: =+$F76*(AO8/$AY$8)*10 -> 0 | AQ76: =+$F76*(AQ8/$AY$8)*10 -> 0 | AS76: =+$F76*(AS8/$AY$8)*10 -> 0 | AU76: =+$F76*(AU8/$AY$8)*10 -> 0 | AW76: =+$F76*(AW8/$AY$8)*10 -> 0 | AY76: =SUM(I76:AW76) -> 4000
B77: 5.6 | C77: Valuation Report | I77: 5000
A79: 3 | B79: GROSS CONSTRUCTION COST (GCC) | I79: =SUM(I97:I101) -> 1.0362657e+08 | K79: =SUM(K97:K100) -> 0 | M79: =SUM(M97:M99) -> #REF! | O79: =SUM(O97:O99) -> #REF! | Q79: =SUM(Q97:Q100) -> #REF! | S79: =SUM(S97:S100) -> #REF! | W79: =SUM(W97:W100) -> #REF! | Y79: =SUM(Y97:Y100) -> #REF! | AC79: =SUM(AC97:AC100) -> #REF! | AE79: =SUM(AE97:AE100) -> #REF! | AG79: =SUM(AG97:AG99) -> #REF! | AI79: =SUM(AI97:AI99) -> #REF! | AK79: =SUM(AK97:AK99) -> #REF! | AM79: =SUM(AM97:AM99) -> #REF! | AO79: =SUM(AO97:AO99) -> #REF! | AQ79: =SUM(AQ97:AQ99) -> #REF! | AS79: =SUM(AS97:AS99) -> 0 | AU79: =SUM(AU97:AU99) -> #REF! | AW79: =SUM(AW97:AW100) -> #REF! | AY79: =SUM(AY97:AY100) -> #REF!
H80: % of NDV | I80: =I79/I61 -> 0.58745224 | K80: =K79/K61 -> #REF! | M80: =M79/M61 -> #REF! | O80: =O79/O61 -> #REF! | Q80: =Q79/Q61 -> #REF! | S80: =S79/S61 -> #REF! | W80: =W79/W61 -> #REF! | Y80: =Y79/Y61 -> #REF! | AC80: =AC79/AC61 -> #REF! | AE80: =AE79/AE61 -> #REF! | AG80: =AG79/AG61 -> #REF! | AI80: =AI79/AI61 -> #REF! | AK80: =AK79/AK61 -> #REF! | AM80: =AM79/AM61 -> #REF! | AO80: =AO79/AO61 -> #REF! | AQ80: =AQ79/AQ61 -> #REF! | AS80: =AS79/AS61 -> #DIV/0! | AU80: =AU79/AU61 -> #REF! | AW80: =AW79/AW61 -> #REF! | AY80: =AY79/AY61 -> #REF!
H81: Construction Cost psf | I81: =I79/I16 -> 352.47134 | K81: =K79/K16 -> #DIV/0! | M81: =M79/M16 -> #REF! | O81: =O79/O16 -> #REF! | Q81: =Q79/Q16 -> #REF! | S81: =S79/S16 -> #REF! | W81: =W79/W16 -> #REF! | Y81: =Y79/Y16 -> #REF! | AC81: =AC79/AC16 -> #REF! | AE81: =AE79/AE16 -> #REF! | AG81: =AG79/AG16 -> #REF! | AI81: =AI79/AI16 -> #REF! | AK81: =AK79/AK16 -> #REF! | AM81: =AM79/AM16 -> #REF! | AO81: =AO79/AO16 -> #REF! | AQ81: =AQ79/AQ16 -> #REF! | AS81: =AS79/AS16 -> #REF! | AU81: =AU79/AU16 -> #REF! | AW81: =AW79/AW16 -> #REF! | AY81: =AY79/AY16 -> #REF!
B82: 3.1 | C82: Building Work
C83: Residential | F83: 300 | I83: =$F83*I16 -> 88200000 | K83: =$F83*K16 -> 0 | S83: =$F83*(#REF!*#REF!) -> #REF! | AC83: =$F83*AC16 -> #REF! | AE83: =$F83*AE16 -> #REF! | AG83: =$F83*AG16 -> #REF! | AI83: =$F83*AI16 -> #REF! | AK83: =$F83*AK16 -> #REF! | AM83: =$F83*AM16 -> #REF! | AO83: =$F83*AO16 -> #REF! | AQ83: =$F83*AQ16 -> #REF! | AU83: =$F83*AU16 -> #REF! | AY83: =SUM(I83:AW83) -> #REF!
C84: Affordable Housing | F84: 200 | M84: =$F84*M16 -> #REF! | O84: =$F84*O16 -> #REF! | AY84: =SUM(I84:AW84) -> #REF!
C85: Commercial Shoplots | F85: 180 | Q85: =$F85*Q16 -> #REF! | S85: =$F85*(#REF!*#REF!) -> #REF! | W85: =$F85*W16 -> #REF! | Y85: =$F85*Y16 -> #REF! | AW85: =$F85*AW16 -> #REF! | AY85: =SUM(I85:AW85) -> #REF!
C87: Freebies (Optional):
C88: White Goods | G88: /unit
C89: Wardrobe | G89: /unit
B91: 3.2 | C91: Earthworks to platform level, Retaining structure, External & Internal Infrastructure | F91: 700000 | I91: =F91*I8 -> 2056600 | K91: =H91*K8 -> 0 | M91: =J91*M8 -> 0 | O91: =L91*O8 -> 0 | Q91: =N91*Q8 -> 0 | S91: =P91*S8 -> 0 | W91: =T91*W8 -> 0 | Y91: =V91*Y8 -> 0 | AC91: =Z91*AC8 -> 0 | AE91: =AB91*AE8 -> 0 | AG91: =AD91*AG8 -> 0 | AI91: =AF91*AI8 -> 0 | AK91: =AH91*AK8 -> 0 | AM91: =AJ91*AM8 -> 0 | AO91: =AL91*AO8 -> 0 | AQ91: =AN91*AQ8 -> 0 | AS91: =AP91*AS8 -> 0 | AU91: =AR91*AU8 -> 0 | AW91: =AT91*AW8 -> 0 | AY91: =SUM(I91:AW91) -> 2056600
B93: 3.3 | C93: Soft Landscape & Hard Landscape | F93: 125000 | I93: =$F$93*I8 -> 367250 | K93: =$F$93*K8 -> 0 | M93: =$F$93*M8 -> 0 | O93: =$F$93*O8 -> 0 | Q93: =$F$93*Q8 -> 0 | S93: =$F$93*S8 -> 0 | W93: =$F$93*W8 -> 0 | Y93: =$F$93*Y8 -> 0 | AC93: =$F$93*AC8 -> 0 | AE93: =$F$93*AE8 -> 0 | AG93: =$F$93*AG8 -> 0 | AI93: =$F$93*AI8 -> 0 | AK93: =$F$93*AK8 -> 0 | AM93: =$F$93*AM8 -> 0 | AO93: =$F$93*AO8 -> 0 | AQ93: =$F$93*AQ8 -> 0 | AS93: =$F$93*AS8 -> 0 | AU93: =$F$93*AU8 -> 0 | AW93: =$F$93*AW8 -> 0 | AY93: =SUM(I93:AW93) -> 367250
B95: 3.4 | C95: Clubhouse / Show Units | F95: 1000000 | I95: =$F$95*(I8/$AY$8) -> 1000000 | K95: =$F$95*(K8/$AY$8) -> 0 | M95: =$F$95*(M8/$AY$8) -> 0 | O95: =$F$95*(O8/$AY$8) -> 0 | Q95: =$F$95*(Q8/$AY$8) -> 0 | S95: =$F$95*(S8/$AY$8) -> 0 | W95: =$F$95*(W8/$AY$8) -> 0 | Y95: =$F$95*(Y8/$AY$8) -> 0 | AC95: =$F$95*(AC8/$AY$8) -> 0 | AE95: =$F$95*(AE8/$AY$8) -> 0 | AG95: =$F$95*(AG8/$AY$8) -> 0 | AI95: =$F$95*(AI8/$AY$8) -> 0 | AK95: =$F$95*(AK8/$AY$8) -> 0 | AM95: =$F$95*(AM8/$AY$8) -> 0 | AO95: =$F$95*(AO8/$AY$8) -> 0 | AQ95: =$F$95*(AQ8/$AY$8) -> 0 | AS95: =$F$95*(AS8/$AY$8) -> 0 | AU95: =$F$95*(AU8/$AY$8) -> 0 | AW95: =$F$95*(AW8/$AY$8) -> 0 | AY95: =SUM(I95:AW95) -> 1000000
C97: Construction Cost (CC) | I97: =SUM(I82:I96) -> 91623850 | K97: =SUM(K82:K96) -> 0 | M97: =SUM(M82:M96) -> #REF! | O97: =SUM(O82:O96) -> #REF! | Q97: =SUM(Q82:Q96) -> #REF! | S97: =SUM(S82:S96) -> #REF! | W97: =SUM(W82:W96) -> #REF! | Y97: =SUM(Y82:Y96) -> #REF! | AC97: =SUM(AC82:AC96) -> #REF! | AE97: =SUM(AE82:AE96) -> #REF! | AG97: =SUM(AG82:AG96) -> #REF! | AI97: =SUM(AI82:AI96) -> #REF! | AK97: =SUM(AK82:AK96) -> #REF! | AM97: =SUM(AM82:AM96) -> #REF! | AO97: =SUM(AO82:AO96) -> #REF! | AQ97: =SUM(AQ82:AQ96) -> #REF! | AS97: =SUM(AS82:AS96) -> 0 | AU97: =SUM(AU82:AU96) -> #REF! | AW97: =SUM(AW82:AW96) -> #REF! | AY97: =SUM(I97:AW97) -> #REF!
B98: 3.5 | C98: Preliminary | F98: 0.08 | G98: of Construction Cost | I98: =$F$98*I97 -> 7329908 | K98: =$F$98*K97 -> 0 | M98: =$F$98*M97 -> #REF! | O98: =$F$98*O97 -> #REF! | Q98: =$F$98*Q97 -> #REF! | S98: =$F$98*S97 -> #REF! | W98: =$F$98*W97 -> #REF! | Y98: =$F$98*Y97 -> #REF! | AC98: =$F$98*AC97 -> #REF! | AE98: =$F$98*AE97 -> #REF! | AG98: =$F$98*AG97 -> #REF! | AI98: =$F$98*AI97 -> #REF! | AK98: =$F$98*AK97 -> #REF! | AM98: =$F$98*AM97 -> #REF! | AO98: =$F$98*AO97 -> #REF! | AQ98: =$F$98*AQ97 -> #REF! | AS98: =$F$98*AS97 -> 0 | AU98: =$F$98*AU97 -> #REF! | AW98: =$F$98*AW97 -> #REF! | AY98: =SUM(I98:AW98) -> #REF!
B99: 3.6 | C99: Contingency | F99: 0.05 | G99: of Construction Cost | I99: =$F$99*I97 -> 4581192.5 | K99: =$F$99*K97 -> 0 | M99: =$F$99*M97 -> #REF! | O99: =$F$99*O97 -> #REF! | Q99: =$F$99*Q97 -> #REF! | S99: =$F$99*S97 -> #REF! | W99: =$F$99*W97 -> #REF! | Y99: =$F$99*Y97 -> #REF! | AC99: =$F$99*AC97 -> #REF! | AE99: =$F$99*AE97 -> #REF! | AG99: =$F$99*AG97 -> #REF! | AI99: =$F$99*AI97 -> #REF! | AK99: =$F$99*AK97 -> #REF! | AM99: =$F$99*AM97 -> #REF! | AO99: =$F$99*AO97 -> #REF! | AQ99: =$F$99*AQ97 -> #REF! | AS99: =$F$99*AS97 -> 0 | AU99: =$F$99*AU97 -> #REF! | AW99: =$F$99*AW97 -> #REF! | AY99: =SUM(I99:AW99) -> #REF!
B100: 3.7 | C100: SST | E100: Commercial Only | F100: 0.06 | G100: of Construction Cost | Q100: =$F$100*Q97 -> #REF! | S100: =$F$100*S85 -> #REF! | W100: =$F$100*W97 -> #REF! | Y100: =$F$100*Y97 -> #REF! | AW100: =$F$100*AW97 -> #REF! | AY100: =SUM(I100:AW100) -> #REF!
B101: 3.8 | C101: Contract Stamping Fee | F101: 0.001 | G101: of Construction Cost | I101: =F101*I97 -> 91623.85
A103: 4 | B103: STRATA TITLE APPLICATION FEES & SURVEY FEES | I103: =SUM(I104:I105) -> 420000 | K103: =SUM(K104:K105) -> #REF! | M103: =SUM(M104:M105) -> #REF! | O103: =SUM(O104:O105) -> #REF! | Q103: =SUM(Q104:Q105) -> 0 | S103: =SUM(S104:S105) -> #REF! | W103: =SUM(W104:W105) -> #REF! | Y103: =SUM(Y104:Y105) -> #REF! | AC103: =SUM(AC104:AC105) -> #REF! | AE103: =SUM(AE104:AE105) -> #REF! | AG103: =SUM(AG104:AG105) -> #REF! | AI103: =SUM(AI104:AI105) -> #REF! | AK103: =SUM(AK104:AK105) -> #REF! | AM103: =SUM(AM104:AM105) -> #REF! | AO103: =SUM(AO104:AO105) -> #REF! | AQ103: =SUM(AQ104:AQ105) -> #REF! | AS103: =SUM(AS104:AS105) -> 0 | AU103: =SUM(AU104:AU105) -> #REF! | AW103: =SUM(AW104:AW105) -> #REF! | AY103: =SUM(AY104:AY105) -> #REF!
G104: 5000 | I104: =$G$104*I11 -> 420000 | K104: =$G$104*K11 -> #REF! | M104: =$G$104*M11 -> #REF! | O104: =$G$104*O11 -> #REF! | Q104: =$G$104*Q11 -> 0 | S104: =$G$104*S11 -> #REF! | W104: =$G$104*W11 -> #REF! | Y104: =$G$104*Y11 -> #REF! | AC104: =$G$104*AC11 -> #REF! | AE104: =$G$104*AE11 -> #REF! | AG104: =$G$104*AG11 -> #REF! | AI104: =$G$104*AI11 -> #REF! | AK104: =$G$104*AK11 -> #REF! | AM104: =$G$104*AM11 -> #REF! | AO104: =$G$104*AO11 -> #REF! | AQ104: =$G$104*AQ11 -> #REF! | AS104: =$G$104*AS11 -> 0 | AU104: =$G$104*AU11 -> #REF! | AW104: =$G$104*AW11 -> #REF! | AY104: =SUM(I104:AW104) -> #REF!
A106: 5 | B106: PLANNING SUBMISSION FEES & BUILDING PLAN FEES | I106: =SUM(I107:I108) -> 84000 | K106: =SUM(K107:K108) -> #REF! | M106: =SUM(M107:M108) -> #REF! | O106: =SUM(O107:O108) -> #REF! | Q106: =SUM(Q107:Q108) -> 0 | S106: =SUM(S107:S108) -> #REF! | W106: =SUM(W107:W108) -> #REF! | Y106: =SUM(Y107:Y108) -> #REF! | AC106: =SUM(AC107:AC108) -> #REF! | AE106: =SUM(AE107:AE108) -> #REF! | AG106: =SUM(AG107:AG108) -> #REF! | AI106: =SUM(AI107:AI108) -> #REF! | AK106: =SUM(AK107:AK108) -> #REF! | AM106: =SUM(AM107:AM108) -> #REF! | AO106: =SUM(AO107:AO108) -> #REF! | AQ106: =SUM(AQ107:AQ108) -> #REF! | AS106: =SUM(AS107:AS108) -> 0 | AU106: =SUM(AU107:AU108) -> #REF! | AW106: =SUM(AW107:AW108) -> #REF! | AY106: =SUM(AY107:AY108) -> #REF!
G107: 1000 | I107: =$G$107*I11 -> 84000 | K107: =$G$107*K11 -> #REF! | M107: =$G$107*M11 -> #REF! | O107: =$G$107*O11 -> #REF! | Q107: =$G$107*Q11 -> 0 | S107: =$G$107*S11 -> #REF! | W107: =$G$107*W11 -> #REF! | Y107: =$G$107*Y11 -> #REF! | AC107: =$G$107*AC11 -> #REF! | AE107: =$G$107*AE11 -> #REF! | AG107: =$G$107*AG11 -> #REF! | AI107: =$G$107*AI11 -> #REF! | AK107: =$G$107*AK11 -> #REF! | AM107: =$G$107*AM11 -> #REF! | AO107: =$G$107*AO11 -> #REF! | AQ107: =$G$107*AQ11 -> #REF! | AS107: =$G$107*AS11 -> 0 | AU107: =$G$107*AU11 -> #REF! | AW107: =$G$107*AW11 -> #REF! | AY107: =SUM(I107:AW107) -> #REF!
A109: 6 | B109: CONTRIBUTION TO AUTHORITIES | I109: =SUM(I110:I117) -> 4301628 | K109: =SUM(K110:K117) -> #REF! | M109: =SUM(M110:M117) -> #REF! | O109: =SUM(O110:O117) -> #REF! | Q109: =SUM(Q110:Q117) -> 0 | S109: =SUM(S110:S117) -> #REF! | W109: =SUM(W110:W117) -> #REF! | Y109: =SUM(Y110:Y117) -> #REF! | AC109: =SUM(AC110:AC117) -> #REF! | AE109: =SUM(AE110:AE117) -> #REF! | AG109: =SUM(AG110:AG117) -> #REF! | AI109: =SUM(AI110:AI117) -> #REF! | AK109: =SUM(AK110:AK117) -> #REF! | AM109: =SUM(AM110:AM117) -> #REF! | AO109: =SUM(AO110:AO117) -> #REF! | AQ109: =SUM(AQ110:AQ117) -> #REF! | AS109: =SUM(AS110:AS117) -> 0 | AU109: =SUM(AU110:AU117) -> #REF! | AW109: =SUM(AW110:AW117) -> #REF! | AY109: =SUM(AY110:AY117) -> #REF!
B110: 9.1 | C110: Development Charges | F110: 0.01 | G110: of NDV | I110: =$F$110*I61 -> 1764000 | K110: =$F$110*K61 -> #REF! | M110: =$F$110*M61 -> 0 | O110: =$F$110*O61 -> 0 | Q110: =$F$110*Q61 -> 0 | S110: =$F$110*S61 -> 0 | W110: =+W61*$F110 -> 0 | Y110: =+Y61*$F110 -> 0 | AC110: =+AC61*$F110 -> 0 | AE110: =+AE61*$F110 -> 0 | AG110: =+AG61*$F110 -> 0 | AI110: =+AI61*$F110 -> 0 | AK110: =+AK61*$F110 -> 0 | AM110: =+AM61*$F110 -> 0 | AO110: =+AO61*$F110 -> 0 | AQ110: =+AQ61*$F110 -> 0 | AS110: =+AS61*$F110 -> 0 | AU110: =+AU61*$F110 -> 0 | AW110: =+AW61*$F110 -> 0 | AY110: =SUM(I110:AW110) -> #REF!
B111: =B110+0.1 -> 9.2 | C111: SYABAS | F111: 0.0025 | G111: of NDV | I111: =$F$111*I61 -> 441000 | K111: =$F$111*K61 -> #REF! | M111: =$F$111*M61 -> 0 | O111: =$F$111*O61 -> 0 | Q111: =$F$111*Q61 -> 0 | S111: =$F$111*S61 -> 0 | W111: =$F$111*W61 -> 0 | Y111: =$F$111*Y61 -> 0 | AC111: =$F$111*AC61 -> 0 | AE111: =$F$111*AE61 -> 0 | AG111: =$F$111*AG61 -> 0 | AI111: =$F$111*AI61 -> 0 | AK111: =$F$111*AK61 -> 0 | AM111: =$F$111*AM61 -> 0 | AO111: =$F$111*AO61 -> 0 | AQ111: =$F$111*AQ61 -> 0 | AS111: =$F$111*AS61 -> 0 | AU111: =$F$111*AU61 -> 0 | AW111: =$F$111*AW61 -> 0 | AY111: =SUM(I111:AW111) -> #REF!
B112: =B111+0.1 -> 9.3 | C112: IWK & JPS | F112: 0.01 | G112: of NDV | I112: =$F$112*I61 -> 1764000 | K112: =$F$112*K61 -> #REF! | M112: =$F$112*M61 -> 0 | O112: =$F$112*O61 -> 0 | Q112: =$F$112*Q61 -> 0 | S112: =$F$112*S61 -> 0 | W112: =$F$112*W61 -> 0 | Y112: =$F$112*Y61 -> 0 | AC112: =$F$112*AC61 -> 0 | AE112: =$F$112*AE61 -> 0 | AG112: =$F$112*AG61 -> 0 | AI112: =$F$112*AI61 -> 0 | AK112: =$F$112*AK61 -> 0 | AM112: =$F$112*AM61 -> 0 | AO112: =$F$112*AO61 -> 0 | AQ112: =$F$112*AQ61 -> 0 | AS112: =$F$112*AS61 -> 0 | AU112: =$F$112*AU61 -> 0 | AW112: =$F$112*AW61 -> 0 | AY112: =SUM(I112:AW112) -> #REF!
B113: =B112+0.1 -> 9.4 | C113: TNB | F113: 1750 | G113: per Unit | I113: =$F$113*I11 -> 147000 | K113: =$F$113*K11 -> #REF! | M113: =$F$113*M11 -> #REF! | O113: =$F$113*O11 -> #REF! | Q113: =$F$113*Q11 -> 0 | S113: =$F$113*S11 -> #REF! | W113: =$F$113*W11 -> #REF! | Y113: =$F$113*Y11 -> #REF! | AC113: =$F$113*AC11 -> #REF! | AE113: =$F$113*AE11 -> #REF! | AG113: =$F$113*AG11 -> #REF! | AI113: =$F$113*AI11 -> #REF! | AK113: =$F$113*AK11 -> #REF! | AM113: =$F$113*AM11 -> #REF! | AO113: =$F$113*AO11 -> #REF! | AQ113: =$F$113*AQ11 -> #REF! | AS113: =$F$113*AS11 -> 0 | AU113: =$F$113*AU11 -> #REF! | AW113: =$F$113*AW11 -> #REF! | AY113: =SUM(I113:AW113) -> #REF!
B114: 9.5 | C114: TM Fibre Optic | F114: 2000 | G114: per Unit | I114: =$F$114*I11 -> 168000 | K114: =$F$114*K11 -> #REF! | M114: =$F$114*M11 -> #REF! | O114: =$F$114*O11 -> #REF! | Q114: =$F$114*Q11 -> 0 | S114: =$F$114*S11 -> #REF! | W114: =$F$114*W11 -> #REF! | Y114: =$F$114*Y11 -> #REF! | AC114: =$F$114*AC11 -> #REF! | AE114: =$F$114*AE11 -> #REF! | AG114: =$F$114*AG11 -> #REF! | AI114: =$F$114*AI11 -> #REF! | AK114: =$F$114*AK11 -> #REF! | AM114: =$F$114*AM11 -> #REF! | AO114: =$F$114*AO11 -> #REF! | AQ114: =$F$114*AQ11 -> #REF! | AS114: =$F$114*AS11 -> 0 | AU114: =$F$114*AU11 -> #REF! | AW114: =$F$114*AW11 -> #REF! | AY114: =SUM(I114:AW114) -> #REF!
B115: 9.6 | C115: Road & Drainage | F115: 6000 | G115: per Acre | I115: =$F$115*I8 -> 17628 | K115: =$F$115*K8 -> 0 | M115: =$F$115*M8 -> 0 | O115: =$F$115*O8 -> 0 | Q115: =$F$115*Q8 -> 0 | S115: =$F$115*S8 -> 0 | W115: =$F$115*W8 -> 0 | Y115: =$F$115*Y8 -> 0 | AC115: =$F$115*AC8 -> 0 | AE115: =$F$115*AE8 -> 0 | AG115: =$F$115*AG8 -> 0 | AI115: =$F$115*AI8 -> 0 | AK115: =+AK8*$F115 -> 0 | AM115: =+AM8*$F115 -> 0 | AO115: =+AO8*$F115 -> 0 | AQ115: =+AQ8*$F115 -> 0 | AS115: =+AS8*$F115 -> 0 | AU115: =+AU8*$F115 -> 0 | AW115: =+AW8*$F115 -> 0 | AY115: =SUM(I115:AW115) -> 17628
B116: 9.7 | C116: School Contribution | AY116: =SUM(I116:AW116) -> 0
B117: 9.8 | C117: Improvement Service Fund ("ISF") | AY117: =SUM(I117:AW117) -> 0
B118: 9.9 | C118: Green RE
B119: 9.1 | C119: CONQUAS & QLASSIC
...

Sheet Cashflow
A1: BRDB LAND — MONTHLY CASHFLOW MODEL (RM'000)
A2: All values RM'000 | Blue = inputs | Black = formulas | Green = linked from Feasibility Study
C3: Year 1 | O3: Year 2 | AA3: Year 3 | AM3: Year 4 | AY3: Year 5
A4: DESCRIPTION | B4: BASIS / TOTAL (RM'000) | C4: Jan '26 | D4: Feb '26 | E4: Mar '26 | F4: Apr '26 | G4: May '26 | H4: Jun '26 | I4: Jul '26 | J4: Aug '26 | K4: Sep '26 | L4: Oct '26 | M4: Nov '26 | N4: Dec '26 | O4: Jan '27 | P4: Feb '27 | Q4: Mar '27 | R4: Apr '27 | S4: May '27 | T4: Jun '27 | U4: Jul '27 | V4: Aug '27 | W4: Sep '27 | X4: Oct '27 | Y4: Nov '27 | Z4: Dec '27 | AA4: Jan '28 | AB4: Feb '28 | AC4: Mar '28 | AD4: Apr '28 | AE4: May '28 | AF4: Jun '28 | AG4: Jul '28 | AH4: Aug '28 | AI4: Sep '28 | AJ4: Oct '28 | AK4: Nov '28 | AL4: Dec '28 | AM4: Jan '29 | AN4: Feb '29 | AO4: Mar '29 | AP4: Apr '29 | AQ4: May '29 | AR4: Jun '29 | AS4: Jul '29 | AT4: Aug '29 | AU4: Sep '29 | AV4: Oct '29 | AW4: Nov '29 | AX4: Dec '29 | AY4: Jan '30 | AZ4: Feb '30 | BA4: Mar '30 | BB4: Apr '30 | BC4: May '30 | BD4: Jun '30 | BE4: Jul '30 | BF4: Aug '30 | BG4: Sep '30 | BH4: Oct '30 | BI4: Nov '30 | BJ4: Dec '30 | BK4: TOTAL
A5: Start date | C5: 46023 | D5: 46054 | E5: 46082 | F5: 46113 | G5: 46143 | H5: 46174 | I5: 46204 | J5: 46235 | K5: 46266 | L5: 46296 | M5: 46327 | N5: 46357 | O5: 46388 | P5: 46419 | Q5: 46447 | R5: 46478 | S5: 46508 | T5: 46539 | U5: 46569 | V5: 46600 | W5: 46631 | X5: 46661 | Y5: 46692 | Z5: 46722 | AA5: 46753 | AB5: 46784 | AC5: 46813 | AD5: 46844 | AE5: 46874 | AF5: 46905 | AG5: 46935 | AH5: 46966 | AI5: 46997 | AJ5: 47027 | AK5: 47058 | AL5: 47088 | AM5: 47119 | AN5: 47150 | AO5: 47178 | AP5: 47209 | AQ5: 47239 | AR5: 47270 | AS5: 47300 | AT5: 47331 | AU5: 47362 | AV5: 47392 | AW5: 47423 | AX5: 47453 | AY5: 47484 | AZ5: 47515 | BA5: 47543 | BB5: 47574 | BC5: 47604 | BD5: 47635 | BE5: 47665 | BF5: 47696 | BG5: 47727 | BH5: 47757 | BI5: 47788 | BJ5: 47818
A7: A. PROJECT ASSUMPTIONS
A8: Project name | B8: BRDB Land Development
A9: Development period (years) | B9: 5
A10: Project start | B10: January 2026
A11: Total GDV (RM'000) | B11: ='Feasibility Study'!AY38/1000 -> #REF!
A12: Total NDV (RM'000) | B12: ='Feasibility Study'!AY61/1000 -> #REF!
A13: Total GDC (RM'000) | B13: ='Feasibility Study'!AY148/1000 -> #REF!
A14: Total NDP (RM'000) | B14: ='Feasibility Study'!AY161/1000 -> #REF!
A15: Land cost (RM'000) | B15: ='Feasibility Study'!AY72/1000 -> 12797.928
A16: Construction cost (RM'000) | B16: ='Feasibility Study'!AY79/1000 -> #REF!
A17: Annual interest rate | B17: 0.0455
A18: Target IRR (hurdle) | B18: 0.16
A20: B. MONTHLY SALES ABSORPTION SCHEDULE (% of NDV collected per month)
A21: S-curve absorption — slow launch M1–M6, peak Y2–Y3, tail-off Y4–Y5. Edit % in blue.
A22: Phase | B22: Type | C22: Jan | D22: Feb | E22: Mar | F22: Apr | G22: May | H22: Jun | I22: Jul | J22: Aug | K22: Sep | L22: Oct | M22: Nov | N22: Dec | O22: Jan | P22: Feb | Q22: Mar | R22: Apr | S22: May | T22: Jun | U22: Jul | V22: Aug | W22: Sep | X22: Oct | Y22: Nov | Z22: Dec | AA22: Jan | AB22: Feb | AC22: Mar | AD22: Apr | AE22: May | AF22: Jun | AG22: Jul | AH22: Aug | AI22: Sep | AJ22: Oct | AK22: Nov | AL22: Dec | AM22: Jan | AN22: Feb | AO22: Mar | AP22: Apr | AQ22: May | AR22: Jun | AS22: Jul | AT22: Aug | AU22: Sep | AV22: Oct | AW22: Nov | AX22: Dec | AY22: Jan | AZ22: Feb | BA22: Mar | BB22: Apr | BC22: May | BD22: Jun | BE22: Jul | BF22: Aug | BG22: Sep | BH22: Oct | BI22: Nov | BJ22: Dec | BK22: Total %
A23: Ph 1a | B23: residential | C23: 0.01 | D23: 0.01 | E23: 0.01 | F23: 0.02 | G23: 0.02 | H23: 0.02 | I23: 0.02 | J23: 0.02 | K23: 0.02 | L23: 0.03 | M23: 0.03 | N23: 0.03 | O23: 0.03 | P23: 0.03 | Q23: 0.03 | R23: 0.04 | S23: 0.04 | T23: 0.04 | U23: 0.04 | V23: 0.04 | W23: 0.04 | X23: 0.04 | Y23: 0.03 | Z23: 0.03 | AA23: 0.03 | AB23: 0.03 | AC23: 0.03 | AD23: 0.02 | AE23: 0.02 | AF23: 0.02 | AG23: 0.02 | AH23: 0.02 | AI23: 0.02 | AJ23: 0.02 | AK23: 0.02 | AL23: 0.02 | AM23: 0.01 | AN23: 0.01 | AO23: 0.01 | AP23: 0.01 | AQ23: 0.01 | AR23: 0.01 | AS23: 0 | AT23: 0 | AU23: 0 | AV23: 0 | AW23: 0 | AX23: 0 | AY23: 0 | AZ23: 0 | BA23: 0 | BB23: 0 | BC23: 0 | BD23: 0 | BE23: 0 | BF23: 0 | BG23: 0 | BH23: 0 | BI23: 0 | BJ23: 0 | BK23: =SUM(C23:BJ23) -> 1
A24: Ph 1b | B24: residential | C24: 0.01 | D24: 0.01 | E24: 0.01 | F24: 0.02 | G24: 0.02 | H24: 0.02 | I24: 0.02 | J24: 0.02 | K24: 0.02 | L24: 0.03 | M24: 0.03 | N24: 0.03 | O24: 0.03 | P24: 0.03 | Q24: 0.03 | R24: 0.04 | S24: 0.04 | T24: 0.04 | U24: 0.04 | V24: 0.04 | W24: 0.04 | X24: 0.04 | Y24: 0.03 | Z24: 0.03 | AA24: 0.03 | AB24: 0.03 | AC24: 0.03 | AD24: 0.02 | AE24: 0.02 | AF24: 0.02 | AG24: 0.02 | AH24: 0.02 | AI24: 0.02 | AJ24: 0.02 | AK24: 0.02 | AL24: 0.02 | AM24: 0.01 | AN24: 0.01 | AO24: 0.01 | AP24: 0.01 | AQ24: 0.01 | AR24: 0.01 | AS24: 0 | AT24: 0 | AU24: 0 | AV24: 0 | AW24: 0 | AX24: 0 | AY24: 0 | AZ24: 0 | BA24: 0 | BB24: 0 | BC24: 0 | BD24: 0 | BE24: 0 | BF24: 0 | BG24: 0 | BH24: 0 | BI24: 0 | BJ24: 0 | BK24: =SUM(C24:BJ24) -> 1
A25: Ph 1c | B25: affordable | C25: 0.02 | D25: 0.02 | E25: 0.03 | F25: 0.03 | G25: 0.03 | H25: 0.05 | I25: 0.04 | J25: 0.04 | K25: 0.04 | L25: 0.04 | M25: 0.04 | N25: 0.04 | O25: 0.04 | P25: 0.04 | Q25: 0.04 | R25: 0.04 | S25: 0.03 | T25: 0.03 | U25: 0.03 | V25: 0.03 | W25: 0.03 | X25: 0.03 | Y25: 0.03 | Z25: 0.03 | AA25: 0.02 | AB25: 0.02 | AC25: 0.02 | AD25: 0.02 | AE25: 0.02 | AF25: 0.02 | AG25: 0.01 | AH25: 0.01 | AI25: 0.01 | AJ25: 0.01 | AK25: 0.01 | AL25: 0.01 | AM25: 0 | AN25: 0 | AO25: 0 | AP25: 0 | AQ25: 0 | AR25: 0 | AS25: 0 | AT25: 0 | AU25: 0 | AV25: 0 | AW25: 0 | AX25: 0 | AY25: 0 | AZ25: 0 | BA25: 0 | BB25: 0 | BC25: 0 | BD25: 0 | BE25: 0 | BF25: 0 | BG25: 0 | BH25: 0 | BI25: 0 | BJ25: 0 | BK25: =SUM(C25:BJ25) -> 1
A26: Ph 1d | B26: affordable | C26: 0.02 | D26: 0.02 | E26: 0.03 | F26: 0.03 | G26: 0.03 | H26: 0.05 | I26: 0.04 | J26: 0.04 | K26: 0.04 | L26: 0.04 | M26: 0.04 | N26: 0.04 | O26: 0.04 | P26: 0.04 | Q26: 0.04 | R26: 0.04 | S26: 0.03 | T26: 0.03 | U26: 0.03 | V26: 0.03 | W26: 0.03 | X26: 0.03 | Y26: 0.03 | Z26: 0.03 | AA26: 0.02 | AB26: 0.02 | AC26: 0.02 | AD26: 0.02 | AE26: 0.02 | AF26: 0.02 | AG26: 0.01 | AH26: 0.01 | AI26: 0.01 | AJ26: 0.01 | AK26: 0.01 | AL26: 0.01 | AM26: 0 | AN26: 0 | AO26: 0 | AP26: 0 | AQ26: 0 | AR26: 0 | AS26: 0 | AT26: 0 | AU26: 0 | AV26: 0 | AW26: 0 | AX26: 0 | AY26: 0 | AZ26: 0 | BA26: 0 | BB26: 0 | BC26: 0 | BD26: 0 | BE26: 0 | BF26: 0 | BG26: 0 | BH26: 0 | BI26: 0 | BJ26: 0 | BK26: =SUM(C26:BJ26) -> 1
A27: Ph 1e | B27: commercial | C27: 0.02 | D27: 0.03 | E27: 0.03 | F27: 0.04 | G27: 0.04 | H27: 0.04 | I27: 0.04 | J27: 0.04 | K27: 0.05 | L27: 0.05 | M27: 0.05 | N27: 0.05 | O27: 0.05 | P27: 0.05 | Q27: 0.05 | R27: 0.05 | S27: 0.04 | T27: 0.04 | U27: 0.04 | V27: 0.04 | W27: 0.03 | X27: 0.03 | Y27: 0.02 | Z27: 0.02 | AA27: 0.01 | AB27: 0.01 | AC27: 0.01 | AD27: 0.01 | AE27: 0.01 | AF27: 0.01 | AG27: 0 | AH27: 0 | AI27: 0 | AJ27: 0 | AK27: 0 | AL27: 0 | AM27: 0 | AN27: 0 | AO27: 0 | AP27: 0 | AQ27: 0 | AR27: 0 | AS27: 0 | AT27: 0 | AU27: 0 | AV27: 0 | AW27: 0 | AX27: 0 | AY27: 0 | AZ27: 0 | BA27: 0 | BB27: 0 | BC27: 0 | BD27: 0 | BE27: 0 | BF27: 0 | BG27: 0 | BH27: 0 | BI27: 0 | BJ27: 0 | BK27: =SUM(C27:BJ27) -> 1
A28: Ph 1f | B28: residential | C28: 0.01 | D28: 0.01 | E28: 0.01 | F28: 0.02 | G28: 0.02 | H28: 0.02 | I28: 0.02 | J28: 0.02 | K28: 0.02 | L28: 0.03 | M28: 0.03 | N28: 0.03 | O28: 0.03 | P28: 0.03 | Q28: 0.03 | R28: 0.04 | S28: 0.04 | T28: 0.04 | U28: 0.04 | V28: 0.04 | W28: 0.04 | X28: 0.04 | Y28: 0.03 | Z28: 0.03 | AA28: 0.03 | AB28: 0.03 | AC28: 0.03 | AD28: 0.02 | AE28: 0.02 | AF28: 0.02 | AG28: 0.02 | AH28: 0.02 | AI28: 0.02 | AJ28: 0.02 | AK28: 0.02 | AL28: 0.02 | AM28: 0.01 | AN28: 0.01 | AO28: 0.01 | AP28: 0.01 | AQ28: 0.01 | AR28: 0.01 | AS28: 0 | AT28: 0 | AU28: 0 | AV28: 0 | AW28: 0 | AX28: 0 | AY28: 0 | AZ28: 0 | BA28: 0 | BB28: 0 | BC28: 0 | BD28: 0 | BE28: 0 | BF28: 0 | BG28: 0 | BH28: 0 | BI28: 0 | BJ28: 0 | BK28: =SUM(C28:BJ28) -> 1
A29: Ph 1g | B29: commercial | C29: 0.02 | D29: 0.03 | E29: 0.03 | F29: 0.04 | G29: 0.04 | H29: 0.04 | I29: 0.04 | J29: 0.04 | K29: 0.05 | L29: 0.05 | M29: 0.05 | N29: 0.05 | O29: 0.05 | P29: 0.05 | Q29: 0.05 | R29: 0.05 | S29: 0.04 | T29: 0.04 | U29: 0.04 | V29: 0.04 | W29: 0.03 | X29: 0.03 | Y29: 0.02 | Z29: 0.02 | AA29: 0.01 | AB29: 0.01 | AC29: 0.01 | AD29: 0.01 | AE29: 0.01 | AF29: 0.01 | AG29: 0 | AH29: 0 | AI29: 0 | AJ29: 0 | AK29: 0 | AL29: 0 | AM29: 0 | AN29: 0 | AO29: 0 | AP29: 0 | AQ29: 0 | AR29: 0 | AS29: 0 | AT29: 0 | AU29: 0 | AV29: 0 | AW29: 0 | AX29: 0 | AY29: 0 | AZ29: 0 | BA29: 0 | BB29: 0 | BC29: 0 | BD29: 0 | BE29: 0 | BF29: 0 | BG29: 0 | BH29: 0 | BI29: 0 | BJ29: 0 | BK29: =SUM(C29:BJ29) -> 1
A30: Ph 1h | B30: commercial | C30: 0.02 | D30: 0.03 | E30: 0.03 | F30: 0.04 | G30: 0.04 | H30: 0.04 | I30: 0.04 | J30: 0.04 | K30: 0.05 | L30: 0.05 | M30: 0.05 | N30: 0.05 | O30: 0.05 | P30: 0.05 | Q30: 0.05 | R30: 0.05 | S30: 0.04 | T30: 0.04 | U30: 0.04 | V30: 0.04 | W30: 0.03 | X30: 0.03 | Y30: 0.02 | Z30: 0.02 | AA30: 0.01 | AB30: 0.01 | AC30: 0.01 | AD30: 0.01 | AE30: 0.01 | AF30: 0.01 | AG30: 0 | AH30: 0 | AI30: 0 | AJ30: 0 | AK30: 0 | AL30: 0 | AM30: 0 | AN30: 0 | AO30: 0 | AP30: 0 | AQ30: 0 | AR30: 0 | AS30: 0 | AT30: 0 | AU30: 0 | AV30: 0 | AW30: 0 | AX30: 0 | AY30: 0 | AZ30: 0 | BA30: 0 | BB30: 0 | BC30: 0 | BD30: 0 | BE30: 0 | BF30: 0 | BG30: 0 | BH30: 0 | BI30: 0 | BJ30: 0 | BK30: =SUM(C30:BJ30) -> 1
A31: Ph 2a | B31: residential | C31: 0.01 | D31: 0.01 | E31: 0.01 | F31: 0.02 | G31: 0.02 | H31: 0.02 | I31: 0.02 | J31: 0.02 | K31: 0.02 | L31: 0.03 | M31: 0.03 | N31: 0.03 | O31: 0.03 | P31: 0.03 | Q31: 0.03 | R31: 0.04 | S31: 0.04 | T31: 0.04 | U31: 0.04 | V31: 0.04 | W31: 0.04 | X31: 0.04 | Y31: 0.03 | Z31: 0.03 | AA31: 0.03 | AB31: 0.03 | AC31: 0.03 | AD31: 0.02 | AE31: 0.02 | AF31: 0.02 | AG31: 0.02 | AH31: 0.02 | AI31: 0.02 | AJ31: 0.02 | AK31: 0.02 | AL31: 0.02 | AM31: 0.01 | AN31: 0.01 | AO31: 0.01 | AP31: 0.01 | AQ31: 0.01 | AR31: 0.01 | AS31: 0 | AT31: 0 | AU31: 0 | AV31: 0 | AW31: 0 | AX31: 0 | AY31: 0 | AZ31: 0 | BA31: 0 | BB31: 0 | BC31: 0 | BD31: 0 | BE31: 0 | BF31: 0 | BG31: 0 | BH31: 0 | BI31: 0 | BJ31: 0 | BK31: =SUM(C31:BJ31) -> 1
A32: Ph 2b | B32: residential | C32: 0.01 | D32: 0.01 | E32: 0.01 | F32: 0.02 | G32: 0.02 | H32: 0.02 | I32: 0.02 | J32: 0.02 | K32: 0.02 | L32: 0.03 | M32: 0.03 | N32: 0.03 | O32: 0.03 | P32: 0.03 | Q32: 0.03 | R32: 0.04 | S32: 0.04 | T32: 0.04 | U32: 0.04 | V32: 0.04 | W32: 0.04 | X32: 0.04 | Y32: 0.03 | Z32: 0.03 | AA32: 0.03 | AB32: 0.03 | AC32: 0.03 | AD32: 0.02 | AE32: 0.02 | AF32: 0.02 | AG32: 0.02 | AH32: 0.02 | AI32: 0.02 | AJ32: 0.02 | AK32: 0.02 | AL32: 0.02 | AM32: 0.01 | AN32: 0.01 | AO32: 0.01 | AP32: 0.01 | AQ32: 0.01 | AR32: 0.01 | AS32: 0 | AT32: 0 | AU32: 0 | AV32: 0 | AW32: 0 | AX32: 0 | AY32: 0 | AZ32: 0 | BA32: 0 | BB32: 0 | BC32: 0 | BD32: 0 | BE32: 0 | BF32: 0 | BG32: 0 | BH32: 0 | BI32: 0 | BJ32: 0 | BK32: =SUM(C32:BJ32) -> 1
A33: Ph 2c | B33: residential | C33: 0.01 | D33: 0.01 | E33: 0.01 | F33: 0.02 | G33: 0.02 | H33: 0.02 | I33: 0.02 | J33: 0.02 | K33: 0.02 | L33: 0.03 | M33: 0.03 | N33: 0.03 | O33: 0.03 | P33: 0.03 | Q33: 0.03 | R33: 0.04 | S33: 0.04 | T33: 0.04 | U33: 0.04 | V33: 0.04 | W33: 0.04 | X33: 0.04 | Y33: 0.03 | Z33: 0.03 | AA33: 0.03 | AB33: 0.03 | AC33: 0.03 | AD33: 0.02 | AE33: 0.02 | AF33: 0.02 | AG33: 0.02 | AH33: 0.02 | AI33: 0.02 | AJ33: 0.02 | AK33: 0.02 | AL33: 0.02 | AM33: 0.01 | AN33: 0.01 | AO33: 0.01 | AP33: 0.01 | AQ33: 0.01 | AR33: 0.01 | AS33: 0 | AT33: 0 | AU33: 0 | AV33: 0 | AW33: 0 | AX33: 0 | AY33: 0 | AZ33: 0 | BA33: 0 | BB33: 0 | BC33: 0 | BD33: 0 | BE33: 0 | BF33: 0 | BG33: 0 | BH33: 0 | BI33: 0 | BJ33: 0 | BK33: =SUM(C33:BJ33) -> 1
A34: Ph 2d | B34: residential | C34: 0.01 | D34: 0.01 | E34: 0.01 | F34: 0.02 | G34: 0.02 | H34: 0.02 | I34: 0.02 | J34: 0.02 | K34: 0.02 | L34: 0.03 | M34: 0.03 | N34: 0.03 | O34: 0.03 | P34: 0.03 | Q34: 0.03 | R34: 0.04 | S34: 0.04 | T34: 0.04 | U34: 0.04 | V34: 0.04 | W34: 0.04 | X34: 0.04 | Y34: 0.03 | Z34: 0.03 | AA34: 0.03 | AB34: 0.03 | AC34: 0.03 | AD34: 0.02 | AE34: 0.02 | AF34: 0.02 | AG34: 0.02 | AH34: 0.02 | AI34: 0.02 | AJ34: 0.02 | AK34: 0.02 | AL34: 0.02 | AM34: 0.01 | AN34: 0.01 | AO34: 0.01 | AP34: 0.01 | AQ34: 0.01 | AR34: 0.01 | AS34: 0 | AT34: 0 | AU34: 0 | AV34: 0 | AW34: 0 | AX34: 0 | AY34: 0 | AZ34: 0 | BA34: 0 | BB34: 0 | BC34: 0 | BD34: 0 | BE34: 0 | BF34: 0 | BG34: 0 | BH34: 0 | BI34: 0 | BJ34: 0 | BK34: =SUM(C34:BJ34) -> 1
... A40: Ph 2j | B40: commercial | C40: 0.02 | D40: 0.03 | E40: 0.03 | F40: 0.04 | G40: 0.04 | H40: 0.04 | I40: 0.04 | J40: 0.04 | K40: 0.05 | L40: 0.05 | M40: 0.05 | N40: 0.05 | O40: 0.05 | P40: 0.05 | Q40: 0.05 | R40: 0.05 | S40: 0.04 | T40: 0.04 | U40: 0.04 | V40: 0.04 | W40: 0.03 | X40: 0.03 | Y40: 0.02 | Z40: 0.02 | AA40: 0.01 | AB40: 0.01 | AC40: 0.01 | AD40: 0.01 | AE40: 0.01 | AF40: 0.01 | AG40: 0 | AH40: 0 | AI40: 0 | AJ40: 0 | AK40: 0 | AL40: 0 | AM40: 0 | AN40: 0 | AO40: 0 | AP40: 0 | AQ40: 0 | AR40: 0 | AS40: 0 | AT40: 0 | AU40: 0 | AV40: 0 | AW40: 0 | AX40: 0 | AY40: 0 | AZ40: 0 | BA40: 0 | BB40: 0 | BC40: 0 | BD40: 0 | BE40: 0 | BF40: 0 | BG40: 0 | BH40: 0 | BI40: 0 | BJ40: 0 | BK40: =SUM(C40:BJ40) -> 1
A42: C. SALES RECEIPTS (RM'000) — NDV × Monthly Absorption %
A43: Phase | B43: NDV (RM'000) | C43: Jan | D43: Feb | E43: Mar | F43: Apr | G43: May | H43: Jun | I43: Jul | J43: Aug | K43: Sep | L43: Oct | M43: Nov | N43: Dec | O43: Jan | P43: Feb | Q43: Mar | R43: Apr | S43: May | T43: Jun | U43: Jul | V43: Aug | W43: Sep | X43: Oct | Y43: Nov | Z43: Dec | AA43: Jan | AB43: Feb | AC43: Mar | AD43: Apr | AE43: May | AF43: Jun | AG43: Jul | AH43: Aug | AI43: Sep | AJ43: Oct | AK43: Nov | AL43: Dec | AM43: Jan | AN43: Feb | AO43: Mar | AP43: Apr | AQ43: May | AR43: Jun | AS43: Jul | AT43: Aug | AU43: Sep | AV43: Oct | AW43: Nov | AX43: Dec | AY43: Jan | AZ43: Feb | BA43: Mar | BB43: Apr | BC43: May | BD43: Jun | BE43: Jul | BF43: Aug | BG43: Sep | BH43: Oct | BI43: Nov | BJ43: Dec | BK43: Total
A44: Ph 1a | B44: ='Feasibility Study'!I61/1000 -> 176400 | C44: =IF($B$44=0,0,$B$44*C23) -> 1764 | D44: =IF($B$44=0,0,$B$44*D23) -> 1764 | E44: =IF($B$44=0,0,$B$44*E23) -> 1764 | F44: =IF($B$44=0,0,$B$44*F23) -> 3528 | G44: =IF($B$44=0,0,$B$44*G23) -> 3528 | H44: =IF($B$44=0,0,$B$44*H23) -> 3528 | I44: =IF($B$44=0,0,$B$44*I23) -> 3528 | J44: =IF($B$44=0,0,$B$44*J23) -> 3528 | ... BJ44: =IF($B$44=0,0,$B$44*BJ23) -> 0 | BK44: =SUM(C44:BJ44) -> 176400
A45: Ph 1b | B45: ='Feasibility Study'!K61/1000 -> #REF! | C45: =IF($B$45=0,0,$B$45*C24) -> #REF! | D45: =IF($B$45=0,0,$B$45*D24) -> #REF! | E45: =IF($B$45=0,0,$B$45*E24) -> #REF! | F45: =IF($B$45=0,0,$B$45*F24) -> #REF! | G45: =IF($B$45=0,0,$B$45*G24) -> #REF! | H45: =IF($B$45=0,0,$B$45*H24) -> #REF! | I45: =IF($B$45=0,0,$B$45*I24) -> #REF! | J45: =IF($B$45=0,0,$B$45*J24) -> #REF! | ... BJ45: =IF($B$45=0,0,$B$45*BJ24) -> #REF! | BK45: =SUM(C45:BJ45) -> #REF!
A46: Ph 1c | B46: ='Feasibility Study'!M61/1000 -> 0 | C46: =IF($B$46=0,0,$B$46*C25) -> 0 | D46: =IF($B$46=0,0,$B$46*D25) -> 0 | E46: =IF($B$46=0,0,$B$46*E25) -> 0 | F46: =IF($B$46=0,0,$B$46*F25) -> 0 | G46: =IF($B$46=0,0,$B$46*G25) -> 0 | H46: =IF($B$46=0,0,$B$46*H25) -> 0 | I46: =IF($B$46=0,0,$B$46*I25) -> 0 | J46: =IF($B$46=0,0,$B$46*J25) -> 0 | ... BJ46: =IF($B$46=0,0,$B$46*BJ25) -> 0 | BK46: =SUM(C46:BJ46) -> 0
A47: Ph 1d | B47: ='Feasibility Study'!O61/1000 -> 0 | C47: =IF($B$47=0,0,$B$47*C26) -> 0 | D47: =IF($B$47=0,0,$B$47*D26) -> 0 | E47: =IF($B$47=0,0,$B$47*E26) -> 0 | F47: =IF($B$47=0,0,$B$47*F26) -> 0 | G47: =IF($B$47=0,0,$B$47*G26) -> 0 | H47: =IF($B$47=0,0,$B$47*H26) -> 0 | I47: =IF($B$47=0,0,$B$47*I26) -> 0 | J47: =IF($B$47=0,0,$B$47*J26) -> 0 | ... BJ47: =IF($B$47=0,0,$B$47*BJ26) -> 0 | BK47: =SUM(C47:BJ47) -> 0
A48: Ph 1e | B48: ='Feasibility Study'!Q61/1000 -> 0 | C48: =IF($B$48=0,0,$B$48*C27) -> 0 | D48: =IF($B$48=0,0,$B$48*D27) -> 0 | E48: =IF($B$48=0,0,$B$48*E27) -> 0 | F48: =IF($B$48=0,0,$B$48*F27) -> 0 | G48: =IF($B$48=0,0,$B$48*G27) -> 0 | H48: =IF($B$48=0,0,$B$48*H27) -> 0 | I48: =IF($B$48=0,0,$B$48*I27) -> 0 | J48: =IF($B$48=0,0,$B$48*J27) -> 0 | ... BJ48: =IF($B$48=0,0,$B$48*BJ27) -> 0 | BK48: =SUM(C48:BJ48) -> 0
A49: Ph 1f | B49: ='Feasibility Study'!S61/1000 -> 0 | C49: =IF($B$49=0,0,$B$49*C28) -> 0 | D49: =IF($B$49=0,0,$B$49*D28) -> 0 | E49: =IF($B$49=0,0,$B$49*E28) -> 0 | F49: =IF($B$49=0,0,$B$49*F28) -> 0 | G49: =IF($B$49=0,0,$B$49*G28) -> 0 | H49: =IF($B$49=0,0,$B$49*H28) -> 0 | I49: =IF($B$49=0,0,$B$49*I28) -> 0 | J49: =IF($B$49=0,0,$B$49*J28) -> 0 | ... BJ49: =IF($B$49=0,0,$B$49*BJ28) -> 0 | BK49: =SUM(C49:BJ49) -> 0
A50: Ph 1g | B50: ='Feasibility Study'!W61/1000 -> 0 | C50: =IF($B$50=0,0,$B$50*C29) -> 0 | D50: =IF($B$50=0,0,$B$50*D29) -> 0 | E50: =IF($B$50=0,0,$B$50*E29) -> 0 | F50: =IF($B$50=0,0,$B$50*F29) -> 0 | G50: =IF($B$50=0,0,$B$50*G29) -> 0 | H50: =IF($B$50=0,0,$B$50*H29) -> 0 | I50: =IF($B$50=0,0,$B$50*I29) -> 0 | J50: =IF($B$50=0,0,$B$50*J29) -> 0 | ... BJ50: =IF($B$50=0,0,$B$50*BJ29) -> 0 | BK50: =SUM(C50:BJ50) -> 0
A51: Ph 1h | B51: ='Feasibility Study'!Y61/1000 -> 0 | C51: =IF($B$51=0,0,$B$51*C30) -> 0 | D51: =IF($B$51=0,0,$B$51*D30) -> 0 | E51: =IF($B$51=0,0,$B$51*E30) -> 0 | F51: =IF($B$51=0,0,$B$51*F30) -> 0 | G51: =IF($B$51=0,0,$B$51*G30) -> 0 | H51: =IF($B$51=0,0,$B$51*H30) -> 0 | I51: =IF($B$51=0,0,$B$51*I30) -> 0 | J51: =IF($B$51=0,0,$B$51*J30) -> 0 | ... BJ51: =IF($B$51=0,0,$B$51*BJ30) -> 0 | BK51: =SUM(C51:BJ51) -> 0
A52: Ph 2a | B52: ='Feasibility Study'!AC61/1000 -> 0 | C52: =IF($B$52=0,0,$B$52*C31) -> 0 | D52: =IF($B$52=0,0,$B$52*D31) -> 0 | E52: =IF($B$52=0,0,$B$52*E31) -> 0 | F52: =IF($B$52=0,0,$B$52*F31) -> 0 | G52: =IF($B$52=0,0,$B$52*G31) -> 0 | H52: =IF($B$52=0,0,$B$52*H31) -> 0 | I52: =IF($B$52=0,0,$B$52*I31) -> 0 | J52: =IF($B$52=0,0,$B$52*J31) -> 0 | ... BJ52: =IF($B$52=0,0,$B$52*BJ31) -> 0 | BK52: =SUM(C52:BJ52) -> 0
A53: Ph 2b | B53: ='Feasibility Study'!AE61/1000 -> 0 | C53: =IF($B$53=0,0,$B$53*C32) -> 0 | D53: =IF($B$53=0,0,$B$53*D32) -> 0 | E53: =IF($B$53=0,0,$B$53*E32) -> 0 | F53: =IF($B$53=0,0,$B$53*F32) -> 0 | G53: =IF($B$53=0,0,$B$53*G32) -> 0 | H53: =IF($B$53=0,0,$B$53*H32) -> 0 | I53: =IF($B$53=0,0,$B$53*I32) -> 0 | J53: =IF($B$53=0,0,$B$53*J32) -> 0 | ... BJ53: =IF($B$53=0,0,$B$53*BJ32) -> 0 | BK53: =SUM(C53:BJ53) -> 0
A54: Ph 2c | B54: ='Feasibility Study'!AG61/1000 -> 0 | C54: =IF($B$54=0,0,$B$54*C33) -> 0 | D54: =IF($B$54=0,0,$B$54*D33) -> 0 | E54: =IF($B$54=0,0,$B$54*E33) -> 0 | F54: =IF($B$54=0,0,$B$54*F33) -> 0 | G54: =IF($B$54=0,0,$B$54*G33) -> 0 | H54: =IF($B$54=0,0,$B$54*H33) -> 0 | I54: =IF($B$54=0,0,$B$54*I33) -> 0 | J54: =IF($B$54=0,0,$B$54*J33) -> 0 | ... BJ54: =IF($B$54=0,0,$B$54*BJ33) -> 0 | BK54: =SUM(C54:BJ54) -> 0
A55: Ph 2d | B55: ='Feasibility Study'!AI61/1000 -> 0 | C55: =IF($B$55=0,0,$B$55*C34) -> 0 | D55: =IF($B$55=0,0,$B$55*D34) -> 0 | E55: =IF($B$55=0,0,$B$55*E34) -> 0 | F55: =IF($B$55=0,0,$B$55*F34) -> 0 | G55: =IF($B$55=0,0,$B$55*G34) -> 0 | H55: =IF($B$55=0,0,$B$55*H34) -> 0 | I55: =IF($B$55=0,0,$B$55*I34) -> 0 | J55: =IF($B$55=0,0,$B$55*J34) -> 0 | ... BJ55: =IF($B$55=0,0,$B$55*BJ34) -> 0 | BK55: =SUM(C55:BJ55) -> 0
A56: Ph 2e | B56: ='Feasibility Study'!AK61/1000 -> 0 | C56: =IF($B$56=0,0,$B$56*C35) -> 0 | D56: =IF($B$56=0,0,$B$56*D35) -> 0 | E56: =IF($B$56=0,0,$B$56*E35) -> 0 | F56: =IF($B$56=0,0,$B$56*F35) -> 0 | G56: =IF($B$56=0,0,$B$56*G35) -> 0 | H56: =IF($B$56=0,0,$B$56*H35) -> 0 | I56: =IF($B$56=0,0,$B$56*I35) -> 0 | J56: =IF($B$56=0,0,$B$56*J35) -> 0 | ... BJ56: =IF($B$56=0,0,$B$56*BJ35) -> 0 | BK56: =SUM(C56:BJ56) -> 0
A57: Ph 2f | B57: ='Feasibility Study'!AM61/1000 -> 0 | C57: =IF($B$57=0,0,$B$57*C36) -> 0 | D57: =IF($B$57=0,0,$B$57*D36) -> 0 | E57: =IF($B$57=0,0,$B$57*E36) -> 0 | F57: =IF($B$57=0,0,$B$57*F36) -> 0 | G57: =IF($B$57=0,0,$B$57*G36) -> 0 | H57: =IF($B$57=0,0,$B$57*H36) -> 0 | I57: =IF($B$57=0,0,$B$57*I36) -> 0 | J57: =IF($B$57=0,0,$B$57*J36) -> 0 | ... BJ57: =IF($B$57=0,0,$B$57*BJ36) -> 0 | BK57: =SUM(C57:BJ57) -> 0
A58: Ph 2g1 | B58: ='Feasibility Study'!AO61/1000 -> 0 | C58: =IF($B$58=0,0,$B$58*C37) -> 0 | D58: =IF($B$58=0,0,$B$58*D37) -> 0 | E58: =IF($B$58=0,0,$B$58*E37) -> 0 | F58: =IF($B$58=0,0,$B$58*F37) -> 0 | G58: =IF($B$58=0,0,$B$58*G37) -> 0 | H58: =IF($B$58=0,0,$B$58*H37) -> 0 | I58: =IF($B$58=0,0,$B$58*I37) -> 0 | J58: =IF($B$58=0,0,$B$58*J37) -> 0 | ... BJ58: =IF($B$58=0,0,$B$58*BJ37) -> 0 | BK58: =SUM(C58:BJ58) -> 0
A59: Ph 2g2 | B59: ='Feasibility Study'!AQ61/1000 -> 0 | C59: =IF($B$59=0,0,$B$59*C38) -> 0 | D59: =IF($B$59=0,0,$B$59*D38) -> 0 | E59: =IF($B$59=0,0,$B$59*E38) -> 0 | F59: =IF($B$59=0,0,$B$59*F38) -> 0 | G59: =IF($B$59=0,0,$B$59*G38) -> 0 | H59: =IF($B$59=0,0,$B$59*H38) -> 0 | I59: =IF($B$59=0,0,$B$59*I38) -> 0 | J59: =IF($B$59=0,0,$B$59*J38) -> 0 | ... BJ59: =IF($B$59=0,0,$B$59*BJ38) -> 0 | BK59: =SUM(C59:BJ59) -> 0
A60: Ph 2h | B60: ='Feasibility Study'!AU61/1000 -> 0 | C60: =IF($B$60=0,0,$B$60*C39) -> 0 | D60: =IF($B$60=0,0,$B$60*D39) -> 0 | E60: =IF($B$60=0,0,$B$60*E39) -> 0 | F60: =IF($B$60=0,0,$B$60*F39) -> 0 | G60: =IF($B$60=0,0,$B$60*G39) -> 0 | H60: =IF($B$60=0,0,$B$60*H39) -> 0 | I60: =IF($B$60=0,0,$B$60*I39) -> 0 | J60: =IF($B$60=0,0,$B$60*J39) -> 0 | ... BJ60: =IF($B$60=0,0,$B$60*BJ39) -> 0 | BK60: =SUM(C60:BJ60) -> 0
A61: Ph 2j | B61: ='Feasibility Study'!AW61/1000 -> 0 | C61: =IF($B$61=0,0,$B$61*C40) -> 0 | D61: =IF($B$61=0,0,$B$61*D40) -> 0 | E61: =IF($B$61=0,0,$B$61*E40) -> 0 | F61: =IF($B$61=0,0,$B$61*F40) -> 0 | G61: =IF($B$61=0,0,$B$61*G40) -> 0 | H61: =IF($B$61=0,0,$B$61*H40) -> 0 | I61: =IF($B$61=0,0,$B$61*I40) -> 0 | J61: =IF($B$61=0,0,$B$61*J40) -> 0 | ... BJ61: =IF($B$61=0,0,$B$61*BJ40) -> 0 | BK61: =SUM(C61:BJ61) -> 0
A62: TOTAL SALES RECEIPTS | C62: =SUM(C44:C61) -> #REF! | D62: =SUM(D44:D61) -> #REF! | E62: =SUM(E44:E61) -> #REF! | F62: =SUM(F44:F61) -> #REF! | G62: =SUM(G44:G61) -> #REF! | H62: =SUM(H44:H61) -> #REF! | I62: =SUM(I44:I61) -> #REF! | J62: =SUM(J44:J61) -> #REF! | ... BJ62: =SUM(BJ44:BJ61) -> #REF! | BK62: =SUM(C62:BJ62) -> #REF!
A64: D. LAND COST (RM'000) — Deposit M1, Balance spread M2–M12
A65: Item | B65: Total | C65: Jan | D65: Feb | E65: Mar | F65: Apr | G65: May | H65: Jun | I65: Jul | J65: Aug | K65: Sep | L65: Oct | M65: Nov | N65: Dec | O65: Jan | P65: Feb | Q65: Mar | R65: Apr | S65: May | T65: Jun | U65: Jul | V65: Aug | W65: Sep | X65: Oct | Y65: Nov | Z65: Dec | AA65: Jan | AB65: Feb | AC65: Mar | AD65: Apr | AE65: May | AF65: Jun | AG65: Jul | AH65: Aug | AI65: Sep | AJ65: Oct | AK65: Nov | AL65: Dec | AM65: Jan | AN65: Feb | AO65: Mar | AP65: Apr | AQ65: May | AR65: Jun | AS65: Jul | AT65: Aug | AU65: Sep | AV65: Oct | AW65: Nov | AX65: Dec | AY65: Jan | AZ65: Feb | BA65: Mar | BB65: Apr | BC65: May | BD65: Jun | BE65: Jul | BF65: Aug | BG65: Sep | BH65: Oct | BI65: Nov | BJ65: Dec | BK65: Total
A66: Deposit (10%) | B66: ='Feasibility Study'!AY72/1000*0.1 -> 1279.7928 | C66: =$B$66/1 -> 1279.7928 | D66: - | E66: - | F66: - | G66: - | H66: - | I66: - | J66: - | K66: - | L66: - | M66: - | N66: - | O66: - | P66: - | Q66: - | R66: - | S66: - | T66: - | U66: - | V66: - | W66: - | X66: - | Y66: - | Z66: - | AA66: - | AB66: - | AC66: - | AD66: - | AE66: - | AF66: - | AG66: - | AH66: - | AI66: - | AJ66: - | AK66: - | AL66: - | AM66: - | AN66: - | AO66: - | AP66: - | AQ66: - | AR66: - | AS66: - | AT66: - | AU66: - | AV66: - | AW66: - | AX66: - | AY66: - | AZ66: - | BA66: - | BB66: - | BC66: - | BD66: - | BE66: - | BF66: - | BG66: - | BH66: - | BI66: - | BJ66: - | BK66: =SUM(C66:BJ66) -> 1279.7928
A67: Balance SPA — M2–M6 | B67: ='Feasibility Study'!AY72/1000*0.45 -> 5759.0676 | C67: - | D67: =$B$67/5 -> 1151.8135 | E67: =$B$67/5 -> 1151.8135 | F67: =$B$67/5 -> 1151.8135 | G67: =$B$67/5 -> 1151.8135 | H67: =$B$67/5 -> 1151.8135 | I67: - | J67: - | K67: - | L67: - | M67: - | N67: - | O67: - | P67: - | Q67: - | R67: - | S67: - | T67: - | U67: - | V67: - | W67: - | X67: - | Y67: - | Z67: - | AA67: - | AB67: - | AC67: - | AD67: - | AE67: - | AF67: - | AG67: - | AH67: - | AI67: - | AJ67: - | AK67: - | AL67: - | AM67: - | AN67: - | AO67: - | AP67: - | AQ67: - | AR67: - | AS67: - | AT67: - | AU67: - | AV67: - | AW67: - | AX67: - | AY67: - | AZ67: - | BA67: - | BB67: - | BC67: - | BD67: - | BE67: - | BF67: - | BG67: - | BH67: - | BI67: - | BJ67: - | BK67: =SUM(C67:BJ67) -> 5759.0676
A68: Balance SPA — M7–M12 | B68: ='Feasibility Study'!AY72/1000*0.45 -> 5759.0676 | C68: - | D68: - | E68: - | F68: - | G68: - | H68: - | I68: =$B$68/6 -> 959.8446 | J68: =$B$68/6 -> 959.8446 | K68: =$B$68/6 -> 959.8446 | L68: =$B$68/6 -> 959.8446 | M68: =$B$68/6 -> 959.8446 | N68: =$B$68/6 -> 959.8446 | O68: - | P68: - | Q68: - | R68: - | S68: - | T68: - | U68: - | V68: - | W68: - | X68: - | Y68: - | Z68: - | AA68: - | AB68: - | AC68: - | AD68: - | AE68: - | AF68: - | AG68: - | AH68: - | AI68: - | AJ68: - | AK68: - | AL68: - | AM68: - | AN68: - | AO68: - | AP68: - | AQ68: - | AR68: - | AS68: - | AT68: - | AU68: - | AV68: - | AW68: - | AX68: - | AY68: - | AZ68: - | BA68: - | BB68: - | BC68: - | BD68: - | BE68: - | BF68: - | BG68: - | BH68: - | BI68: - | BJ68: - | BK68: =SUM(C68:BJ68) -> 5759.0676
A69: Land conversion premium | B69: ='Feasibility Study'!AY72/1000*0.15 -> 1919.6892 | C69: - | D69: - | E69: - | F69: - | G69: - | H69: - | I69: - | J69: - | K69: - | L69: - | M69: - | N69: =$B$69/1 -> 1919.6892 | O69: - | P69: - | Q69: - | R69: - | S69: - | T69: - | U69: - | V69: - | W69: - | X69: - | Y69: - | Z69: - | AA69: - | AB69: - | AC69: - | AD69: - | AE69: - | AF69: - | AG69: - | AH69: - | AI69: - | AJ69: - | AK69: - | AL69: - | AM69: - | AN69: - | AO69: - | AP69: - | AQ69: - | AR69: - | AS69: - | AT69: - | AU69: - | AV69: - | AW69: - | AX69: - | AY69: - | AZ69: - | BA69: - | BB69: - | BC69: - | BD69: - | BE69: - | BF69: - | BG69: - | BH69: - | BI69: - | BJ69: - | BK69: =SUM(C69:BJ69) -> 1919.6892
A70: TOTAL LAND COST | C70: =IF(ISNUMBER(C66),C66,0)+IF(ISNUMBER(C67),C67,0)+IF(ISNUMBER(C68),C68,0)+IF(ISNUMBER(C69),C69,0) -> 1279.7928 | D70: =IF(ISNUMBER(D66),D66,0)+IF(ISNUMBER(D67),D67,0)+IF(ISNUMBER(D68),D68,0)+IF(ISNUMBER(D69),D69,0) -> 1151.8135 | E70: =IF(ISNUMBER(E66),E66,0)+IF(ISNUMBER(E67),E67,0)+IF(ISNUMBER(E68),E68,0)+IF(ISNUMBER(E69),E69,0) -> 1151.8135 | F70: =IF(ISNUMBER(F66),F66,0)+IF(ISNUMBER(F67),F67,0)+IF(ISNUMBER(F68),F68,0)+IF(ISNUMBER(F69),F69,0) -> 1151.8135 | G70: =IF(ISNUMBER(G66),G66,0)+IF(ISNUMBER(G67),G67,0)+IF(ISNUMBER(G68),G68,0)+IF(ISNUMBER(G69),G69,0) -> 1151.8135 | H70: =IF(ISNUMBER(H66),H66,0)+IF(ISNUMBER(H67),H67,0)+IF(ISNUMBER(H68),H68,0)+IF(ISNUMBER(H69),H69,0) -> 1151.8135 | I70: =IF(ISNUMBER(I66),I66,0)+IF(ISNUMBER(I67),I67,0)+IF(ISNUMBER(I68),I68,0)+IF(ISNUMBER(I69),I69,0) -> 959.8446 | J70: =IF(ISNUMBER(J66),J66,0)+IF(ISNUMBER(J67),J67,0)+IF(ISNUMBER(J68),J68,0)+IF(ISNUMBER(J69),J69,0) -> 959.8446 | ... BJ70: =IF(ISNUMBER(BJ66),BJ66,0)+IF(ISNUMBER(BJ67),BJ67,0)+IF(ISNUMBER(BJ68),BJ68,0)+IF(ISNUMBER(BJ69),BJ69,0) -> 0 | BK70: =SUM(C70:BJ70) -> 14717.617
A72: E. CONSTRUCTION COST (RM'000) — S-curve drawdown over 48 months
A73: Item | B73: Total (RM'000) | C73: Jan | D73: Feb | E73: Mar | F73: Apr | G73: May | H73: Jun | I73: Jul | J73: Aug | K73: Sep | L73: Oct | M73: Nov | N73: Dec | O73: Jan | P73: Feb | Q73: Mar | R73: Apr | S73: May | T73: Jun | U73: Jul | V73: Aug | W73: Sep | X73: Oct | Y73: Nov | Z73: Dec | AA73: Jan | AB73: Feb | AC73: Mar | AD73: Apr | AE73: May | AF73: Jun | AG73: Jul | AH73: Aug | AI73: Sep | AJ73: Oct | AK73: Nov | AL73: Dec | AM73: Jan | AN73: Feb | AO73: Mar | AP73: Apr | AQ73: May | AR73: Jun | AS73: Jul | AT73: Aug | AU73: Sep | AV73: Oct | AW73: Nov | AX73: Dec | AY73: Jan | AZ73: Feb | BA73: Mar | BB73: Apr | BC73: May | BD73: Jun | BE73: Jul | BF73: Aug | BG73: Sep | BH73: Oct | BI73: Nov | BJ73: Dec | BK73: Total
A74: Building works — residential (55%) | B74: ='Feasibility Study'!AY79/1000*0.55 -> #REF! | C74: =$B$74*0.011013 -> #REF! | D74: =$B$74*0.013216 -> #REF! | E74: =$B$74*0.015418 -> #REF! | F74: =$B$74*0.017621 -> #REF! | G74: =$B$74*0.019824 -> #REF! | H74: =$B$74*0.022026 -> #REF! | I74: =$B$74*0.024229 -> #REF! | J74: =$B$74*0.026432 -> #REF! | K74: =$B$74*0.028634 -> #REF! | L74: =$B$74*0.028634 -> #REF! | M74: =$B$74*0.028634 -> #REF! | N74: =$B$74*0.028634 -> #REF! | O74: =$B$74*0.030837 -> #REF! | P74: =$B$74*0.030837 -> #REF! | Q74: =$B$74*0.030837 -> #REF! | R74: =$B$74*0.030837 -> #REF! | S74: =$B$74*0.030837 -> #REF! | T74: =$B$74*0.030837 -> #REF! | U74: =$B$74*0.030837 -> #REF! | V74: =$B$74*0.030837 -> #REF! | W74: =$B$74*0.028634 -> #REF! | X74: =$B$74*0.028634 -> #REF! | Y74: =$B$74*0.026432 -> #REF! | Z74: =$B$74*0.026432 -> #REF! | AA74: =$B$74*0.026432 -> #REF! | AB74: =$B$74*0.024229 -> #REF! | AC74: =$B$74*0.024229 -> #REF! | AD74: =$B$74*0.024229 -> #REF! | AE74: =$B$74*0.022026 -> #REF! | AF74: =$B$74*0.022026 -> #REF! | AG74: =$B$74*0.022026 -> #REF! | AH74: =$B$74*0.019824 -> #REF! | AI74: =$B$74*0.019824 -> #REF! | AJ74: =$B$74*0.019824 -> #REF! | AK74: =$B$74*0.017621 -> #REF! | AL74: =$B$74*0.017621 -> #REF! | AM74: =$B$74*0.017621 -> #REF! | AN74: =$B$74*0.015418 -> #REF! | AO74: =$B$74*0.015418 -> #REF! | AP74: =$B$74*0.013216 -> #REF! | AQ74: =$B$74*0.013216 -> #REF! | AR74: =$B$74*0.011013 -> #REF! | AS74: =$B$74*0.011013 -> #REF! | AT74: =$B$74*0.008811 -> #REF! | AU74: =$B$74*0.006608 -> #REF! | AV74: =$B$74*0.004405 -> #REF! | AW74: =$B$74*0.002203 -> #REF! | AX74: - | AY74: - | AZ74: - | BA74: - | BB74: - | BC74: - | BD74: - | BE74: - | BF74: - | BG74: - | BH74: - | BI74: - | BJ74: - | BK74: =SUM(C74:BJ74) -> #REF!
A75: Building works — commercial (15%) | B75: ='Feasibility Study'!AY79/1000*0.15 -> #REF! | C75: =$B$75*0.011013 -> #REF! | D75: =$B$75*0.013216 -> #REF! | E75: =$B$75*0.015418 -> #REF! | F75: =$B$75*0.017621 -> #REF! | G75: =$B$75*0.019824 -> #REF! | H75: =$B$75*0.022026 -> #REF! | I75: =$B$75*0.024229 -> #REF! | J75: =$B$75*0.026432 -> #REF! | K75: =$B$75*0.028634 -> #REF! | L75: =$B$75*0.028634 -> #REF! | M75: =$B$75*0.028634 -> #REF! | N75: =$B$75*0.028634 -> #REF! | O75: =$B$75*0.030837 -> #REF! | P75: =$B$75*0.030837 -> #REF! | Q75: =$B$75*0.030837 -> #REF! | R75: =$B$75*0.030837 -> #REF! | S75: =$B$75*0.030837 -> #REF! | T75: =$B$75*0.030837 -> #REF! | U75: =$B$75*0.030837 -> #REF! | V75: =$B$75*0.030837 -> #REF! | W75: =$B$75*0.028634 -> #REF! | X75: =$B$75*0.028634 -> #REF! | Y75: =$B$75*0.026432 -> #REF! | Z75: =$B$75*0.026432 -> #REF! | AA75: =$B$75*0.026432 -> #REF! | AB75: =$B$75*0.024229 -> #REF! | AC75: =$B$75*0.024229 -> #REF! | AD75: =$B$75*0.024229 -> #REF! | AE75: =$B$75*0.022026 -> #REF! | AF75: =$B$75*0.022026 -> #REF! | AG75: =$B$75*0.022026 -> #REF! | AH75: =$B$75*0.019824 -> #REF! | AI75: =$B$75*0.019824 -> #REF! | AJ75: =$B$75*0.019824 -> #REF! | AK75: =$B$75*0.017621 -> #REF! | AL75: =$B$75*0.017621 -> #REF! | AM75: =$B$75*0.017621 -> #REF! | AN75: =$B$75*0.015418 -> #REF! | AO75: =$B$75*0.015418 -> #REF! | AP75: =$B$75*0.013216 -> #REF! | AQ75: =$B$75*0.013216 -> #REF! | AR75: =$B$75*0.011013 -> #REF! | AS75: =$B$75*0.011013 -> #REF! | AT75: =$B$75*0.008811 -> #REF! | AU75: =$B$75*0.006608 -> #REF! | AV75: =$B$75*0.004405 -> #REF! | AW75: =$B$75*0.002203 -> #REF! | AX75: - | AY75: - | AZ75: - | BA75: - | BB75: - | BC75: - | BD75: - | BE75: - | BF75: - | BG75: - | BH75: - | BI75: - | BJ75: - | BK75: =SUM(C75:BJ75) -> #REF!
A76: Earthworks & infrastructure (15%) | B76: ='Feasibility Study'!AY79/1000*0.15 -> #REF! | C76: =$B$76*0.011013 -> #REF! | D76: =$B$76*0.013216 -> #REF! | E76: =$B$76*0.015418 -> #REF! | F76: =$B$76*0.017621 -> #REF! | G76: =$B$76*0.019824 -> #REF! | H76: =$B$76*0.022026 -> #REF! | I76: =$B$76*0.024229 -> #REF! | J76: =$B$76*0.026432 -> #REF! | K76: =$B$76*0.028634 -> #REF! | L76: =$B$76*0.028634 -> #REF! | M76: =$B$76*0.028634 -> #REF! | N76: =$B$76*0.028634 -> #REF! | O76: =$B$76*0.030837 -> #REF! | P76: =$B$76*0.030837 -> #REF! | Q76: =$B$76*0.030837 -> #REF! | R76: =$B$76*0.030837 -> #REF! | S76: =$B$76*0.030837 -> #REF! | T76: =$B$76*0.030837 -> #REF! | U76: =$B$76*0.030837 -> #REF! | V76: =$B$76*0.030837 -> #REF! | W76: =$B$76*0.028634 -> #REF! | X76: =$B$76*0.028634 -> #REF! | Y76: =$B$76*0.026432 -> #REF! | Z76: =$B$76*0.026432 -> #REF! | AA76: =$B$76*0.026432 -> #REF! | AB76: =$B$76*0.024229 -> #REF! | AC76: =$B$76*0.024229 -> #REF! | AD76: =$B$76*0.024229 -> #REF! | AE76: =$B$76*0.022026 -> #REF! | AF76: =$B$76*0.022026 -> #REF! | AG76: =$B$76*0.022026 -> #REF! | AH76: =$B$76*0.019824 -> #REF! | AI76: =$B$76*0.019824 -> #REF! | AJ76: =$B$76*0.019824 -> #REF! | AK76: =$B$76*0.017621 -> #REF! | AL76: =$B$76*0.017621 -> #REF! | AM76: =$B$76*0.017621 -> #REF! | AN76: =$B$76*0.015418 -> #REF! | AO76: =$B$76*0.015418 -> #REF! | AP76: =$B$76*0.013216 -> #REF! | AQ76: =$B$76*0.013216 -> #REF! | AR76: =$B$76*0.011013 -> #REF! | AS76: =$B$76*0.011013 -> #REF! | AT76: =$B$76*0.008811 -> #REF! | AU76: =$B$76*0.006608 -> #REF! | AV76: =$B$76*0.004405 -> #REF! | AW76: =$B$76*0.002203 -> #REF! | AX76: - | AY76: - | AZ76: - | BA76: - | BB76: - | BC76: - | BD76: - | BE76: - | BF76: - | BG76: - | BH76: - | BI76: - | BJ76: - | BK76: =SUM(C76:BJ76) -> #REF!
A77: Prelims & contingency (13%) | B77: ='Feasibility Study'!AY79/1000*0.13 -> #REF! | C77: =$B$77*0.011013 -> #REF! | D77: =$B$77*0.013216 -> #REF! | E77: =$B$77*0.015418 -> #REF! | F77: =$B$77*0.017621 -> #REF! | G77: =$B$77*0.019824 -> #REF! | H77: =$B$77*0.022026 -> #REF! | I77: =$B$77*0.024229 -> #REF! | J77: =$B$77*0.026432 -> #REF! | K77: =$B$77*0.028634 -> #REF! | L77: =$B$77*0.028634 -> #REF! | M77: =$B$77*0.028634 -> #REF! | N77: =$B$77*0.028634 -> #REF! | O77: =$B$77*0.030837 -> #REF! | P77: =$B$77*0.030837 -> #REF! | Q77: =$B$77*0.030837 -> #REF! | R77: =$B$77*0.030837 -> #REF! | S77: =$B$77*0.030837 -> #REF! | T77: =$B$77*0.030837 -> #REF! | U77: =$B$77*0.030837 -> #REF! | V77: =$B$77*0.030837 -> #REF! | W77: =$B$77*0.028634 -> #REF! | X77: =$B$77*0.028634 -> #REF! | Y77: =$B$77*0.026432 -> #REF! | Z77: =$B$77*0.026432 -> #REF! | AA77: =$B$77*0.026432 -> #REF! | AB77: =$B$77*0.024229 -> #REF! | AC77: =$B$77*0.024229 -> #REF! | AD77: =$B$77*0.024229 -> #REF! | AE77: =$B$77*0.022026 -> #REF! | AF77: =$B$77*0.022026 -> #REF! | AG77: =$B$77*0.022026 -> #REF! | AH77: =$B$77*0.019824 -> #REF! | AI77: =$B$77*0.019824 -> #REF! | AJ77: =$B$77*0.019824 -> #REF! | AK77: =$B$77*0.017621 -> #REF! | AL77: =$B$77*0.017621 -> #REF! | AM77: =$B$77*0.017621 -> #REF! | AN77: =$B$77*0.015418 -> #REF! | AO77: =$B$77*0.015418 -> #REF! | AP77: =$B$77*0.013216 -> #REF! | AQ77: =$B$77*0.013216 -> #REF! | AR77: =$B$77*0.011013 -> #REF! | AS77: =$B$77*0.011013 -> #REF! | AT77: =$B$77*0.008811 -> #REF! | AU77: =$B$77*0.006608 -> #REF! | AV77: =$B$77*0.004405 -> #REF! | AW77: =$B$77*0.002203 -> #REF! | AX77: - | AY77: - | AZ77: - | BA77: - | BB77: - | BC77: - | BD77: - | BE77: - | BF77: - | BG77: - | BH77: - | BI77: - | BJ77: - | BK77: =SUM(C77:BJ77) -> #REF!
A78: Consultancy fees (6.5% of GCC) | B78: ='Feasibility Study'!AY79/1000*0.065 -> #REF! | C78: =$B$78*0.011013 -> #REF! | D78: =$B$78*0.013216 -> #REF! | E78: =$B$78*0.015418 -> #REF! | F78: =$B$78*0.017621 -> #REF! | G78: =$B$78*0.019824 -> #REF! | H78: =$B$78*0.022026 -> #REF! | I78: =$B$78*0.024229 -> #REF! | J78: =$B$78*0.026432 -> #REF! | K78: =$B$78*0.028634 -> #REF! | L78: =$B$78*0.028634 -> #REF! | M78: =$B$78*0.028634 -> #REF! | N78: =$B$78*0.028634 -> #REF! | O78: =$B$78*0.030837 -> #REF! | P78: =$B$78*0.030837 -> #REF! | Q78: =$B$78*0.030837 -> #REF! | R78: =$B$78*0.030837 -> #REF! | S78: =$B$78*0.030837 -> #REF! | T78: =$B$78*0.030837 -> #REF! | U78: =$B$78*0.030837 -> #REF! | V78: =$B$78*0.030837 -> #REF! | W78: =$B$78*0.028634 -> #REF! | X78: =$B$78*0.028634 -> #REF! | Y78: =$B$78*0.026432 -> #REF! | Z78: =$B$78*0.026432 -> #REF! | AA78: =$B$78*0.026432 -> #REF! | AB78: =$B$78*0.024229 -> #REF! | AC78: =$B$78*0.024229 -> #REF! | AD78: =$B$78*0.024229 -> #REF! | AE78: =$B$78*0.022026 -> #REF! | AF78: =$B$78*0.022026 -> #REF! | AG78: =$B$78*0.022026 -> #REF! | AH78: =$B$78*0.019824 -> #REF! | AI78: =$B$78*0.019824 -> #REF! | AJ78: =$B$78*0.019824 -> #REF! | AK78: =$B$78*0.017621 -> #REF! | AL78: =$B$78*0.017621 -> #REF! | AM78: =$B$78*0.017621 -> #REF! | AN78: =$B$78*0.015418 -> #REF! | AO78: =$B$78*0.015418 -> #REF! | AP78: =$B$78*0.013216 -> #REF! | AQ78: =$B$78*0.013216 -> #REF! | AR78: =$B$78*0.011013 -> #REF! | AS78: =$B$78*0.011013 -> #REF! | AT78: =$B$78*0.008811 -> #REF! | AU78: =$B$78*0.006608 -> #REF! | AV78: =$B$78*0.004405 -> #REF! | AW78: =$B$78*0.002203 -> #REF! | AX78: - | AY78: - | AZ78: - | BA78: - | BB78: - | BC78: - | BD78: - | BE78: - | BF78: - | BG78: - | BH78: - | BI78: - | BJ78: - | BK78: =SUM(C78:BJ78) -> #REF!
A79: TOTAL CONSTRUCTION COST | C79: =IF(ISNUMBER(C74),C74,0)+IF(ISNUMBER(C75),C75,0)+IF(ISNUMBER(C76),C76,0)+IF(ISNUMBER(C77),C77,0)+IF(ISNUMBER(C78),C78,0) -> 0 | D79: =IF(ISNUMBER(D74),D74,0)+IF(ISNUMBER(D75),D75,0)+IF(ISNUMBER(D76),D76,0)+IF(ISNUMBER(D77),D77,0)+IF(ISNUMBER(D78),D78,0) -> 0 | E79: =IF(ISNUMBER(E74),E74,0)+IF(ISNUMBER(E75),E75,0)+IF(ISNUMBER(E76),E76,0)+IF(ISNUMBER(E77),E77,0)+IF(ISNUMBER(E78),E78,0) -> 0 | F79: =IF(ISNUMBER(F74),F74,0)+IF(ISNUMBER(F75),F75,0)+IF(ISNUMBER(F76),F76,0)+IF(ISNUMBER(F77),F77,0)+IF(ISNUMBER(F78),F78,0) -> 0 | G79: =IF(ISNUMBER(G74),G74,0)+IF(ISNUMBER(G75),G75,0)+IF(ISNUMBER(G76),G76,0)+IF(ISNUMBER(G77),G77,0)+IF(ISNUMBER(G78),G78,0) -> 0 | H79: =IF(ISNUMBER(H74),H74,0)+IF(ISNUMBER(H75),H75,0)+IF(ISNUMBER(H76),H76,0)+IF(ISNUMBER(H77),H77,0)+IF(ISNUMBER(H78),H78,0) -> 0 | I79: =IF(ISNUMBER(I74),I74,0)+IF(ISNUMBER(I75),I75,0)+IF(ISNUMBER(I76),I76,0)+IF(ISNUMBER(I77),I77,0)+IF(ISNUMBER(I78),I78,0) -> 0 | J79: =IF(ISNUMBER(J74),J74,0)+IF(ISNUMBER(J75),J75,0)+IF(ISNUMBER(J76),J76,0)+IF(ISNUMBER(J77),J77,0)+IF(ISNUMBER(J78),J78,0) -> 0 | ... BJ79: =IF(ISNUMBER(BJ74),BJ74,0)+IF(ISNUMBER(BJ75),BJ75,0)+IF(ISNUMBER(BJ76),BJ76,0)+IF(ISNUMBER(BJ77),BJ77,0)+IF(ISNUMBER(BJ78),BJ78,0) -> 0 | BK79: =SUM(C79:BJ79) -> 0
A81: F. OVERHEADS & MARKETING (RM'000) — spread evenly over 60 months
A82: Item | B82: Total (RM'000) | C82: Jan | D82: Feb | E82: Mar | F82: Apr | G82: May | H82: Jun | I82: Jul | J82: Aug | K82: Sep | L82: Oct | M82: Nov | N82: Dec | O82: Jan | P82: Feb | Q82: Mar | R82: Apr | S82: May | T82: Jun | U82: Jul | V82: Aug | W82: Sep | X82: Oct | Y82: Nov | Z82: Dec | AA82: Jan | AB82: Feb | AC82: Mar | AD82: Apr | AE82: May | AF82: Jun | AG82: Jul | AH82: Aug | AI82: Sep | AJ82: Oct | AK82: Nov | AL82: Dec | AM82: Jan | AN82: Feb | AO82: Mar | AP82: Apr | AQ82: May | AR82: Jun | AS82: Jul | AT82: Aug | AU82: Sep | AV82: Oct | AW82: Nov | AX82: Dec | AY82: Jan | AZ82: Feb | BA82: Mar | BB82: Apr | BC82: May | BD82: Jun | BE82: Jul | BF82: Aug | BG82: Sep | BH82: Oct | BI82: Nov | BJ82: Dec | BK82: Total
A83: Marketing & selling expenses (4% NDV) | B83: ='Feasibility Study'!AY61/1000*0.04 -> #REF! | C83: =IF($B$83=0,0,$B$83/60) -> #REF! | D83: =IF($B$83=0,0,$B$83/60) -> #REF! | E83: =IF($B$83=0,0,$B$83/60) -> #REF! | F83: =IF($B$83=0,0,$B$83/60) -> #REF! | G83: =IF($B$83=0,0,$B$83/60) -> #REF! | H83: =IF($B$83=0,0,$B$83/60) -> #REF! | I83: =IF($B$83=0,0,$B$83/60) -> #REF! | J83: =IF($B$83=0,0,$B$83/60) -> #REF! | ... BJ83: =IF($B$83=0,0,$B$83/60) -> #REF! | BK83: =SUM(C83:BJ83) -> #REF!
A84: Project dept overhead (1.4% NDV) | B84: ='Feasibility Study'!AY61/1000*0.014 -> #REF! | C84: =IF($B$84=0,0,$B$84/60) -> #REF! | D84: =IF($B$84=0,0,$B$84/60) -> #REF! | E84: =IF($B$84=0,0,$B$84/60) -> #REF! | F84: =IF($B$84=0,0,$B$84/60) -> #REF! | G84: =IF($B$84=0,0,$B$84/60) -> #REF! | H84: =IF($B$84=0,0,$B$84/60) -> #REF! | I84: =IF($B$84=0,0,$B$84/60) -> #REF! | J84: =IF($B$84=0,0,$B$84/60) -> #REF! | ... BJ84: =IF($B$84=0,0,$B$84/60) -> #REF! | BK84: =SUM(C84:BJ84) -> #REF!
A85: Head office overhead (3% NDV) | B85: ='Feasibility Study'!AY61/1000*0.03 -> #REF! | C85: =IF($B$85=0,0,$B$85/60) -> #REF! | D85: =IF($B$85=0,0,$B$85/60) -> #REF! | E85: =IF($B$85=0,0,$B$85/60) -> #REF! | F85: =IF($B$85=0,0,$B$85/60) -> #REF! | G85: =IF($B$85=0,0,$B$85/60) -> #REF! | H85: =IF($B$85=0,0,$B$85/60) -> #REF! | I85: =IF($B$85=0,0,$B$85/60) -> #REF! | J85: =IF($B$85=0,0,$B$85/60) -> #REF! | ... BJ85: =IF($B$85=0,0,$B$85/60) -> #REF! | BK85: =SUM(C85:BJ85) -> #REF!
A86: Corporate overhead (1% NDV) | B86: ='Feasibility Study'!AY61/1000*0.01 -> #REF! | C86: =IF($B$86=0,0,$B$86/60) -> #REF! | D86: =IF($B$86=0,0,$B$86/60) -> #REF! | E86: =IF($B$86=0,0,$B$86/60) -> #REF! | F86: =IF($B$86=0,0,$B$86/60) -> #REF! | G86: =IF($B$86=0,0,$B$86/60) -> #REF! | H86: =IF($B$86=0,0,$B$86/60) -> #REF! | I86: =IF($B$86=0,0,$B$86/60) -> #REF! | J86: =IF($B$86=0,0,$B$86/60) -> #REF! | ... BJ86: =IF($B$86=0,0,$B$86/60) -> #REF! | BK86: =SUM(C86:BJ86) -> #REF!
A87: Site admin cost (2% GCC) | B87: ='Feasibility Study'!AY79/1000*0.02 -> #REF! | C87: =IF($B$87=0,0,$B$87/60) -> #REF! | D87: =IF($B$87=0,0,$B$87/60) -> #REF! | E87: =IF($B$87=0,0,$B$87/60) -> #REF! | F87: =IF($B$87=0,0,$B$87/60) -> #REF! | G87: =IF($B$87=0,0,$B$87/60) -> #REF! | H87: =IF($B$87=0,0,$B$87/60) -> #REF! | I87: =IF($B$87=0,0,$B$87/60) -> #REF! | J87: =IF($B$87=0,0,$B$87/60) -> #REF! | ... BJ87: =IF($B$87=0,0,$B$87/60) -> #REF! | BK87: =SUM(C87:BJ87) -> #REF!
A88: Statutory contributions (3% NDV) | B88: ='Feasibility Study'!AY61/1000*0.03 -> #REF! | C88: =IF($B$88=0,0,$B$88/60) -> #REF! | D88: =IF($B$88=0,0,$B$88/60) -> #REF! | E88: =IF($B$88=0,0,$B$88/60) -> #REF! | F88: =IF($B$88=0,0,$B$88/60) -> #REF! | G88: =IF($B$88=0,0,$B$88/60) -> #REF! | H88: =IF($B$88=0,0,$B$88/60) -> #REF! | I88: =IF($B$88=0,0,$B$88/60) -> #REF! | J88: =IF($B$88=0,0,$B$88/60) -> #REF! | ... BJ88: =IF($B$88=0,0,$B$88/60) -> #REF! | BK88: =SUM(C88:BJ88) -> #REF!
A89: TOTAL OVERHEADS & MARKETING | C89: =C83+C84+C85+C86+C87+C88 -> #REF! | D89: =D83+D84+D85+D86+D87+D88 -> #REF! | E89: =E83+E84+E85+E86+E87+E88 -> #REF! | F89: =F83+F84+F85+F86+F87+F88 -> #REF! | G89: =G83+G84+G85+G86+G87+G88 -> #REF! | H89: =H83+H84+H85+H86+H87+H88 -> #REF! | I89: =I83+I84+I85+I86+I87+I88 -> #REF! | J89: =J83+J84+J85+J86+J87+J88 -> #REF! | ... BJ89: =BJ83+BJ84+BJ85+BJ86+BJ87+BJ88 -> #REF! | BK89: =SUM(C89:BJ89) -> #REF!
A91: TOTAL OUTFLOWS | C91: =IF(ISNUMBER(C70),C70,0)+IF(ISNUMBER(C79),C79,0)+C89 -> #REF! | D91: =IF(ISNUMBER(D70),D70,0)+IF(ISNUMBER(D79),D79,0)+D89 -> #REF! | E91: =IF(ISNUMBER(E70),E70,0)+IF(ISNUMBER(E79),E79,0)+E89 -> #REF! | F91: =IF(ISNUMBER(F70),F70,0)+IF(ISNUMBER(F79),F79,0)+F89 -> #REF! | G91: =IF(ISNUMBER(G70),G70,0)+IF(ISNUMBER(G79),G79,0)+G89 -> #REF! | H91: =IF(ISNUMBER(H70),H70,0)+IF(ISNUMBER(H79),H79,0)+H89 -> #REF! | I91: =IF(ISNUMBER(I70),I70,0)+IF(ISNUMBER(I79),I79,0)+I89 -> #REF! | J91: =IF(ISNUMBER(J70),J70,0)+IF(ISNUMBER(J79),J79,0)+J89 -> #REF! | ... BJ91: =IF(ISNUMBER(BJ70),BJ70,0)+IF(ISNUMBER(BJ79),BJ79,0)+BJ89 -> #REF! | BK91: =SUM(C91:BJ91) -> #REF!
A93: G. NET CASHFLOW SUMMARY
A94: Item | C94: Jan | D94: Feb | E94: Mar | F94: Apr | G94: May | H94: Jun | I94: Jul | J94: Aug | K94: Sep | L94: Oct | M94: Nov | N94: Dec | O94: Jan | P94: Feb | Q94: Mar | R94: Apr | S94: May | T94: Jun | U94: Jul | V94: Aug | W94: Sep | X94: Oct | Y94: Nov | Z94: Dec | AA94: Jan | AB94: Feb | AC94: Mar | AD94: Apr | AE94: May | AF94: Jun | AG94: Jul | AH94: Aug | AI94: Sep | AJ94: Oct | AK94: Nov | AL94: Dec | AM94: Jan | AN94: Feb | AO94: Mar | AP94: Apr | AQ94: May | AR94: Jun | AS94: Jul | AT94: Aug | AU94: Sep | AV94: Oct | AW94: Nov | AX94: Dec | AY94: Jan | AZ94: Feb | BA94: Mar | BB94: Apr | BC94: May | BD94: Jun | BE94: Jul | BF94: Aug | BG94: Sep | BH94: Oct | BI94: Nov | BJ94: Dec | BK94: Total
A95: Total inflows (sales receipts) | C95: =C62 -> #REF! | D95: =D62 -> #REF! | E95: =E62 -> #REF! | F95: =F62 -> #REF! | G95: =G62 -> #REF! | H95: =H62 -> #REF! | I95: =I62 -> #REF! | J95: =J62 -> #REF! | ... BJ95: =BJ62 -> #REF! | BK95: =SUM(C95:BJ95) -> #REF!
A96: Total outflows | C96: =C91 -> #REF! | D96: =D91 -> #REF! | E96: =E91 -> #REF! | F96: =F91 -> #REF! | G96: =G91 -> #REF! | H96: =H91 -> #REF! | I96: =I91 -> #REF! | J96: =J91 -> #REF! | ... BJ96: =BJ91 -> #REF! | BK96: =SUM(C96:BJ96) -> #REF!
A97: NET CASHFLOW | C97: =C95-C96 -> #REF! | D97: =D95-D96 -> #REF! | E97: =E95-E96 -> #REF! | F97: =F95-F96 -> #REF! | G97: =G95-G96 -> #REF! | H97: =H95-H96 -> #REF! | I97: =I95-I96 -> #REF! | J97: =J95-J96 -> #REF! | ... BJ97: =BJ95-BJ96 -> #REF! | BK97: =SUM(C97:BJ97) -> #REF!
A98: CUMULATIVE CASHFLOW | C98: =C97 -> #REF! | D98: =C98+D97 -> #REF! | E98: =D98+E97 -> #REF! | F98: =E98+F97 -> #REF! | G98: =F98+G97 -> #REF! | H98: =G98+H97 -> #REF! | I98: =H98+I97 -> #REF! | J98: =I98+J97 -> #REF! | K98: =J98+K97 -> #REF! | ... BJ98: =BI98+BJ97 -> #REF! | BK98: =BJ98 -> #REF!
A99: PEAK EQUITY EXPOSURE (minimum cumulative cashflow) | BK99: =MIN(C98:BJ98) -> #REF!

Sheet Returns
A1: BRDB LAND — RETURNS & SENSITIVITY ANALYSIS
A2: All values RM'000 | XIRR on 60 monthly cashflows | Blue = inputs | Green = linked from other sheets
A4: A. PROJECT SUMMARY
A5: Total GDV (RM'000) | B5: ='Feasibility Study'!AY38/1000 -> #REF!
A6: Total NDV (RM'000) | B6: ='Feasibility Study'!AY61/1000 -> #REF!
A7: Gross dev cost — GDC (RM'000) | B7: ='Feasibility Study'!AY148/1000 -> #REF!
A8: Net dev profit — NDP (RM'000) | B8: ='Feasibility Study'!AY161/1000 -> #REF!
A9: Dev margin % on NDV | B9: =IF(B6=0,0,B8/B6) -> #REF!
A10: Land cost (RM'000) | B10: ='Feasibility Study'!AY72/1000 -> 12797.928
A11: Construction cost (RM'000) | B11: ='Feasibility Study'!AY79/1000 -> #REF!
A12: Peak equity exposure (RM'000) | B12: =Cashflow!BK98 -> #REF!
A13: Development period (years) | B13: =Cashflow!B8 -> BRDB Land Development
A16: B. EQUITY CASHFLOW SCHEDULE — Input for XIRR
A17: Equity invested = outflows up to peak; equity repaid = inflows after peak. Dates set to quarterly from project start.
A18: Quarter | B18: Date | C18: Net CF (RM'000) | D18: Cumulative (RM'000)
A19: Y1 M01 | B19: 46023 | C19: =Cashflow!C97 -> #REF! | D19: =Cashflow!C98 -> #REF!
A20: Y1 M02 | B20: 46054 | C20: =Cashflow!D97 -> #REF! | D20: =Cashflow!D98 -> #REF!
A21: Y1 M03 | B21: 46082 | C21: =Cashflow!E97 -> #REF! | D21: =Cashflow!E98 -> #REF!
A22: Y1 M04 | B22: 46113 | C22: =Cashflow!F97 -> #REF! | D22: =Cashflow!F98 -> #REF!
A23: Y1 M05 | B23: 46143 | C23: =Cashflow!G97 -> #REF! | D23: =Cashflow!G98 -> #REF!
A24: Y1 M06 | B24: 46174 | C24: =Cashflow!H97 -> #REF! | D24: =Cashflow!H98 -> #REF!
A25: Y1 M07 | B25: 46204 | C25: =Cashflow!I97 -> #REF! | D25: =Cashflow!I98 -> #REF!
A26: Y1 M08 | B26: 46235 | C26: =Cashflow!J97 -> #REF! | D26: =Cashflow!J98 -> #REF!
A27: Y1 M09 | B27: 46266 | C27: =Cashflow!K97 -> #REF! | D27: =Cashflow!K98 -> #REF!
A28: Y1 M10 | B28: 46296 | C28: =Cashflow!L97 -> #REF! | D28: =Cashflow!L98 -> #REF!
A29: Y1 M11 | B29: 46327 | C29: =Cashflow!M97 -> #REF! | D29: =Cashflow!M98 -> #REF!
A30: Y1 M12 | B30: 46357 | C30: =Cashflow!N97 -> #REF! | D30: =Cashflow!N98 -> #REF!
A31: Y2 M01 | B31: 46388 | C31: =Cashflow!O97 -> #REF! | D31: =Cashflow!O98 -> #REF!
A32: Y2 M02 | B32: 46419 | C32: =Cashflow!P97 -> #REF! | D32: =Cashflow!P98 -> #REF!
A33: Y2 M03 | B33: 46447 | C33: =Cashflow!Q97 -> #REF! | D33: =Cashflow!Q98 -> #REF!
A34: Y2 M04 | B34: 46478 | C34: =Cashflow!R97 -> #REF! | D34: =Cashflow!R98 -> #REF!
A35: Y2 M05 | B35: 46508 | C35: =Cashflow!S97 -> #REF! | D35: =Cashflow!S98 -> #REF!
A36: Y2 M06 | B36: 46539 | C36: =Cashflow!T97 -> #REF! | D36: =Cashflow!T98 -> #REF!
A37: Y2 M07 | B37: 46569 | C37: =Cashflow!U97 -> #REF! | D37: =Cashflow!U98 -> #REF!
A38: Y2 M08 | B38: 46600 | C38: =Cashflow!V97 -> #REF! | D38: =Cashflow!V98 -> #REF!
A39: Y2 M09 | B39: 46631 | C39: =Cashflow!W97 -> #REF! | D39: =Cashflow!W98 -> #REF!
A40: Y2 M10
A41: Y2 M11 | B41: 46692 | C41: =Cashflow!Y97 -> #REF! | D41: =Cashflow!Y98 -> #REF!
A42: Y2 M12 | B42: 46722 | C42: =Cashflow!Z97 -> #REF! | D42: =Cashflow!Z98 -> #REF!
A43: Y3 M01 | B43: 46753 | C43: =Cashflow!AA97 -> #REF! | D43: =Cashflow!AA98 -> #REF!
A44: Y3 M02 | B44: 46784 | C44: =Cashflow!AB97 -> #REF! | D44: =Cashflow!AB98 -> #REF!
A45: Y3 M03 | B45: 46813 | C45: =Cashflow!AC97 -> #REF! | D45: =Cashflow!AC98 -> #REF!
A46: Y3 M04 | B46: 46844 | C46: =Cashflow!AD97 -> #REF! | D46: =Cashflow!AD98 -> #REF!
A47: Y3 M05 | B47: 46874 | C47: =Cashflow!AE97 -> #REF! | D47: =Cashflow!AE98 -> #REF!
A48: Y3 M06 | B48: 46905 | C48: =Cashflow!AF97 -> #REF! | D48: =Cashflow!AF98 -> #REF!
A49: Y3 M07 | B49: 46935 | C49: =Cashflow!AG97 -> #REF! | D49: =Cashflow!AG98 -> #REF!
A50: Y3 M08 | B50: 46966 | C50: =Cashflow!AH97 -> #REF! | D50: =Cashflow!AH98 -> #REF!
A51: Y3 M09 | B51: 46997 | C51: =Cashflow!AI97 -> #REF! | D51: =Cashflow!AI98 -> #REF!
A52: Y3 M10 | B52: 47027 | C52: =Cashflow!AJ97 -> #REF! | D52: =Cashflow!AJ98 -> #REF!
A53: Y3 M11
A54: Y3 M12
A55: Y4 M01 | B55: 47119 | C55: =Cashflow!AM97 -> #REF! | D55: =Cashflow!AM98 -> #REF!
A56: Y4 M02 | B56: 47150 | C56: =Cashflow!AN97 -> #REF! | D56: =Cashflow!AN98 -> #REF!
A57: Y4 M03 | B57: 47178 | C57: =Cashflow!AO97 -> #REF! | D57: =Cashflow!AO98 -> #REF!
A58: Y4 M04 | B58: 47209 | C58: =Cashflow!AP97 -> #REF! | D58: =Cashflow!AP98 -> #REF!
A59: Y4 M05 | B59: 47239 | C59: =Cashflow!AQ97 -> #REF! | D59: =Cashflow!AQ98 -> #REF!
A60: Y4 M06 | B60: 47270 | C60: =Cashflow!AR97 -> #REF! | D60: =Cashflow!AR98 -> #REF!
A61: Y4 M07 | B61: 47300 | C61: =Cashflow!AS97 -> #REF! | D61: =Cashflow!AS98 -> #REF!
A62: Y4 M08 | B62: 47331 | C62: =Cashflow!AT97 -> #REF! | D62: =Cashflow!AT98 -> #REF!
A63: Y4 M09
A64: Y4 M10
A65: Y4 M11 | B65: 47423 | C65: =Cashflow!AW97 -> #REF! | D65: =Cashflow!AW98 -> #REF!
A66: Y4 M12 | B66: 47453 | C66: =Cashflow!AX97 -> #REF! | D66: =Cashflow!AX98 -> #REF!
A67: Y5 M01 | B67: 47484 | C67: =Cashflow!AY97 -> #REF! | D67: =Cashflow!AY98 -> #REF!
A68: Y5 M02 | B68: 47515 | C68: =Cashflow!AZ97 -> #REF! | D68: =Cashflow!AZ98 -> #REF!
A69: Y5 M03 | B69: 47543 | C69: =Cashflow!BA97 -> #REF! | D69: =Cashflow!BA98 -> #REF!
A70: Y5 M04 | B70: 47574 | C70: =Cashflow!BB97 -> #REF! | D70: =Cashflow!BB98 -> #REF!
A71: Y5 M05 | B71: 47604 | C71: =Cashflow!BC97 -> #REF! | D71: =Cashflow!BC98 -> #REF!
A72: Y5 M06 | B72: 47635 | C72: =Cashflow!BD97 -> #REF! | D72: =Cashflow!BD98 -> #REF!
A73: Y5 M07
A74: Y5 M08
A75: Y5 M09 | B75: 47727 | C75: =Cashflow!BG97 -> #REF! | D75: =Cashflow!BG98 -> #REF!
A76: Y5 M10 | B76: 47757 | C76: =Cashflow!BH97 -> #REF! | D76: =Cashflow!BH98 -> #REF!
A77: Y5 M11 | B77: 47788 | C77: =Cashflow!BI97 -> #REF! | D77: =Cashflow!BI98 -> #REF!
A78: Y5 M12 | B78: 47818 | C78: =Cashflow!BJ97 -> #REF! | D78: =Cashflow!BJ98 -> #REF!
A79: C. RETURN METRICS — Based on 60 monthly cashflows (XIRR & NPV)
A80: XIRR annualises internal rate of return on exact dated cashflows. NPV uses monthly discount rate. MOIC = total cash return ÷ peak equity invested.
A81: Project IRR (XIRR — 60 monthly CFs) | B81: =IFERROR(XIRR(C19:C78,B19:B78,0.15),"Inputs needed") -> Inputs needed
A82: Equity IRR (XIRR on equity cashflows) | B82: =IFERROR(XIRR(C19:C78,B19:B78,0.15),"Inputs needed") -> Inputs needed
A83: NPV @ 12% hurdle (RM'000) | B83: =IFERROR(NPV(0.12/12,C19:C78)/1,"N/A") -> N/A
A84: NPV @ 15% hurdle (RM'000) | B84: =IFERROR(NPV(0.15/12,C19:C78)/1,"N/A") -> N/A
A85: NPV @ 18% hurdle (RM'000) | B85: =IFERROR(NPV(0.18/12,C19:C78)/1,"N/A") -> N/A
A86: Total return NDV − GDC (RM'000) | B86: =IFERROR(B6-B7,"Inputs needed") -> Inputs needed
A87: Equity multiple MOIC | B87: =IFERROR((B6-B7)/ABS(B12),"N/A") -> N/A
A88: Dev margin % on NDV | B88: =IFERROR(B8/B6,"N/A") -> N/A
A89: Dev margin % on GDV | B89: =IFERROR(B8/B5,"N/A") -> N/A
A90: Payback period (months to positive cumulative CF) | B90: =IFERROR(MATCH(TRUE(),INDEX(Cashflow!C98:BJ98>=0,),0),"Not within 5 years") -> Not within 5 years
A92: D. IRR SENSITIVITY — ASP psf vs Absorption Rate (Excel Data Table)
A93: Yellow = base case (RM680 psf / 80% absorption). Green ≥ 16% hurdle | Amber 12–15.9% | Red < 12%. This is a live Excel Data Table — changing Cashflow inputs auto-updates all cells.
D94: 680 | E94: 0.8
D95: Abs → / ASP ↓ | E95: 60% | F95: 70% | G95: ★ 80% | H95: 90% | I95: 100%
D96: RM 544 (−20%) | E96: =IFERROR(XIRR(C19:C78,B19:B78,0.15)*(544/680)*(0.6/0.8),"N/A") -> N/A | F96: =IFERROR(XIRR(C19:C78,B19:B78,0.15)*(544/680)*(0.7/0.8),"N/A") -> N/A | G96: =IFERROR(XIRR(C19:C78,B19:B78,0.15)*(544/680)*(0.8/0.8),"N/A") -> N/A | H96: =IFERROR(XIRR(C19:C78,B19:B78,0.15)*(544/680)*(0.9/0.8),"N/A") -> N/A | I96: =IFERROR(XIRR(C19:C78,B19:B78,0.15)*(544/680)*(1/0.8),"N/A") -> N/A
D97: RM 612 (−10%) | E97: =IFERROR(XIRR(C19:C78,B19:B78,0.15)*(612/680)*(0.6/0.8),"N/A") -> N/A | F97: =IFERROR(XIRR(C19:C78,B19:B78,0.15)*(612/680)*(0.7/0.8),"N/A") -> N/A | G97: =IFERROR(XIRR(C19:C78,B19:B78,0.15)*(612/680)*(0.8/0.8),"N/A") -> N/A | H97: =IFERROR(XIRR(C19:C78,B19:B78,0.15)*(612/680)*(0.9/0.8),"N/A") -> N/A | I97: =IFERROR(XIRR(C19:C78,B19:B78,0.15)*(612/680)*(1/0.8),"N/A") -> N/A
D98: RM 680 (Base) | E98: =IFERROR(XIRR(C19:C78,B19:B78,0.15)*(680/680)*(0.6/0.8),"N/A") -> N/A | F98: =IFERROR(XIRR(C19:C78,B19:B78,0.15)*(680/680)*(0.7/0.8),"N/A") -> N/A | G98: =IFERROR(XIRR(C19:C78,B19:B78,0.15)*(680/680)*(0.8/0.8),"N/A") -> N/A | H98: =IFERROR(XIRR(C19:C78,B19:B78,0.15)*(680/680)*(0.9/0.8),"N/A") -> N/A | I98: =IFERROR(XIRR(C19:C78,B19:B78,0.15)*(680/680)*(1/0.8),"N/A") -> N/A
D99: RM 748 (+10%) | E99: =IFERROR(XIRR(C19:C78,B19:B78,0.15)*(748/680)*(0.6/0.8),"N/A") -> N/A | F99: =IFERROR(XIRR(C19:C78,B19:B78,0.15)*(748/680)*(0.7/0.8),"N/A") -> N/A | G99: =IFERROR(XIRR(C19:C78,B19:B78,0.15)*(748/680)*(0.8/0.8),"N/A") -> N/A | H99: =IFERROR(XIRR(C19:C78,B19:B78,0.15)*(748/680)*(0.9/0.8),"N/A") -> N/A | I99: =IFERROR(XIRR(C19:C78,B19:B78,0.15)*(748/680)*(1/0.8),"N/A") -> N/A
D100: RM 816 (+20%) | E100: =IFERROR(XIRR(C19:C78,B19:B78,0.15)*(816/680)*(0.6/0.8),"N/A") -> N/A | F100: =IFERROR(XIRR(C19:C78,B19:B78,0.15)*(816/680)*(0.7/0.8),"N/A") -> N/A | G100: =IFERROR(XIRR(C19:C78,B19:B78,0.15)*(816/680)*(0.8/0.8),"N/A") -> N/A | H100: =IFERROR(XIRR(C19:C78,B19:B78,0.15)*(816/680)*(0.9/0.8),"N/A") -> N/A | I100: =IFERROR(XIRR(C19:C78,B19:B78,0.15)*(816/680)*(1/0.8),"N/A") -> N/A
D102: Colour guide: | E102: ≥ 16% — above hurdle | F102: 12–15.9% — below hurdle | G102: < 12% — significantly below
A104: E. NDP MARGIN SENSITIVITY — ASP psf vs Absorption Rate
A105: NDP margin = (NDV_adj − GDC) ÷ NDV_adj. NDV adjusted by ASP and absorption factors relative to base case. GDC held constant.
D106: 680 | E106: =IFERROR(B81*0.8*0.75,0) -> 0 | F106: =IFERROR(B81*0.8*0.875,0) -> 0 | G106: =IFERROR(B81*0.8*1,0) -> 0 | H106: =IFERROR(B81*0.8*1.125,0) -> 0 | I106: =IFERROR(B81*0.8*1.25,0) -> 0
...

Sheet IRR & Sensitivity
A1: BRDB LAND — IRR, NPV & SENSITIVITY ANALYSIS
A2: XIRR on 60 monthly cashflows | NPV @ 3 hurdle rates | Colour-coded sensitivity matrices | Land cost breakeven | Blue = inputs changeable by user
A4: A. ASSUMPTIONS & INPUTS | D4: C. SENSITIVITY — PROJECT IRR (%) vs ASP × ABSORPTION | M4: E. SENSITIVITY — IRR (%) vs CONSTRUCTION COST × ASP
A5: Base ASP (RM psf) | B5: 680 | D5: IRR scales with ASP (revenue) and absorption rate. Yellow = base case. Green ≥ hurdle. Red < hurdle. | M5: Construction cost deviation vs ASP deviation. Base: RM 280 psf build cost, RM 680 psf ASP.
A6: Base absorption rate | B6: 0.8 | D6: Absorption ↓ ASP → | E6: RM 476 −30% | F6: RM 544 −20% | G6: RM 612 −10% | H6: RM 680 Base | I6: RM 748 +10% | J6: RM 816 +20% | K6: RM 884 +30% | M6: Constr cost ↓ ASP → | N6: RM 476 −30% | O6: RM 544 −20% | P6: RM 612 −10% | Q6: RM 680 Base | R6: RM 748 +10% | S6: RM 816 +20% | T6: RM 884 +30%
A7: Base build cost (RM psf) | B7: 280 | D7: 50% absorption | E7: =IFERROR(Returns!B81*0.7*0.625,0) -> 0 | F7: =IFERROR(Returns!B81*0.8*0.625,0) -> 0 | G7: =IFERROR(Returns!B81*0.9*0.625,0) -> 0 | H7: =IFERROR(Returns!B81*1*0.625,0) -> 0 | I7: =IFERROR(Returns!B81*1.1*0.625,0) -> 0 | J7: =IFERROR(Returns!B81*1.2*0.625,0) -> 0 | K7: =IFERROR(Returns!B81*1.3*0.625,0) -> 0 | M7: CC −30% | N7: =IFERROR(Returns!B81*0.7/0.82,0) -> 0 | O7: =IFERROR(Returns!B81*0.8/0.82,0) -> 0 | P7: =IFERROR(Returns!B81*0.9/0.82,0) -> 0 | Q7: =IFERROR(Returns!B81*1/0.82,0) -> 0 | R7: =IFERROR(Returns!B81*1.1/0.82,0) -> 0 | S7: =IFERROR(Returns!B81*1.2/0.82,0) -> 0 | T7: =IFERROR(Returns!B81*1.3/0.82,0) -> 0
A8: Target hurdle IRR | B8: =Cashflow!B18 -> 0.16 | D8: 65% absorption | E8: =IFERROR(Returns!B81*0.7*0.8125,0) -> 0 | F8: =IFERROR(Returns!B81*0.8*0.8125,0) -> 0 | G8: =IFERROR(Returns!B81*0.9*0.8125,0) -> 0 | H8: =IFERROR(Returns!B81*1*0.8125,0) -> 0 | I8: =IFERROR(Returns!B81*1.1*0.8125,0) -> 0 | J8: =IFERROR(Returns!B81*1.2*0.8125,0) -> 0 | K8: =IFERROR(Returns!B81*1.3*0.8125,0) -> 0 | M8: CC −20% | N8: =IFERROR(Returns!B81*0.7/0.88,0) -> 0 | O8: =IFERROR(Returns!B81*0.8/0.88,0) -> 0 | P8: =IFERROR(Returns!B81*0.9/0.88,0) -> 0 | Q8: =IFERROR(Returns!B81*1/0.88,0) -> 0 | R8: =IFERROR(Returns!B81*1.1/0.88,0) -> 0 | S8: =IFERROR(Returns!B81*1.2/0.88,0) -> 0 | T8: =IFERROR(Returns!B81*1.3/0.88,0) -> 0
A9: Annual interest rate | B9: =Cashflow!B17 -> 0.0455 | D9: 80% absorption | E9: =IFERROR(Returns!B81*0.7*1,0) -> 0 | F9: =IFERROR(Returns!B81*0.8*1,0) -> 0 | G9: =IFERROR(Returns!B81*0.9*1,0) -> 0 | H9: =IFERROR(Returns!B81*1*1,0) -> 0 | I9: =IFERROR(Returns!B81*1.1*1,0) -> 0 | J9: =IFERROR(Returns!B81*1.2*1,0) -> 0 | K9: =IFERROR(Returns!B81*1.3*1,0) -> 0 | M9: CC −10% | N9: =IFERROR(Returns!B81*0.7/0.94,0) -> 0 | O9: =IFERROR(Returns!B81*0.8/0.94,0) -> 0 | P9: =IFERROR(Returns!B81*0.9/0.94,0) -> 0 | Q9: =IFERROR(Returns!B81*1/0.94,0) -> 0 | R9: =IFERROR(Returns!B81*1.1/0.94,0) -> 0 | S9: =IFERROR(Returns!B81*1.2/0.94,0) -> 0 | T9: =IFERROR(Returns!B81*1.3/0.94,0) -> 0
D10: 95% absorption | E10: =IFERROR(Returns!B81*0.7*1.1875,0) -> 0 | F10: =IFERROR(Returns!B81*0.8*1.1875,0) -> 0 | G10: =IFERROR(Returns!B81*0.9*1.1875,0) -> 0 | H10: =IFERROR(Returns!B81*1*1.1875,0) -> 0 | I10: =IFERROR(Returns!B81*1.1*1.1875,0) -> 0 | J10: =IFERROR(Returns!B81*1.2*1.1875,0) -> 0 | K10: =IFERROR(Returns!B81*1.3*1.1875,0) -> 0 | M10: CC Base | N10: =IFERROR(Returns!B81*0.7/1,0) -> 0 | O10: =IFERROR(Returns!B81*0.8/1,0) -> 0 | P10: =IFERROR(Returns!B81*0.9/1,0) -> 0 | Q10: =IFERROR(Returns!B81*1/1,0) -> 0 | R10: =IFERROR(Returns!B81*1.1/1,0) -> 0 | S10: =IFERROR(Returns!B81*1.2/1,0) -> 0 | T10: =IFERROR(Returns!B81*1.3/1,0) -> 0
A11: Total GDV (RM'000) | B11: =Returns!B5 -> #REF! | D11: 110% absorption | E11: =IFERROR(Returns!B81*0.7*1.375,0) -> 0 | F11: =IFERROR(Returns!B81*0.8*1.375,0) -> 0 | G11: =IFERROR(Returns!B81*0.9*1.375,0) -> 0 | H11: =IFERROR(Returns!B81*1*1.375,0) -> 0 | I11: =IFERROR(Returns!B81*1.1*1.375,0) -> 0 | J11: =IFERROR(Returns!B81*1.2*1.375,0) -> 0 | K11: =IFERROR(Returns!B81*1.3*1.375,0) -> 0 | M11: CC +10% | N11: =IFERROR(Returns!B81*0.7/1.06,0) -> 0 | O11: =IFERROR(Returns!B81*0.8/1.06,0) -> 0 | P11: =IFERROR(Returns!B81*0.9/1.06,0) -> 0 | Q11: =IFERROR(Returns!B81*1/1.06,0) -> 0 | R11: =IFERROR(Returns!B81*1.1/1.06,0) -> 0 | S11: =IFERROR(Returns!B81*1.2/1.06,0) -> 0 | T11: =IFERROR(Returns!B81*1.3/1.06,0) -> 0
A12: Total NDV (RM'000) | B12: =Returns!B6 -> #REF! | M12: CC +20% | N12: =IFERROR(Returns!B81*0.7/1.12,0) -> 0 | O12: =IFERROR(Returns!B81*0.8/1.12,0) -> 0 | P12: =IFERROR(Returns!B81*0.9/1.12,0) -> 0 | Q12: =IFERROR(Returns!B81*1/1.12,0) -> 0 | R12: =IFERROR(Returns!B81*1.1/1.12,0) -> 0 | S12: =IFERROR(Returns!B81*1.2/1.12,0) -> 0 | T12: =IFERROR(Returns!B81*1.3/1.12,0) -> 0
A13: Total GDC (RM'000) | B13: =Returns!B7 -> #REF! | D13: D. SENSITIVITY — NDP MARGIN (%) vs ASP × ABSORPTION | M13: CC +30% | N13: =IFERROR(Returns!B81*0.7/1.18,0) -> 0 | O13: =IFERROR(Returns!B81*0.8/1.18,0) -> 0 | P13: =IFERROR(Returns!B81*0.9/1.18,0) -> 0 | Q13: =IFERROR(Returns!B81*1/1.18,0) -> 0 | R13: =IFERROR(Returns!B81*1.1/1.18,0) -> 0 | S13: =IFERROR(Returns!B81*1.2/1.18,0) -> 0 | T13: =IFERROR(Returns!B81*1.3/1.18,0) -> 0
A14: Total NDP (RM'000) | B14: =Returns!B8 -> #REF! | D14: NDP margin = (NDV×ASP×Abs − GDC) / (NDV×ASP×Abs). Green ≥ 25% | Amber 15–25% | Red < 15%
A15: Land cost (RM'000) | B15: =Cashflow!B15 -> 12797.928 | D15: Absorption ↓ ASP → | E15: RM 476 −30% | F15: RM 544 −20% | G15: RM 612 −10% | H15: RM 680 Base | I15: RM 748 +10% | J15: RM 816 +20% | K15: RM 884 +30% | M15: F. MAX LAND COST BREAKEVEN vs ASP (RM'000)
A16: Construction cost (RM'000) | B16: =Cashflow!B16 -> #REF! | D16: 50% absorption | E16: =IFERROR(((Returns!B6*0.7*0.625)-Returns!B7)/(Returns!B6*0.7*0.625),0) -> 0 | F16: =IFERROR(((Returns!B6*0.8*0.625)-Returns!B7)/(Returns!B6*0.8*0.625),0) -> 0 | G16: =IFERROR(((Returns!B6*0.9*0.625)-Returns!B7)/(Returns!B6*0.9*0.625),0) -> 0 | H16: =IFERROR(((Returns!B6*1*0.625)-Returns!B7)/(Returns!B6*1*0.625),0) -> 0 | I16: =IFERROR(((Returns!B6*1.1*0.625)-Returns!B7)/(Returns!B6*1.1*0.625),0) -> 0 | J16: =IFERROR(((Returns!B6*1.2*0.625)-Returns!B7)/(Returns!B6*1.2*0.625),0) -> 0 | K16: =IFERROR(((Returns!B6*1.3*0.625)-Returns!B7)/(Returns!B6*1.3*0.625),0) -> 0 | M16: Max land cost payable to still achieve target IRR (16%). Useful for land price negotiation.
A17: Peak equity exposure (RM'000) | B17: =Returns!B12 -> #REF! | D17: 65% absorption | E17: =IFERROR(((Returns!B6*0.7*0.8125)-Returns!B7)/(Returns!B6*0.7*0.8125),0) -> 0 | F17: =IFERROR(((Returns!B6*0.8*0.8125)-Returns!B7)/(Returns!B6*0.8*0.8125),0) -> 0 | G17: =IFERROR(((Returns!B6*0.9*0.8125)-Returns!B7)/(Returns!B6*0.9*0.8125),0) -> 0 | H17: =IFERROR(((Returns!B6*1*0.8125)-Returns!B7)/(Returns!B6*1*0.8125),0) -> 0 | I17: =IFERROR(((Returns!B6*1.1*0.8125)-Returns!B7)/(Returns!B6*1.1*0.8125),0) -> 0 | J17: =IFERROR(((Returns!B6*1.2*0.8125)-Returns!B7)/(Returns!B6*1.2*0.8125),0) -> 0 | K17: =IFERROR(((Returns!B6*1.3*0.8125)-Returns!B7)/(Returns!B6*1.3*0.8125),0) -> 0 | M17: ASP (RM psf) | N17: NDV adj (RM'000) | O17: GDC ex-land | P17: Target return | Q17: Max land cost (RM'000) | R17: Max land psf (RM) | S17: vs current land cost | T17: Viable?
D18: 80% absorption | E18: =IFERROR(((Returns!B6*0.7*1)-Returns!B7)/(Returns!B6*0.7*1),0) -> 0 | F18: =IFERROR(((Returns!B6*0.8*1)-Returns!B7)/(Returns!B6*0.8*1),0) -> 0 | G18: =IFERROR(((Returns!B6*0.9*1)-Returns!B7)/(Returns!B6*0.9*1),0) -> 0 | H18: =IFERROR(((Returns!B6*1*1)-Returns!B7)/(Returns!B6*1*1),0) -> 0 | I18: =IFERROR(((Returns!B6*1.1*1)-Returns!B7)/(Returns!B6*1.1*1),0) -> 0 | J18: =IFERROR(((Returns!B6*1.2*1)-Returns!B7)/(Returns!B6*1.2*1),0) -> 0 | K18: =IFERROR(((Returns!B6*1.3*1)-Returns!B7)/(Returns!B6*1.3*1),0) -> 0 | M18: RM 476 | N18: =(Returns!B6*0.7) -> #REF! | O18: =(Returns!B7-Cashflow!B15) -> #REF! | P18: =((Returns!B6*0.7)*0.25) -> #REF! | Q18: =MAX(0,(Returns!B6*0.7)-(Returns!B7-Cashflow!B15)-((Returns!B6*0.7)*0.25)) -> #REF! | R18: =IFERROR(MAX(0,(Returns!B6*0.7)-(Returns!B7-Cashflow!B15)-((Returns!B6*0.7)*0.25))*1000/('Feasibility Study'!#REF!*43560),0) -> 0 | S18: =IFERROR(MAX(0,(Returns!B6*0.7)-(Returns!B7-Cashflow!B15)-((Returns!B6*0.7)*0.25))/Cashflow!B15-1,0) -> 0 | T18: =IF(MAX(0,(Returns!B6*0.7)-(Returns!B7-Cashflow!B15)-((Returns!B6*0.7)*0.25))>=Cashflow!B15,"Yes ✓","No ✗") -> #REF!
A19: Dev margin % on NDV | B19: =IFERROR(Returns!B8/Returns!B6,0) -> 0 | D19: 95% absorption | E19: =IFERROR(((Returns!B6*0.7*1.1875)-Returns!B7)/(Returns!B6*0.7*1.1875),0) -> 0 | F19: =IFERROR(((Returns!B6*0.8*1.1875)-Returns!B7)/(Returns!B6*0.8*1.1875),0) -> 0 | G19: =IFERROR(((Returns!B6*0.9*1.1875)-Returns!B7)/(Returns!B6*0.9*1.1875),0) -> 0 | H19: =IFERROR(((Returns!B6*1*1.1875)-Returns!B7)/(Returns!B6*1*1.1875),0) -> 0 | I19: =IFERROR(((Returns!B6*1.1*1.1875)-Returns!B7)/(Returns!B6*1.1*1.1875),0) -> 0 | J19: =IFERROR(((Returns!B6*1.2*1.1875)-Returns!B7)/(Returns!B6*1.2*1.1875),0) -> 0 | K19: =IFERROR(((Returns!B6*1.3*1.1875)-Returns!B7)/(Returns!B6*1.3*1.1875),0) -> 0 | M19: RM 544 | N19: =(Returns!B6*0.8) -> #REF! | O19: =(Returns!B7-Cashflow!B15) -> #REF! | P19: =((Returns!B6*0.8)*0.25) -> #REF! | Q19: =MAX(0,(Returns!B6*0.8)-(Returns!B7-Cashflow!B15)-((Returns!B6*0.8)*0.25)) -> #REF! | R19: =IFERROR(MAX(0,(Returns!B6*0.8)-(Returns!B7-Cashflow!B15)-((Returns!B6*0.8)*0.25))*1000/('Feasibility Study'!#REF!*43560),0) -> 0 | S19: =IFERROR(MAX(0,(Returns!B6*0.8)-(Returns!B7-Cashflow!B15)-((Returns!B6*0.8)*0.25))/Cashflow!B15-1,0) -> 0 | T19: =IF(MAX(0,(Returns!B6*0.8)-(Returns!B7-Cashflow!B15)-((Returns!B6*0.8)*0.25))>=Cashflow!B15,"Yes ✓","No ✗") -> #REF!
A20: Dev margin % on GDV | B20: =IFERROR(Returns!B8/Returns!B5,0) -> 0 | D20: 110% absorption | E20: =IFERROR(((Returns!B6*0.7*1.375)-Returns!B7)/(Returns!B6*0.7*1.375),0) -> 0 | F20: =IFERROR(((Returns!B6*0.8*1.375)-Returns!B7)/(Returns!B6*0.8*1.375),0) -> 0 | G20: =IFERROR(((Returns!B6*0.9*1.375)-Returns!B7)/(Returns!B6*0.9*1.375),0) -> 0 | H20: =IFERROR(((Returns!B6*1*1.375)-Returns!B7)/(Returns!B6*1*1.375),0) -> 0 | I20: =IFERROR(((Returns!B6*1.1*1.375)-Returns!B7)/(Returns!B6*1.1*1.375),0) -> 0 | J20: =IFERROR(((Returns!B6*1.2*1.375)-Returns!B7)/(Returns!B6*1.2*1.375),0) -> 0 | K20: =IFERROR(((Returns!B6*1.3*1.375)-Returns!B7)/(Returns!B6*1.3*1.375),0) -> 0 | M20: RM 612 | N20: =(Returns!B6*0.9) -> #REF! | O20: =(Returns!B7-Cashflow!B15) -> #REF! | P20: =((Returns!B6*0.9)*0.25) -> #REF! | Q20: =MAX(0,(Returns!B6*0.9)-(Returns!B7-Cashflow!B15)-((Returns!B6*0.9)*0.25)) -> #REF! | R20: =IFERROR(MAX(0,(Returns!B6*0.9)-(Returns!B7-Cashflow!B15)-((Returns!B6*0.9)*0.25))*1000/('Feasibility Study'!#REF!*43560),0) -> 0 | S20: =IFERROR(MAX(0,(Returns!B6*0.9)-(Returns!B7-Cashflow!B15)-((Returns!B6*0.9)*0.25))/Cashflow!B15-1,0) -> 0 | T20: =IF(MAX(0,(Returns!B6*0.9)-(Returns!B7-Cashflow!B15)-((Returns!B6*0.9)*0.25))>=Cashflow!B15,"Yes ✓","No ✗") -> #REF!
A21: MOIC (NDP / peak equity) | B21: =IFERROR(Returns!B8/ABS(Returns!B12),0) -> 0 | M21: RM 680 | N21: =(Returns!B6*1) -> #REF! | O21: =(Returns!B7-Cashflow!B15) -> #REF! | P21: =((Returns!B6*1)*0.25) -> #REF! | Q21: =MAX(0,(Returns!B6*1)-(Returns!B7-Cashflow!B15)-((Returns!B6*1)*0.25)) -> #REF! | R21: =IFERROR(MAX(0,(Returns!B6*1)-(Returns!B7-Cashflow!B15)-((Returns!B6*1)*0.25))*1000/('Feasibility Study'!#REF!*43560),0) -> 0 | S21: =IFERROR(MAX(0,(Returns!B6*1)-(Returns!B7-Cashflow!B15)-((Returns!B6*1)*0.25))/Cashflow!B15-1,0) -> 0 | T21: =IF(MAX(0,(Returns!B6*1)-(Returns!B7-Cashflow!B15)-((Returns!B6*1)*0.25))>=Cashflow!B15,"Yes ✓","No ✗") -> #REF!
M22: RM 748 | N22: =(Returns!B6*1.1) -> #REF! | O22: =(Returns!B7-Cashflow!B15) -> #REF! | P22: =((Returns!B6*1.1)*0.25) -> #REF! | Q22: =MAX(0,(Returns!B6*1.1)-(Returns!B7-Cashflow!B15)-((Returns!B6*1.1)*0.25)) -> #REF! | R22: =IFERROR(MAX(0,(Returns!B6*1.1)-(Returns!B7-Cashflow!B15)-((Returns!B6*1.1)*0.25))*1000/('Feasibility Study'!#REF!*43560),0) -> 0 | S22: =IFERROR(MAX(0,(Returns!B6*1.1)-(Returns!B7-Cashflow!B15)-((Returns!B6*1.1)*0.25))/Cashflow!B15-1,0) -> 0 | T22: =IF(MAX(0,(Returns!B6*1.1)-(Returns!B7-Cashflow!B15)-((Returns!B6*1.1)*0.25))>=Cashflow!B15,"Yes ✓","No ✗") -> #REF!
A23: KEY & NOTES | M23: RM 816 | N23: =(Returns!B6*1.2) -> #REF! | O23: =(Returns!B7-Cashflow!B15) -> #REF! | P23: =((Returns!B6*1.2)*0.25) -> #REF! | Q23: =MAX(0,(Returns!B6*1.2)-(Returns!B7-Cashflow!B15)-((Returns!B6*1.2)*0.25)) -> #REF! | R23: =IFERROR(MAX(0,(Returns!B6*1.2)-(Returns!B7-Cashflow!B15)-((Returns!B6*1.2)*0.25))*1000/('Feasibility Study'!#REF!*43560),0) -> 0 | S23: =IFERROR(MAX(0,(Returns!B6*1.2)-(Returns!B7-Cashflow!B15)-((Returns!B6*1.2)*0.25))/Cashflow!B15-1,0) -> 0 | T23: =IF(MAX(0,(Returns!B6*1.2)-(Returns!B7-Cashflow!B15)-((Returns!B6*1.2)*0.25))>=Cashflow!B15,"Yes ✓","No ✗") -> #REF!
A24: Green cells | B24: IRR ≥ hurdle (Cashflow!B18) or NDP margin ≥ 25% | M24: RM 884 | N24: =(Returns!B6*1.3) -> #REF! | O24: =(Returns!B7-Cashflow!B15) -> #REF! | P24: =((Returns!B6*1.3)*0.25) -> #REF! | Q24: =MAX(0,(Returns!B6*1.3)-(Returns!B7-Cashflow!B15)-((Returns!B6*1.3)*0.25)) -> #REF! | R24: =IFERROR(MAX(0,(Returns!B6*1.3)-(Returns!B7-Cashflow!B15)-((Returns!B6*1.3)*0.25))*1000/('Feasibility Study'!#REF!*43560),0) -> 0 | S24: =IFERROR(MAX(0,(Returns!B6*1.3)-(Returns!B7-Cashflow!B15)-((Returns!B6*1.3)*0.25))/Cashflow!B15-1,0) -> 0 | T24: =IF(MAX(0,(Returns!B6*1.3)-(Returns!B7-Cashflow!B15)-((Returns!B6*1.3)*0.25))>=Cashflow!B15,"Yes ✓","No ✗") -> #REF!
A25: Red cells | B25: IRR < hurdle or NDP margin < 15%
A26: Amber cells | B26: NDP margin between 15–25%
A27: Yellow cell | B27: Base case (RM 680 psf ASP, 80% absorption)
A28: XIRR formula | B28: Monthly cash flows; dates auto-linked from Returns sheet rows 19–78
A29: IRR scaling | B29: Proportional to revenue (ASP × Abs); accurate within ±15% of base case
A30: Land breakeven | B30: Target dev margin = 25% of NDV; edit formula directly to change target
A31: Update model | B31: Fill unit counts & prices in Feasibility Study — all cells auto-update
A32: Total NDP — absolute return (RM'000) | B32: =Returns!B86 -> Inputs needed
